Workbook

Sheet 1Tarifas Distribuidoras - INPUT
A1: Dados Distribuidora | M1: PONTA | R1: FORA PONTA | W1: ENCARGO
A2: Distribuidora | B2: Início de Vigência | C2: Fim de Vigência | D2: USO DA REDE PONTA | E2: USO DA REDE F. PONTA | F2: ENCARGO | G2: Encargo Auto Produtor | H2: Desconto Auto-Produção | I2: ICMS | J2: PIS | K2: COFINS | L2: PIS/COFINS Faturamento Distribuidora | M2: Valor Bruto Ponta | N2: Valor ICMS | O2: Valor PIS Ponta | P2: Valor COFINS Ponta | Q2: LIQUIDO SAP | R2: Valor Bruto Ponta | S2: Valor ICMS | T2: Valor PIS Ponta | U2: Valor COFINS Ponta | V2: LIQUIDO SAP | W2: Valor Bruto Ponta | X2: Valor ICMS | Y2: Valor PIS Ponta | Z2: Valor COFINS Ponta | AA2: LIQUIDO SAP
A3: ONS | B3: 45839 | C3: 46203 | D3: 7.099 | E3: 7.086 | F3: 66.52 | G3: 0 | H3: =F3-G3 -> 66.52 | I3: 0.18 | J3: 0.0165 | K3: 0.076 | L3: 0.08 | M3: =($D3/(1-$I3))/(1-$L3) -> 9.4101273 | N3: =M3*$I$3 -> 1.6938229 | O3: =M3*$J$3 -> 0.1552671 | P3: =M3*$K$3 -> 0.71516967 | Q3: =M3-O3-P3-N3 -> 6.8458676 | R3: =($E3/(1-$I3))/(1-$L3) -> 9.392895 | S3: =R3*$I3 -> 1.6907211 | T3: =R3*$J3 -> 0.15498277 | U3: =R3*$K3 -> 0.71386002 | V3: =R3-T3-U3-S3 -> 6.8333311 | W3: =($F3/(1-$I3))/(1-$L3) -> 88.176034 | X3: =W3*$I3 -> 15.871686 | Y3: =W3*$J3 -> 1.4549046 | Z3: =W3*$K3 -> 6.7013786 | AA3: =W3-Y3-Z3-X3 -> 64.148065
A4: ONS | B4: 46204 | C4: 46568 | D4: 7.78 | E4: 7.82 | F4: 60.66 | G4: 0 | H4: =F4-G4 -> 60.66 | I4: 0.18 | J4: 0.0165 | K4: 0.076 | L4: 0.08 | M4: =($D4/(1-I4))/(1-L4) -> 10.312831 | N4: =M4*I4 -> 1.8563097 | O4: =M4*J4 -> 0.17016172 | P4: =M4*K4 -> 0.78377519 | Q4: =M4-O4-P4-N4 -> 7.5025848 | R4: =($E4/(1-$I4))/(1-$L4) -> 10.365854 | S4: =R4*$I4 -> 1.8658537 | T4: =R4*$J4 -> 0.17103659 | U4: =R4*$K4 -> 0.78780488 | V4: =R4-T4-U4-S4 -> 7.5411585 | W4: =($F4/(1-$I4))/(1-$L4) -> 80.408271 | X4: =W4*$I4 -> 14.473489 | Y4: =W4*$J4 -> 1.3267365 | Z4: =W4*$K4 -> 6.1110286 | AA4: =W4-Y4-Z4-X4 -> 58.497017
A5: EDP | B5: 45870 | C5: 46234 | D5: 21.44 | E5: 9.83 | F5: 90.88 | G5: 13.33 | H5: =F5-G5 -> 77.55 | I5: 0.17 | J5: 0.0165 | K5: 0.076 | L5: 0.07 | M5: =($D5/(1-I5))/(1-L5) -> 27.775619 | N5: =M5*I5 -> 4.7218552 | O5: =M5*J5 -> 0.45829771 | P5: =M5*K5 -> 2.110947 | Q5: =M5-O5-P5-N5 -> 20.484519 | R5: =($E5/(1-$I5))/(1-$L5) -> 12.73481 | S5: =R5*$I5 -> 2.1649177 | T5: =R5*$J5 -> 0.21012437 | U5: =R5*$K5 -> 0.96784558 | V5: =R5-T5-U5-S5 -> 9.3919225 | W5: =($F5/(1-$I5))/(1-$L5) -> 117.73546 | X5: =W5*$I5 -> 20.015028 | Y5: =W5*$J5 -> 1.9426351 | Z5: =W5*$K5 -> 8.9478948 | AA5: =W5-Y5-Z5-X5 -> 86.8299
A6: EDP | B6: 46235 | C6: 46599 | D6: 21.056063 | E6: 8.941315 | F6: 87.09764 | G6: 8.4769741 | H6: =F6-G6 -> 78.620665 | I6: 0.17 | J6: 0.0165 | K6: 0.076 | L6: 0.07 | M6: =($D6/(1-I6))/(1-L6) -> 27.278227 | N6: =M6*I6 -> 4.6372985 | O6: =M6*J6 -> 0.45009074 | P6: =M6*K6 -> 2.0731452 | Q6: =M6-O6-P6-N6 -> 20.117692 | R6: =($E6/(1-$I6))/(1-$L6) -> 11.583515 | S6: =R6*$I6 -> 1.9691975 | T6: =R6*$J6 -> 0.19112799 | U6: =R6*$K6 -> 0.88034712 | V6: =R6-T6-U6-S6 -> 8.5428421 | W6: =($F6/(1-$I6))/(1-$L6) -> 112.83539 | X6: =W6*$I6 -> 19.182017 | Y6: =W6*$J6 -> 1.861784 | Z6: =W6*$K6 -> 8.5754898 | AA6: =W6-Y6-Z6-X6 -> 83.216102
A7: ENERGISA | B7: 45839 | C7: 46203 | D7: 15.96 | E7: 8.58 | F7: 83.19 | G7: 12.754801 | H7: =F7-G7 -> 70.435199 | I7: 0 | J7: 0.0165 | K7: 0.076 | L7: 0.07 | M7: =($D7/(1-I7))/(1-L7) -> 17.16129 | N7: =M7*I7 -> 0 | O7: =M7*J7 -> 0.28316129 | P7: =M7*K7 -> 1.3042581 | Q7: =M7-O7-P7-N7 -> 15.573871 | R7: =($E7/(1-$I7))/(1-$L7) -> 9.2258065 | S7: =R7*$I7 -> 0 | T7: =R7*$J7 -> 0.15222581 | U7: =R7*$K7 -> 0.70116129 | V7: =R7-T7-U7-S7 -> 8.3724194 | W7: =($F7/(1-$I7))/(1-$L7) -> 89.451613 | X7: =W7*$I7 -> 0 | Y7: =W7*$J7 -> 1.4759516 | Z7: =W7*$K7 -> 6.7983226 | AA7: =W7-Y7-Z7-X7 -> 81.177339
A8: ENERGISA | B8: 46204 | C8: 46568 | D8: 29.665248 | E8: 11.691942 | F8: 84.428166 | G8: 9.9877642 | H8: =F8-G8 -> 74.440402 | I8: 0 | J8: 0.0165 | K8: 0.076 | L8: 0.07 | M8: =($D8/(1-I8))/(1-L8) -> 31.898117 | N8: =M8*I8 -> 0 | O8: =M8*J8 -> 0.52631892 | P8: =M8*K8 -> 2.4242569 | Q8: =M8-O8-P8-N8 -> 28.947541 | R8: =($E8/(1-$I8))/(1-$L8) -> 12.571981 | S8: =R8*$I8 -> 0 | T8: =R8*$J8 -> 0.20743768 | U8: =R8*$K8 -> 0.95547052 | V8: =R8-T8-U8-S8 -> 11.409072 | W8: =($F8/(1-$I8))/(1-$L8) -> 90.782975 | X8: =W8*$I8 -> 0 | Y8: =W8*$J8 -> 1.4979191 | Z8: =W8*$K8 -> 6.8995061 | AA8: =W8-Y8-Z8-X8 -> 82.385549
M9: CALCULO
A10: Fornecedores de Energia - Mercado Livre
A11: Fornecedor | B11: Data Base | C11: Preço Base | D11: IPCA Realizado | E11: IPCA Projetado | F11: IPCA Total | G11: Preço | H11: Montante | I11: Valor Montante
A12: Cemig Convencional | B12: 44317 | C12: 142.59 | D12: 0.276 | E12: 0.0235 | F12: =D12+E12 -> 0.2995 | G12: =(C12)+(C12*F12) -> 185.2957 | H12: 80 | I12: =H12*G12 -> 14823.656
A13: Cemig Incentivada | B13: 45231 | C13: 152.88 | D13: 0.0874 | E13: 0.0199 | F13: =D13+E13 -> 0.1073 | G13: =(C13)+(C13*F13) -> 169.28402 | H13: 10 | I13: =H13*G13 -> 1692.8402
A14: Elera | B14: 45323 | C14: 159.2 | D14: 0.0679 | E14: 0.0196 | F14: =D14+E14 -> 0.0875 | G14: =(C14)+(C14*F14) -> 173.13 | H14: 20 | I14: =H14*G14 -> 3462.6
A15: Matrix | B15: 45383 | C15: 143.4 | D15: 0.0622 | E15: 0.0195 | F15: =D15+E15 -> 0.0817 | G15: =(C15)+(C15*F15) -> 155.11578 | H15: 20 | I15: =H15*G15 -> 3102.3156
I16: =SUM(I12:I15)/SUM(H12:H15) -> 177.54932
A18: Considerar que hdaverá um campo para cadastrar o valor do iPCA do mês de faturamento até o final do ano corrente, para projetar o custo do ano seguinte
A20: CALCULO
A21: Valor de Energia Por Estado | C21: ICMS | D21: PIS | E21: COFINS | F21: IPCA | G21: Valor Bruto | H21: Valor ICMS | I21: Valor PIS | J21: Valor Cofins | K21: LIQUIDO SAP
A22: MG | B22: =$I$16 -> 177.54932 | C22: 0.18 | D22: 0.0165 | E22: 0.076 | F22: 0.0216 | G22: =(B22/(1-F22))/(1-C22) -> 221.30373 | H22: =G22*C22 -> 39.834671 | I22: =G22*D22 -> 3.6515115 | J22: =G22*E22 -> 16.819083 | K22: =G22-I22-J22-H22 -> 160.99846
A23: ES | B23: =$I$16 -> 177.54932 | C23: 0.17 | D23: 0.0165 | E23: 0.076 | F23: 0.0216 | G23: =(B23/(1-F23))/(1-C23) -> 218.63742 | H23: =G23*C23 -> 37.168361 | I23: =G23*D23 -> 3.6075174 | J23: =G23*E23 -> 16.616444 | K23: =G23-I23-J23-H23 -> 161.2451
A25: Deverá haver cadastro de estados, informando para cada ano, o valor dos impostos de PIS/COFINS e ICMS. Deverá haver cadastro de unidades, e todas as unidades deverão ser cadastradas, incluvise as que geram energia. No cadastro de unidades, deverá indicar se é uma idade de produção de energia ou não. Quando não for uma unidade de produção de energia, deverá indicar se irá receber créditos de geração de energia, e deverá escolher sobre qual unidade receberá esses créditos. No cadastro de unidade, tambem deverá haver indicação se ela está conectada na rede de distribuição ou na rede basica

Sheet 2Tabela Tarifas Distribuidoras
A1: MG | E1: Janeiro Pjanejado | F1: Fevereiro Pjanejado | G1: Março Pjanejado | H1: Abril Pjanejado | I1: Maio Pjanejado | J1: Junho Pjanejado | K1: Julho Pjanejado | L1: Agosto Pjanejado | M1: Setembro Pjanejado | N1: Outubro Pjanejado | O1: Novembro Pjanejado | P1: Dezembro Pjanejado
A2: Unidade | B2: Serviço | C2: Horário/Encargo | D2: Centro de Custo
A3: Germano | B3: TUSD FIO / DEMANDA | C3: Ponta | D3: 50610003 | E3: ='1Tarifas Distribuidoras - INPUT'!$Q$3 -> 6.8458676 | F3: ='1Tarifas Distribuidoras - INPUT'!$Q$3 -> 6.8458676 | G3: ='1Tarifas Distribuidoras - INPUT'!$Q$3 -> 6.8458676 | H3: ='1Tarifas Distribuidoras - INPUT'!$Q$3 -> 6.8458676 | I3: ='1Tarifas Distribuidoras - INPUT'!$Q$3 -> 6.8458676 | J3: ='1Tarifas Distribuidoras - INPUT'!$Q$3 -> 6.8458676 | K3: ='1Tarifas Distribuidoras - INPUT'!$Q$4 -> 7.5025848 | L3: ='1Tarifas Distribuidoras - INPUT'!$Q$4 -> 7.5025848 | M3: ='1Tarifas Distribuidoras - INPUT'!$Q$4 -> 7.5025848 | N3: ='1Tarifas Distribuidoras - INPUT'!$Q$4 -> 7.5025848 | O3: ='1Tarifas Distribuidoras - INPUT'!$Q$4 -> 7.5025848 | P3: ='1Tarifas Distribuidoras - INPUT'!$Q$4 -> 7.5025848
A4: Germano | B4: TUSD FIO / DEMANDA | C4: Fora Ponta | D4: 50610003 | E4: ='1Tarifas Distribuidoras - INPUT'!$V$3 -> 6.8333311 | F4: ='1Tarifas Distribuidoras - INPUT'!$V$3 -> 6.8333311 | G4: ='1Tarifas Distribuidoras - INPUT'!$V$3 -> 6.8333311 | H4: ='1Tarifas Distribuidoras - INPUT'!$V$3 -> 6.8333311 | I4: ='1Tarifas Distribuidoras - INPUT'!$V$3 -> 6.8333311 | J4: ='1Tarifas Distribuidoras - INPUT'!$V$3 -> 6.8333311 | K4: ='1Tarifas Distribuidoras - INPUT'!$V$4 -> 7.5411585 | L4: ='1Tarifas Distribuidoras - INPUT'!$V$4 -> 7.5411585 | M4: ='1Tarifas Distribuidoras - INPUT'!$V$4 -> 7.5411585 | N4: ='1Tarifas Distribuidoras - INPUT'!$V$4 -> 7.5411585 | O4: ='1Tarifas Distribuidoras - INPUT'!$V$4 -> 7.5411585 | P4: ='1Tarifas Distribuidoras - INPUT'!$V$4 -> 7.5411585
A5: Germano | B5: TUSD ENCARGO | C5: Encargo Transmis | D5: 50610006 | E5: ='1Tarifas Distribuidoras - INPUT'!$AA$3 -> 64.148065 | F5: ='1Tarifas Distribuidoras - INPUT'!$AA$3 -> 64.148065 | G5: ='1Tarifas Distribuidoras - INPUT'!$AA$3 -> 64.148065 | H5: ='1Tarifas Distribuidoras - INPUT'!$AA$3 -> 64.148065 | I5: ='1Tarifas Distribuidoras - INPUT'!$AA$3 -> 64.148065 | J5: ='1Tarifas Distribuidoras - INPUT'!$AA$4 -> 58.497017 | K5: ='1Tarifas Distribuidoras - INPUT'!$AA$4 -> 58.497017 | L5: ='1Tarifas Distribuidoras - INPUT'!$AA$4 -> 58.497017 | M5: ='1Tarifas Distribuidoras - INPUT'!$AA$4 -> 58.497017 | N5: ='1Tarifas Distribuidoras - INPUT'!$AA$4 -> 58.497017 | O5: ='1Tarifas Distribuidoras - INPUT'!$AA$4 -> 58.497017 | P5: ='1Tarifas Distribuidoras - INPUT'!$AA$4 -> 58.497017
A6: Germano | B6: TUSD ENCARGO | C6: Desconto Enc. G.A. | D6: 50610006 | E6: ='1Tarifas Distribuidoras - INPUT'!$H$3 -> 66.52 | F6: ='1Tarifas Distribuidoras - INPUT'!$H$3 -> 66.52 | G6: ='1Tarifas Distribuidoras - INPUT'!$H$3 -> 66.52 | H6: ='1Tarifas Distribuidoras - INPUT'!$H$3 -> 66.52 | I6: ='1Tarifas Distribuidoras - INPUT'!$H$3 -> 66.52 | J6: ='1Tarifas Distribuidoras - INPUT'!$H$3 -> 66.52 | K6: ='1Tarifas Distribuidoras - INPUT'!$H$4 -> 60.66 | L6: ='1Tarifas Distribuidoras - INPUT'!$H$4 -> 60.66 | M6: ='1Tarifas Distribuidoras - INPUT'!$H$4 -> 60.66 | N6: ='1Tarifas Distribuidoras - INPUT'!$H$4 -> 60.66 | O6: ='1Tarifas Distribuidoras - INPUT'!$H$4 -> 60.66 | P6: ='1Tarifas Distribuidoras - INPUT'!$H$4 -> 60.66
A7: Germano | B7: TUSD ENCARGO | C7: Encargo Distribuição | D7: 50610006
A8: Matipó | B8: TUSD FIO / DEMANDA | C8: Ponta | D8: 50610003 | E8: ='1Tarifas Distribuidoras - INPUT'!$Q$7 -> 15.573871 | F8: ='1Tarifas Distribuidoras - INPUT'!$Q$7 -> 15.573871 | G8: ='1Tarifas Distribuidoras - INPUT'!$Q$7 -> 15.573871 | H8: ='1Tarifas Distribuidoras - INPUT'!$Q$7 -> 15.573871 | I8: ='1Tarifas Distribuidoras - INPUT'!$Q$7 -> 15.573871 | J8: ='1Tarifas Distribuidoras - INPUT'!$Q$7 -> 15.573871 | K8: ='1Tarifas Distribuidoras - INPUT'!$D$8 -> 29.665248 | L8: ='1Tarifas Distribuidoras - INPUT'!$D$8 -> 29.665248 | M8: ='1Tarifas Distribuidoras - INPUT'!$D$8 -> 29.665248 | N8: ='1Tarifas Distribuidoras - INPUT'!$D$8 -> 29.665248 | O8: ='1Tarifas Distribuidoras - INPUT'!$D$8 -> 29.665248 | P8: ='1Tarifas Distribuidoras - INPUT'!$D$8 -> 29.665248
A9: Matipó | B9: TUSD FIO / DEMANDA | C9: Fora Ponta | D9: 50610003 | E9: ='1Tarifas Distribuidoras - INPUT'!$V$7 -> 8.3724194 | F9: ='1Tarifas Distribuidoras - INPUT'!$V$7 -> 8.3724194 | G9: ='1Tarifas Distribuidoras - INPUT'!$V$7 -> 8.3724194 | H9: ='1Tarifas Distribuidoras - INPUT'!$V$7 -> 8.3724194 | I9: ='1Tarifas Distribuidoras - INPUT'!$V$7 -> 8.3724194 | J9: ='1Tarifas Distribuidoras - INPUT'!$V$7 -> 8.3724194 | K9: ='1Tarifas Distribuidoras - INPUT'!$E$8 -> 11.691942 | L9: ='1Tarifas Distribuidoras - INPUT'!$E$8 -> 11.691942 | M9: ='1Tarifas Distribuidoras - INPUT'!$E$8 -> 11.691942 | N9: ='1Tarifas Distribuidoras - INPUT'!$E$8 -> 11.691942 | O9: ='1Tarifas Distribuidoras - INPUT'!$E$8 -> 11.691942 | P9: ='1Tarifas Distribuidoras - INPUT'!$E$8 -> 11.691942
A10: Matipó | B10: TUSD ENCARGO | C10: Encargo Transmis | D10: 50610006
A11: Matipó | B11: TUSD ENCARGO | C11: Desconto Enc. G.A. | D11: 50610006
A12: Matipó | B12: TUSD ENCARGO | C12: Encargo Distribuição | D12: 50610006 | E12: ='1Tarifas Distribuidoras - INPUT'!$AA$7 -> 81.177339 | F12: ='1Tarifas Distribuidoras - INPUT'!$AA$7 -> 81.177339 | G12: ='1Tarifas Distribuidoras - INPUT'!$AA$7 -> 81.177339 | H12: ='1Tarifas Distribuidoras - INPUT'!$AA$7 -> 81.177339 | I12: ='1Tarifas Distribuidoras - INPUT'!$AA$7 -> 81.177339 | J12: ='1Tarifas Distribuidoras - INPUT'!$AA$7 -> 81.177339 | K12: ='1Tarifas Distribuidoras - INPUT'!$AA$8 -> 82.385549 | L12: ='1Tarifas Distribuidoras - INPUT'!$AA$8 -> 82.385549 | M12: ='1Tarifas Distribuidoras - INPUT'!$AA$8 -> 82.385549 | N12: ='1Tarifas Distribuidoras - INPUT'!$AA$8 -> 82.385549 | O12: ='1Tarifas Distribuidoras - INPUT'!$AA$8 -> 82.385549 | P12: ='1Tarifas Distribuidoras - INPUT'!$AA$8 -> 82.385549
A13: MG | B13: Consumo de Energia | C13: PMIX | D13: 50610002 | E13: ='1Tarifas Distribuidoras - INPUT'!$K$22 -> 160.99846 | F13: ='1Tarifas Distribuidoras - INPUT'!$K$22 -> 160.99846 | G13: ='1Tarifas Distribuidoras - INPUT'!$K$22 -> 160.99846 | H13: ='1Tarifas Distribuidoras - INPUT'!$K$22 -> 160.99846 | I13: ='1Tarifas Distribuidoras - INPUT'!$K$22 -> 160.99846 | J13: ='1Tarifas Distribuidoras - INPUT'!$K$22 -> 160.99846 | K13: ='1Tarifas Distribuidoras - INPUT'!$K$22 -> 160.99846 | L13: ='1Tarifas Distribuidoras - INPUT'!$K$22 -> 160.99846 | ... P13: ='1Tarifas Distribuidoras - INPUT'!$K$22 -> 160.99846
A15: ES | E15: Janeiro Pjanejado | F15: Fevereiro Pjanejado | G15: Março Pjanejado | H15: Abril Pjanejado | I15: Maio Pjanejado | J15: Junho Pjanejado | K15: Julho Pjanejado | L15: Agosto Pjanejado | M15: Setembro Pjanejado | N15: Outubro Pjanejado | O15: Novembro Pjanejado | P15: Dezembro Pjanejado
A16: Unidade | B16: Serviço | C16: Horário/Encargo | D16: Centro de Custo
A17: UBU | B17: TUSD FIO / DEMANDA | C17: Ponta | D17: 50610003 | E17: ='1Tarifas Distribuidoras - INPUT'!$Q$5 -> 20.484519 | F17: ='1Tarifas Distribuidoras - INPUT'!$Q$5 -> 20.484519 | G17: ='1Tarifas Distribuidoras - INPUT'!$Q$5 -> 20.484519 | H17: ='1Tarifas Distribuidoras - INPUT'!$Q$5 -> 20.484519 | I17: ='1Tarifas Distribuidoras - INPUT'!$Q$5 -> 20.484519 | J17: ='1Tarifas Distribuidoras - INPUT'!$Q$5 -> 20.484519 | K17: ='1Tarifas Distribuidoras - INPUT'!$Q$5 -> 20.484519 | L17: ='1Tarifas Distribuidoras - INPUT'!$Q$6 -> 20.117692 | M17: ='1Tarifas Distribuidoras - INPUT'!$Q$6 -> 20.117692 | N17: ='1Tarifas Distribuidoras - INPUT'!$Q$6 -> 20.117692 | O17: ='1Tarifas Distribuidoras - INPUT'!$Q$6 -> 20.117692 | P17: ='1Tarifas Distribuidoras - INPUT'!$Q$6 -> 20.117692
A18: UBU | B18: TUSD FIO / DEMANDA | C18: Fora Ponta | D18: 50610003 | E18: ='1Tarifas Distribuidoras - INPUT'!$V$7 -> 8.3724194 | F18: ='1Tarifas Distribuidoras - INPUT'!$V$7 -> 8.3724194 | G18: ='1Tarifas Distribuidoras - INPUT'!$V$7 -> 8.3724194 | H18: ='1Tarifas Distribuidoras - INPUT'!$V$7 -> 8.3724194 | I18: ='1Tarifas Distribuidoras - INPUT'!$V$7 -> 8.3724194 | J18: ='1Tarifas Distribuidoras - INPUT'!$V$7 -> 8.3724194 | K18: ='1Tarifas Distribuidoras - INPUT'!$E$8 -> 11.691942 | L18: ='1Tarifas Distribuidoras - INPUT'!$V$6 -> 8.5428421 | M18: ='1Tarifas Distribuidoras - INPUT'!$V$6 -> 8.5428421 | N18: ='1Tarifas Distribuidoras - INPUT'!$V$6 -> 8.5428421 | O18: ='1Tarifas Distribuidoras - INPUT'!$V$6 -> 8.5428421 | P18: ='1Tarifas Distribuidoras - INPUT'!$V$6 -> 8.5428421
A19: UBU | B19: TUSD ENCARGO | C19: Encargo Transmis | D19: 50610006
A20: UBU | B20: TUSD ENCARGO | C20: Desconto Enc. G.A. | D20: 50610006 | E20: ='1Tarifas Distribuidoras - INPUT'!$H$5 -> 77.55 | F20: ='1Tarifas Distribuidoras - INPUT'!$H$5 -> 77.55 | G20: ='1Tarifas Distribuidoras - INPUT'!$H$5 -> 77.55 | H20: ='1Tarifas Distribuidoras - INPUT'!$H$5 -> 77.55 | I20: ='1Tarifas Distribuidoras - INPUT'!$H$5 -> 77.55 | J20: ='1Tarifas Distribuidoras - INPUT'!$H$5 -> 77.55 | K20: ='1Tarifas Distribuidoras - INPUT'!$H$5 -> 77.55 | L20: ='1Tarifas Distribuidoras - INPUT'!$H$6 -> 78.620665 | M20: ='1Tarifas Distribuidoras - INPUT'!$H$6 -> 78.620665 | N20: ='1Tarifas Distribuidoras - INPUT'!$H$6 -> 78.620665 | O20: ='1Tarifas Distribuidoras - INPUT'!$H$6 -> 78.620665 | P20: ='1Tarifas Distribuidoras - INPUT'!$H$6 -> 78.620665
A21: UBU | B21: TUSD ENCARGO | C21: Encargo Distribuição | D21: 50610006 | E21: ='1Tarifas Distribuidoras - INPUT'!$AA$5 -> 86.8299 | F21: ='1Tarifas Distribuidoras - INPUT'!$AA$5 -> 86.8299 | G21: ='1Tarifas Distribuidoras - INPUT'!$AA$5 -> 86.8299 | H21: ='1Tarifas Distribuidoras - INPUT'!$AA$5 -> 86.8299 | I21: ='1Tarifas Distribuidoras - INPUT'!$AA$5 -> 86.8299 | J21: ='1Tarifas Distribuidoras - INPUT'!$AA$5 -> 86.8299 | K21: ='1Tarifas Distribuidoras - INPUT'!$AA$5 -> 86.8299 | L21: ='1Tarifas Distribuidoras - INPUT'!$AA$6 -> 83.216102 | M21: ='1Tarifas Distribuidoras - INPUT'!$AA$6 -> 83.216102 | N21: ='1Tarifas Distribuidoras - INPUT'!$AA$6 -> 83.216102 | O21: ='1Tarifas Distribuidoras - INPUT'!$AA$6 -> 83.216102 | P21: ='1Tarifas Distribuidoras - INPUT'!$AA$6 -> 83.216102
A22: ES | B22: Consumo de Energia | C22: PMIX | D22: 50610002 | E22: ='1Tarifas Distribuidoras - INPUT'!$K$23 -> 161.2451 | F22: ='1Tarifas Distribuidoras - INPUT'!$K$23 -> 161.2451 | G22: ='1Tarifas Distribuidoras - INPUT'!$K$23 -> 161.2451 | H22: ='1Tarifas Distribuidoras - INPUT'!$K$23 -> 161.2451 | I22: ='1Tarifas Distribuidoras - INPUT'!$K$23 -> 161.2451 | J22: ='1Tarifas Distribuidoras - INPUT'!$K$23 -> 161.2451 | K22: ='1Tarifas Distribuidoras - INPUT'!$K$23 -> 161.2451 | L22: ='1Tarifas Distribuidoras - INPUT'!$K$23 -> 161.2451 | ... P22: ='1Tarifas Distribuidoras - INPUT'!$K$23 -> 161.2451

Sheet 3Planejamento Produção - INPUT
A1: Volumes (ktms) - Planejado | B1: Jan | C1: Fev | D1: Mar | E1: Abr | F1: Mai | G1: Jun | H1: Jul | I1: Ago | J1: Set | K1: Out | L1: Nov | M1: Dez
A2: Aréa | B2: M1 | C2: M2 | D2: M3 | E2: M4 | F2: M5 | G2: M6 | H2: M7 | I2: M8 | J2: M9 | K2: M10 | L2: M11 | M2: M12
B3: 31 | C3: 28 | D3: 31 | E3: 30 | F3: 31 | G3: 30 | H3: 31 | I3: 31 | J3: 30 | K3: 31 | L3: 30 | M3: 31
A4: Filtragem Germano (Arenoso) | B4: 1059.0685 | C4: 1021.032 | D4: 1004.4547 | E4: 1119.82 | F4: 1137.3517 | G4: 1148.2279 | H4: 1188.5718 | I4: 1138.5113 | J4: 1149.783 | K4: 1159.5339 | L4: 1051.4634 | M4: 1120.4827
A5: Beneficiamento Usina 1 | B5: 0 | C5: 0 | D5: 0 | E5: 0 | F5: 0 | G5: 0 | H5: 0 | I5: 0 | J5: 0 | K5: 0 | L5: 0 | M5: 0
A6: Beneficiamento Usina 2 | B6: 599.77701 | C6: 546.47305 | D6: 576.60359 | E6: 565.60741 | F6: 584.42848 | G6: 619.56526 | H6: 641.88963 | I6: 641.70219 | J6: 624.34908 | K6: 611.98334 | L6: 525.62356 | M6: 585.60584
A7: Beneficiamento Usina 3 | B7: 660.81339 | C7: 683.62185 | D7: 680.47395 | E7: 806.83856 | F7: 828.46327 | G7: 802.19253 | H7: 822.42659 | I7: 751.43493 | J7: 793.45275 | K7: 794.81849 | L7: 734.24252 | M7: 726.84026
A8: Mineroduto 1 | B8: 0 | C8: 0 | D8: 0 | E8: 0 | F8: 0 | G8: 0 | H8: 0 | I8: 0 | J8: 0 | K8: 0 | L8: 0 | M8: 0
A9: Mineroduto 2 | B9: 0 | C9: 0 | D9: 0 | E9: 0 | F9: 0 | G9: 0 | H9: 0 | I9: 0 | J9: 0 | K9: 0 | L9: 0 | M9: 0
A10: Mineroduto 3 | B10: 1260.5904 | C10: 1230.0949 | D10: =1053.1452909432+203.932249053542 -> 1257.0775 | E10: 1372.446 | F10: 1412.8918 | G10: 1421.7578 | H10: 1464.3162 | I10: 1393.1371 | J10: 1417.8018 | K10: 1406.8018 | L10: 1259.8661 | M10: 1312.4461
A11: Preparação 1 | B11: 0 | C11: 0 | D11: 0 | E11: 0 | F11: 0 | G11: 0 | H11: 0 | I11: 0 | J11: 0 | K11: 0 | L11: 0 | M11: 0
A12: Preparação 2 | B12: 1260.5904 | C12: 1230.0949 | D12: 1257.0775 | E12: 1372.446 | F12: 1412.8918 | G12: 1421.7578 | H12: 1464.3162 | I12: 1393.1371 | J12: 1417.8018 | K12: 1406.8018 | L12: 1259.8661 | M12: 1312.4461
A13: Usina 1 | B13: 0 | C13: 0 | D13: 0 | E13: 0 | F13: 0 | G13: 0 | H13: 0 | I13: 0 | J13: 0 | K13: 0 | L13: 0 | M13: 0
A14: Usina 2 | B14: 0 | C14: 0 | D14: 0 | E14: 0 | F14: 0 | G14: 0 | H14: 0 | I14: 0 | J14: 0 | K14: 0 | L14: 0 | M14: 0
A15: Usina 3 | B15: 474.39089 | C15: 457.31995 | D15: 385.05165 | E15: 522.00976 | F15: 527.21094 | G15: 532.46778 | H15: 560.31596 | I15: 527.28544 | J15: 523.74398 | K15: 536.10451 | L15: 471.71974 | M15: 488.46413
A16: Usina 4 | B16: 592.83754 | C16: 551.3311 | D16: 678.84305 | E16: 651.57415 | F16: 637.68127 | G16: 687.99477 | H16: 700.10889 | I16: 636.35485 | J16: 675.2507 | K16: 669.7878 | L16: 565.4284 | M16: 628.82557
A17: Vendas | B17: 1067.2284 | C17: 1008.651 | D17: 1063.8947 | E17: 1173.5839 | F17: 1164.8922 | G17: 1220.4626 | H17: 1260.4248 | I17: 1163.6403 | J17: 1198.9947 | K17: 1205.8923 | L17: 1037.1481 | M17: 1117.2897
A18: Produção PSC + PSM | B18: 143.85506 | C18: 174.65286 | D18: 143.82505 | E18: 144.81226 | F18: 193.95903 | G18: 145.23416 | H18: 145.59382 | I18: 176.04776 | J18: 162.94095 | K18: 145.10303 | L18: 174.90933 | M18: 144.30561
A19: Pellet Feed (embarque) | B19: 385.92688 | C19: 385.92688 | D19: 385.92688 | E19: 385.92688 | F19: 385.92688 | G19: 385.92688 | H19: 385.92688 | I19: 385.92688 | J19: 385.92688 | K19: 385.92688 | L19: 385.92688 | M19: 385.92688
A21: Os dados dessa planilha são todos imputados por cada área. Assim, alguém de área de produção deverá cadastrar todos os dados presentees nessa planilha.

Sheet 4Produção - OCULTA
B1: Produção por mês em tms ( tonelada métrica seca)
A2: Área | B2: Jan | C2: Fev | D2: Mar | E2: Abr | F2: Mai | G2: Jun | H2: Jul | I2: Ago | J2: Set | K2: Out | L2: Nov | M2: Dez
A3: Filtragem Germano (Arenoso) | B3: ='3Planejamento Produção - INPUT'!B4*$B$20 -> 1059068.5 | C3: ='3Planejamento Produção - INPUT'!C4*$B$20 -> 1021032 | D3: ='3Planejamento Produção - INPUT'!D4*$B$20 -> 1004454.7 | E3: ='3Planejamento Produção - INPUT'!E4*$B$20 -> 1119820 | F3: ='3Planejamento Produção - INPUT'!F4*$B$20 -> 1137351.7 | G3: ='3Planejamento Produção - INPUT'!G4*$B$20 -> 1148227.9 | H3: ='3Planejamento Produção - INPUT'!H4*$B$20 -> 1188571.8 | I3: ='3Planejamento Produção - INPUT'!I4*$B$20 -> 1138511.3 | ... M3: ='3Planejamento Produção - INPUT'!M4*$B$20 -> 1120482.7
A4: Beneficiamento Usina 1 | B4: ='3Planejamento Produção - INPUT'!B5*$B$20 -> 0 | C4: ='3Planejamento Produção - INPUT'!C5*$B$20 -> 0 | D4: ='3Planejamento Produção - INPUT'!D5*$B$20 -> 0 | E4: ='3Planejamento Produção - INPUT'!E5*$B$20 -> 0 | F4: ='3Planejamento Produção - INPUT'!F5*$B$20 -> 0 | G4: ='3Planejamento Produção - INPUT'!G5*$B$20 -> 0 | H4: ='3Planejamento Produção - INPUT'!H5*$B$20 -> 0 | I4: ='3Planejamento Produção - INPUT'!I5*$B$20 -> 0 | ... M4: ='3Planejamento Produção - INPUT'!M5*$B$20 -> 0
A5: Beneficiamento Usina 2 | B5: ='3Planejamento Produção - INPUT'!B6*$B$20 -> 599777.01 | C5: ='3Planejamento Produção - INPUT'!C6*$B$20 -> 546473.05 | D5: ='3Planejamento Produção - INPUT'!D6*$B$20 -> 576603.59 | E5: ='3Planejamento Produção - INPUT'!E6*$B$20 -> 565607.41 | F5: ='3Planejamento Produção - INPUT'!F6*$B$20 -> 584428.48 | G5: ='3Planejamento Produção - INPUT'!G6*$B$20 -> 619565.26 | H5: ='3Planejamento Produção - INPUT'!H6*$B$20 -> 641889.63 | I5: ='3Planejamento Produção - INPUT'!I6*$B$20 -> 641702.19 | ... M5: ='3Planejamento Produção - INPUT'!M6*$B$20 -> 585605.84
A6: Beneficiamento Usina 3 | B6: ='3Planejamento Produção - INPUT'!B7*$B$20 -> 660813.39 | C6: ='3Planejamento Produção - INPUT'!C7*$B$20 -> 683621.85 | D6: ='3Planejamento Produção - INPUT'!D7*$B$20 -> 680473.95 | E6: ='3Planejamento Produção - INPUT'!E7*$B$20 -> 806838.56 | F6: ='3Planejamento Produção - INPUT'!F7*$B$20 -> 828463.27 | G6: ='3Planejamento Produção - INPUT'!G7*$B$20 -> 802192.53 | H6: ='3Planejamento Produção - INPUT'!H7*$B$20 -> 822426.59 | I6: ='3Planejamento Produção - INPUT'!I7*$B$20 -> 751434.93 | ... M6: ='3Planejamento Produção - INPUT'!M7*$B$20 -> 726840.26
A7: Mineroduto 1 | B7: ='3Planejamento Produção - INPUT'!B8*$B$20 -> 0 | C7: ='3Planejamento Produção - INPUT'!C8*$B$20 -> 0 | D7: ='3Planejamento Produção - INPUT'!D8*$B$20 -> 0 | E7: ='3Planejamento Produção - INPUT'!E8*$B$20 -> 0 | F7: ='3Planejamento Produção - INPUT'!F8*$B$20 -> 0 | G7: ='3Planejamento Produção - INPUT'!G8*$B$20 -> 0 | H7: ='3Planejamento Produção - INPUT'!H8*$B$20 -> 0 | I7: ='3Planejamento Produção - INPUT'!I8*$B$20 -> 0 | ... M7: ='3Planejamento Produção - INPUT'!M8*$B$20 -> 0
A8: Mineroduto 2 | B8: ='3Planejamento Produção - INPUT'!B9*$B$20 -> 0 | C8: ='3Planejamento Produção - INPUT'!C9*$B$20 -> 0 | D8: ='3Planejamento Produção - INPUT'!D9*$B$20 -> 0 | E8: ='3Planejamento Produção - INPUT'!E9*$B$20 -> 0 | F8: ='3Planejamento Produção - INPUT'!F9*$B$20 -> 0 | G8: ='3Planejamento Produção - INPUT'!G9*$B$20 -> 0 | H8: ='3Planejamento Produção - INPUT'!H9*$B$20 -> 0 | I8: ='3Planejamento Produção - INPUT'!I9*$B$20 -> 0 | ... M8: ='3Planejamento Produção - INPUT'!M9*$B$20 -> 0
A9: Mineroduto 3 | B9: ='3Planejamento Produção - INPUT'!B10*$B$20 -> 1260590.4 | C9: ='3Planejamento Produção - INPUT'!C10*$B$20 -> 1230094.9 | D9: ='3Planejamento Produção - INPUT'!D10*$B$20 -> 1257077.5 | E9: ='3Planejamento Produção - INPUT'!E10*$B$20 -> 1372446 | F9: ='3Planejamento Produção - INPUT'!F10*$B$20 -> 1412891.8 | G9: ='3Planejamento Produção - INPUT'!G10*$B$20 -> 1421757.8 | H9: ='3Planejamento Produção - INPUT'!H10*$B$20 -> 1464316.2 | I9: ='3Planejamento Produção - INPUT'!I10*$B$20 -> 1393137.1 | ... M9: ='3Planejamento Produção - INPUT'!M10*$B$20 -> 1312446.1
A10: Preparação 1 | B10: ='3Planejamento Produção - INPUT'!B11*$B$20 -> 0 | C10: ='3Planejamento Produção - INPUT'!C11*$B$20 -> 0 | D10: ='3Planejamento Produção - INPUT'!D11*$B$20 -> 0 | E10: ='3Planejamento Produção - INPUT'!E11*$B$20 -> 0 | F10: ='3Planejamento Produção - INPUT'!F11*$B$20 -> 0 | G10: ='3Planejamento Produção - INPUT'!G11*$B$20 -> 0 | H10: ='3Planejamento Produção - INPUT'!H11*$B$20 -> 0 | I10: ='3Planejamento Produção - INPUT'!I11*$B$20 -> 0 | ... M10: ='3Planejamento Produção - INPUT'!M11*$B$20 -> 0
A11: Preparação 2 | B11: ='3Planejamento Produção - INPUT'!B12*$B$20 -> 1260590.4 | C11: ='3Planejamento Produção - INPUT'!C12*$B$20 -> 1230094.9 | D11: ='3Planejamento Produção - INPUT'!D12*$B$20 -> 1257077.5 | E11: ='3Planejamento Produção - INPUT'!E12*$B$20 -> 1372446 | F11: ='3Planejamento Produção - INPUT'!F12*$B$20 -> 1412891.8 | G11: ='3Planejamento Produção - INPUT'!G12*$B$20 -> 1421757.8 | H11: ='3Planejamento Produção - INPUT'!H12*$B$20 -> 1464316.2 | I11: ='3Planejamento Produção - INPUT'!I12*$B$20 -> 1393137.1 | ... M11: ='3Planejamento Produção - INPUT'!M12*$B$20 -> 1312446.1
A12: Usina 1 | B12: ='3Planejamento Produção - INPUT'!B13*$B$20 -> 0 | C12: ='3Planejamento Produção - INPUT'!C13*$B$20 -> 0 | D12: ='3Planejamento Produção - INPUT'!D13*$B$20 -> 0 | E12: ='3Planejamento Produção - INPUT'!E13*$B$20 -> 0 | F12: ='3Planejamento Produção - INPUT'!F13*$B$20 -> 0 | G12: ='3Planejamento Produção - INPUT'!G13*$B$20 -> 0 | H12: ='3Planejamento Produção - INPUT'!H13*$B$20 -> 0 | I12: ='3Planejamento Produção - INPUT'!I13*$B$20 -> 0 | ... M12: ='3Planejamento Produção - INPUT'!M13*$B$20 -> 0
A13: Usina 2 | B13: ='3Planejamento Produção - INPUT'!B14*$B$20 -> 0 | C13: ='3Planejamento Produção - INPUT'!C14*$B$20 -> 0 | D13: ='3Planejamento Produção - INPUT'!D14*$B$20 -> 0 | E13: ='3Planejamento Produção - INPUT'!E14*$B$20 -> 0 | F13: ='3Planejamento Produção - INPUT'!F14*$B$20 -> 0 | G13: ='3Planejamento Produção - INPUT'!G14*$B$20 -> 0 | H13: ='3Planejamento Produção - INPUT'!H14*$B$20 -> 0 | I13: ='3Planejamento Produção - INPUT'!I14*$B$20 -> 0 | ... M13: ='3Planejamento Produção - INPUT'!M14*$B$20 -> 0
A14: Usina 3 | B14: ='3Planejamento Produção - INPUT'!B15*$B$20 -> 474390.89 | C14: ='3Planejamento Produção - INPUT'!C15*$B$20 -> 457319.95 | D14: ='3Planejamento Produção - INPUT'!D15*$B$20 -> 385051.65 | E14: ='3Planejamento Produção - INPUT'!E15*$B$20 -> 522009.76 | F14: ='3Planejamento Produção - INPUT'!F15*$B$20 -> 527210.94 | G14: ='3Planejamento Produção - INPUT'!G15*$B$20 -> 532467.78 | H14: ='3Planejamento Produção - INPUT'!H15*$B$20 -> 560315.96 | I14: ='3Planejamento Produção - INPUT'!I15*$B$20 -> 527285.44 | ... M14: ='3Planejamento Produção - INPUT'!M15*$B$20 -> 488464.13
... A18: Pellet Feed (embarque) | B18: ='3Planejamento Produção - INPUT'!B19*$B$20 -> 385926.88 | C18: ='3Planejamento Produção - INPUT'!C19*$B$20 -> 385926.88 | D18: ='3Planejamento Produção - INPUT'!D19*$B$20 -> 385926.88 | E18: ='3Planejamento Produção - INPUT'!E19*$B$20 -> 385926.88 | F18: ='3Planejamento Produção - INPUT'!F19*$B$20 -> 385926.88 | G18: ='3Planejamento Produção - INPUT'!G19*$B$20 -> 385926.88 | H18: ='3Planejamento Produção - INPUT'!H19*$B$20 -> 385926.88 | I18: ='3Planejamento Produção - INPUT'!I19*$B$20 -> 385926.88 | ... M18: ='3Planejamento Produção - INPUT'!M19*$B$20 -> 385926.88
A20: Multiplicador | B20: 1000

Sheet 5Plan Consumo Especifico -INPUT
A1: PLANEJADO | B1: Consumo Específico de Energia Elétrica (kWh/tms)
A2: Área | B2: 46023 | C2: =B2 + 35 -> 46058 | D2: =C2 + 30 -> 46088 | E2: =D2 + 30 -> 46118 | F2: =E2 + 30 -> 46148 | G2: =F2 + 30 -> 46178 | H2: =G2 + 30 -> 46208 | I2: =H2 + 30 -> 46238 | J2: =I2 + 30 -> 46268 | K2: =J2 + 30 -> 46298 | ... M2: =L2 + 30 -> 46358
A3: Filtragem Germano | B3: 3.2782218 | C3: 3.3594929 | D3: 3.2873827 | E3: 3.0110439 | F3: 2.924849 | G3: 2.9066097 | H3: 2.8221329 | I3: 2.9663232 | J3: 2.9147197 | K3: 2.9375104 | L3: 3.2801066 | M3: 3.1486969
A4: Mineração | B4: 1.484089 | C4: 1.3742516 | D4: 1.4888116 | E4: 1.3200199 | F4: 1.3244418 | G4: 1.2736057 | H4: 1.2783034 | I4: 1.3434574 | J4: 1.2771984 | K4: 1.3300897 | L4: 1.437355 | M4: 1.4263995
A5: Beneficiamento 1
A6: Beneficiamento 2 | B6: 42.39599 | C6: 46.531371 | D6: 44.099864 | E6: 44.957226 | F6: 43.509413 | G6: 41.041908 | H6: 39.614505 | I6: 39.626077 | J6: 40.727441 | K6: 41.55038 | L6: 48.377094 | M6: 43.421937
A7: Beneficiamento 3 | B7: 42.214994 | C7: 40.806527 | D7: 40.9953 | E7: 34.57474 | F7: 33.672263 | G7: 34.774985 | H7: 33.91942 | I7: 37.123951 | J7: 35.158027 | K7: 35.097615 | L7: 37.993214 | M7: 38.380143
A8: Brumal
A9: Mineroduto 1
A10: Mineroduto 2
A11: Mineroduto 3 | B11: 7.1050642 | C11: 7.1923077 | D11: 7.558579 | E11: 7.1050642 | F11: 7.0579495 | G11: 7.1972582 | H11: 7.1267817 | I11: 7.18065 | J11: 7.1050642 | K11: 7.18065 | L11: 7.1428571 | M11: 7.18065
A12: Preparação 1 | B12: 0 | C12: 0 | D12: 0 | E12: 0 | F12: 0 | G12: 0 | H12: 0 | I12: 0 | J12: 0 | K12: 0 | L12: 0 | M12: 0
A13: Preparação 2 | B13: 10.77 | C13: 10.77 | D13: 10.77 | E13: 10.77 | F13: 10.77 | G13: 10.77 | H13: 10.77 | I13: 10.77 | J13: 10.77 | K13: 10.77 | L13: 10.77 | M13: 10.77
A14: Usina 1
A15: Usina 2
A16: Usina 3 | B16: 29.95 | C16: 29.95 | D16: 29.95 | E16: 29.95 | F16: 29.95 | G16: 29.95 | H16: 29.95 | I16: 29.95 | J16: 29.95 | K16: 29.95 | L16: 29.95 | M16: 29.95
A17: Usina 4 | B17: 32.17 | C17: 32.17 | D17: 32.17 | E17: 32.17 | F17: 32.17 | G17: 32.17 | H17: 32.17 | I17: 32.17 | J17: 32.17 | K17: 32.17 | L17: 32.17 | M17: 32.17
A18: Estocagem | B18: 0.86881696 | C18: 0.86881696 | D18: 0.86881696 | E18: 0.86881696 | F18: 0.86881696 | G18: 0.86881696 | H18: 0.86881696 | I18: 0.86881696 | J18: 0.86881696 | K18: 0.86881696 | L18: 0.86881696 | M18: 0.86881696
A20: Os dados dessa planilha são todos imputados por cada área. Assim, alguém de área de consumo deverá cadastrar todos os dados presentees nessa planilha.

Sheet 6Consumo Especifico - OCULTA
C1: Consumo planejado por mês
A2: Centro de Custo | B2: Área | C2: Jan | D2: Fev | E2: Mar | F2: Abr | G2: Mai | H2: Jun | I2: Jul | J2: Ago | K2: Set | L2: Out | M2: Nov | N2: Dez
A3: 11140030 | B3: Filtragem Germano | C3: ='5Plan Consumo Especifico -INPUT'!B3 -> 3.2782218 | D3: ='5Plan Consumo Especifico -INPUT'!C3 -> 3.3594929 | E3: ='5Plan Consumo Especifico -INPUT'!D3 -> 3.2873827 | F3: ='5Plan Consumo Especifico -INPUT'!E3 -> 3.0110439 | G3: ='5Plan Consumo Especifico -INPUT'!F3 -> 2.924849 | H3: ='5Plan Consumo Especifico -INPUT'!G3 -> 2.9066097 | I3: ='5Plan Consumo Especifico -INPUT'!H3 -> 2.8221329 | J3: ='5Plan Consumo Especifico -INPUT'!I3 -> 2.9663232 | ... N3: ='5Plan Consumo Especifico -INPUT'!M3 -> 3.1486969
A4: 11110060 | B4: Mineração 1 | C4: ='5Plan Consumo Especifico -INPUT'!B4 -> 1.484089 | D4: ='5Plan Consumo Especifico -INPUT'!C4 -> 1.3742516 | E4: ='5Plan Consumo Especifico -INPUT'!D4 -> 1.4888116 | F4: ='5Plan Consumo Especifico -INPUT'!E4 -> 1.3200199 | G4: ='5Plan Consumo Especifico -INPUT'!F4 -> 1.3244418 | H4: ='5Plan Consumo Especifico -INPUT'!G4 -> 1.2736057 | I4: ='5Plan Consumo Especifico -INPUT'!H4 -> 1.2783034 | J4: ='5Plan Consumo Especifico -INPUT'!I4 -> 1.3434574 | ... N4: ='5Plan Consumo Especifico -INPUT'!M4 -> 1.4263995
A5: 11130180 | B5: Beneficiamento 1 | C5: ='5Plan Consumo Especifico -INPUT'!B5 -> 0 | D5: ='5Plan Consumo Especifico -INPUT'!C5 -> 0 | E5: ='5Plan Consumo Especifico -INPUT'!D5 -> 0 | F5: ='5Plan Consumo Especifico -INPUT'!E5 -> 0 | G5: ='5Plan Consumo Especifico -INPUT'!F5 -> 0 | H5: ='5Plan Consumo Especifico -INPUT'!G5 -> 0 | I5: ='5Plan Consumo Especifico -INPUT'!H5 -> 0 | J5: ='5Plan Consumo Especifico -INPUT'!I5 -> 0 | ... N5: ='5Plan Consumo Especifico -INPUT'!M5 -> 0
A6: 11131180 | B6: Beneficiamento 2 | C6: ='5Plan Consumo Especifico -INPUT'!B6 -> 42.39599 | D6: ='5Plan Consumo Especifico -INPUT'!C6 -> 46.531371 | E6: ='5Plan Consumo Especifico -INPUT'!D6 -> 44.099864 | F6: ='5Plan Consumo Especifico -INPUT'!E6 -> 44.957226 | G6: ='5Plan Consumo Especifico -INPUT'!F6 -> 43.509413 | H6: ='5Plan Consumo Especifico -INPUT'!G6 -> 41.041908 | I6: ='5Plan Consumo Especifico -INPUT'!H6 -> 39.614505 | J6: ='5Plan Consumo Especifico -INPUT'!I6 -> 39.626077 | ... N6: ='5Plan Consumo Especifico -INPUT'!M6 -> 43.421937
A7: 11132180 | B7: Beneficiamento 3 | C7: ='5Plan Consumo Especifico -INPUT'!B7 -> 42.214994 | D7: ='5Plan Consumo Especifico -INPUT'!C7 -> 40.806527 | E7: ='5Plan Consumo Especifico -INPUT'!D7 -> 40.9953 | F7: ='5Plan Consumo Especifico -INPUT'!E7 -> 34.57474 | G7: ='5Plan Consumo Especifico -INPUT'!F7 -> 33.672263 | H7: ='5Plan Consumo Especifico -INPUT'!G7 -> 34.774985 | I7: ='5Plan Consumo Especifico -INPUT'!H7 -> 33.91942 | J7: ='5Plan Consumo Especifico -INPUT'!I7 -> 37.123951 | ... N7: ='5Plan Consumo Especifico -INPUT'!M7 -> 38.380143
A8: 11162040 | B8: Mineroduto 1 | C8: ='5Plan Consumo Especifico -INPUT'!B9 -> 0 | D8: ='5Plan Consumo Especifico -INPUT'!C9 -> 0 | E8: ='5Plan Consumo Especifico -INPUT'!D9 -> 0 | F8: ='5Plan Consumo Especifico -INPUT'!E9 -> 0 | G8: ='5Plan Consumo Especifico -INPUT'!F9 -> 0 | H8: ='5Plan Consumo Especifico -INPUT'!G9 -> 0 | I8: ='5Plan Consumo Especifico -INPUT'!H9 -> 0 | J8: ='5Plan Consumo Especifico -INPUT'!I9 -> 0 | ... N8: ='5Plan Consumo Especifico -INPUT'!M9 -> 0
A9: 11162090 | B9: Mineroduto 2 | C9: ='5Plan Consumo Especifico -INPUT'!B10 -> 0 | D9: ='5Plan Consumo Especifico -INPUT'!C10 -> 0 | E9: ='5Plan Consumo Especifico -INPUT'!D10 -> 0 | F9: ='5Plan Consumo Especifico -INPUT'!E10 -> 0 | G9: ='5Plan Consumo Especifico -INPUT'!F10 -> 0 | H9: ='5Plan Consumo Especifico -INPUT'!G10 -> 0 | I9: ='5Plan Consumo Especifico -INPUT'!H10 -> 0 | J9: ='5Plan Consumo Especifico -INPUT'!I10 -> 0 | ... N9: ='5Plan Consumo Especifico -INPUT'!M10 -> 0
A10: 11162120 | B10: Mineroduto 3 | C10: ='5Plan Consumo Especifico -INPUT'!B11 -> 7.1050642 | D10: ='5Plan Consumo Especifico -INPUT'!C11 -> 7.1923077 | E10: ='5Plan Consumo Especifico -INPUT'!D11 -> 7.558579 | F10: ='5Plan Consumo Especifico -INPUT'!E11 -> 7.1050642 | G10: ='5Plan Consumo Especifico -INPUT'!F11 -> 7.0579495 | H10: ='5Plan Consumo Especifico -INPUT'!G11 -> 7.1972582 | I10: ='5Plan Consumo Especifico -INPUT'!H11 -> 7.1267817 | J10: ='5Plan Consumo Especifico -INPUT'!I11 -> 7.18065 | ... N10: ='5Plan Consumo Especifico -INPUT'!M11 -> 7.18065
A11: 12110080 | B11: Preparação 1 | C11: ='5Plan Consumo Especifico -INPUT'!B12 -> 0 | D11: ='5Plan Consumo Especifico -INPUT'!C12 -> 0 | E11: ='5Plan Consumo Especifico -INPUT'!D12 -> 0 | F11: ='5Plan Consumo Especifico -INPUT'!E12 -> 0 | G11: ='5Plan Consumo Especifico -INPUT'!F12 -> 0 | H11: ='5Plan Consumo Especifico -INPUT'!G12 -> 0 | I11: ='5Plan Consumo Especifico -INPUT'!H12 -> 0 | J11: ='5Plan Consumo Especifico -INPUT'!I12 -> 0 | ... N11: ='5Plan Consumo Especifico -INPUT'!M12 -> 0
A12: 12111080 | B12: Preparação 2 | C12: ='5Plan Consumo Especifico -INPUT'!B13 -> 10.77 | D12: ='5Plan Consumo Especifico -INPUT'!C13 -> 10.77 | E12: ='5Plan Consumo Especifico -INPUT'!D13 -> 10.77 | F12: ='5Plan Consumo Especifico -INPUT'!E13 -> 10.77 | G12: ='5Plan Consumo Especifico -INPUT'!F13 -> 10.77 | H12: ='5Plan Consumo Especifico -INPUT'!G13 -> 10.77 | I12: ='5Plan Consumo Especifico -INPUT'!H13 -> 10.77 | J12: ='5Plan Consumo Especifico -INPUT'!I13 -> 10.77 | ... N12: ='5Plan Consumo Especifico -INPUT'!M13 -> 10.77
A13: 12133040 | B13: Usina 1 | C13: ='5Plan Consumo Especifico -INPUT'!B14 -> 0 | D13: ='5Plan Consumo Especifico -INPUT'!C14 -> 0 | E13: ='5Plan Consumo Especifico -INPUT'!D14 -> 0 | F13: ='5Plan Consumo Especifico -INPUT'!E14 -> 0 | G13: ='5Plan Consumo Especifico -INPUT'!F14 -> 0 | H13: ='5Plan Consumo Especifico -INPUT'!G14 -> 0 | I13: ='5Plan Consumo Especifico -INPUT'!H14 -> 0 | J13: ='5Plan Consumo Especifico -INPUT'!I14 -> 0 | ... N13: ='5Plan Consumo Especifico -INPUT'!M14 -> 0
A14: 12135040 | B14: Usina 2 | C14: ='5Plan Consumo Especifico -INPUT'!B15 -> 0 | D14: ='5Plan Consumo Especifico -INPUT'!C15 -> 0 | E14: ='5Plan Consumo Especifico -INPUT'!D15 -> 0 | F14: ='5Plan Consumo Especifico -INPUT'!E15 -> 0 | G14: ='5Plan Consumo Especifico -INPUT'!F15 -> 0 | H14: ='5Plan Consumo Especifico -INPUT'!G15 -> 0 | I14: ='5Plan Consumo Especifico -INPUT'!H15 -> 0 | J14: ='5Plan Consumo Especifico -INPUT'!I15 -> 0 | ... N14: ='5Plan Consumo Especifico -INPUT'!M15 -> 0
A15: 12136040 | B15: Usina 3 | C15: ='5Plan Consumo Especifico -INPUT'!B16 -> 29.95 | D15: ='5Plan Consumo Especifico -INPUT'!C16 -> 29.95 | E15: ='5Plan Consumo Especifico -INPUT'!D16 -> 29.95 | F15: ='5Plan Consumo Especifico -INPUT'!E16 -> 29.95 | G15: ='5Plan Consumo Especifico -INPUT'!F16 -> 29.95 | H15: ='5Plan Consumo Especifico -INPUT'!G16 -> 29.95 | I15: ='5Plan Consumo Especifico -INPUT'!H16 -> 29.95 | J15: ='5Plan Consumo Especifico -INPUT'!I16 -> 29.95 | ... N15: ='5Plan Consumo Especifico -INPUT'!M16 -> 29.95
A16: 12138040 | B16: Usina 4 | C16: ='5Plan Consumo Especifico -INPUT'!B17 -> 32.17 | D16: ='5Plan Consumo Especifico -INPUT'!C17 -> 32.17 | E16: ='5Plan Consumo Especifico -INPUT'!D17 -> 32.17 | F16: ='5Plan Consumo Especifico -INPUT'!E17 -> 32.17 | G16: ='5Plan Consumo Especifico -INPUT'!F17 -> 32.17 | H16: ='5Plan Consumo Especifico -INPUT'!G17 -> 32.17 | I16: ='5Plan Consumo Especifico -INPUT'!H17 -> 32.17 | J16: ='5Plan Consumo Especifico -INPUT'!I17 -> 32.17 | ... N16: ='5Plan Consumo Especifico -INPUT'!M17 -> 32.17
A17: 12420080 | B17: Estocagem | C17: ='5Plan Consumo Especifico -INPUT'!B18 -> 0.86881696 | D17: ='5Plan Consumo Especifico -INPUT'!C18 -> 0.86881696 | E17: ='5Plan Consumo Especifico -INPUT'!D18 -> 0.86881696 | F17: ='5Plan Consumo Especifico -INPUT'!E18 -> 0.86881696 | G17: ='5Plan Consumo Especifico -INPUT'!F18 -> 0.86881696 | H17: ='5Plan Consumo Especifico -INPUT'!G18 -> 0.86881696 | I17: ='5Plan Consumo Especifico -INPUT'!H18 -> 0.86881696 | J17: ='5Plan Consumo Especifico -INPUT'!I18 -> 0.86881696 | ... N17: ='5Plan Consumo Especifico -INPUT'!M18 -> 0.86881696

Sheet 7Consumo Área - CALC
C1: Consumo planejado por mês
A2: Centro de Custo | B2: Área | C2: Jan | D2: Fev | E2: Mar | F2: Abr | G2: Mai | H2: Jun | I2: Jul | J2: Ago | K2: Set | L2: Out | M2: Nov | N2: Dez | O2: Planejado
A3: 11140030 | B3: Filtragem Germano | C3: ='6Consumo Especifico - OCULTA'!C3*'4Produção - OCULTA'!B3 -> 3471861.4 | D3: ='6Consumo Especifico - OCULTA'!D3*'4Produção - OCULTA'!C3 -> 3430149.9 | E3: ='6Consumo Especifico - OCULTA'!E3*'4Produção - OCULTA'!D3 -> 3302027 | F3: ='6Consumo Especifico - OCULTA'!F3*'4Produção - OCULTA'!E3 -> 3371827.1 | G3: ='6Consumo Especifico - OCULTA'!G3*'4Produção - OCULTA'!F3 -> 3326581.9 | H3: ='6Consumo Especifico - OCULTA'!H3*'4Produção - OCULTA'!G3 -> 3337450.4 | I3: ='6Consumo Especifico - OCULTA'!I3*'4Produção - OCULTA'!H3 -> 3354307.5 | J3: ='6Consumo Especifico - OCULTA'!J3*'4Produção - OCULTA'!I3 -> 3377192.5 | ... N3: ='6Consumo Especifico - OCULTA'!N3*'4Produção - OCULTA'!M3 -> 3528060.5 | O3: =SUM(C3:N3) -> 40705808
A4: 11110060 | B4: Mineração 1 | C4: =('4Produção - OCULTA'!B4+'4Produção - OCULTA'!B5+'4Produção - OCULTA'!B6)*'6Consumo Especifico - OCULTA'!C4 -> 1870828.3 | D4: =('4Produção - OCULTA'!C4+'4Produção - OCULTA'!C5+'4Produção - OCULTA'!C6)*'6Consumo Especifico - OCULTA'!D4 -> 1690459.9 | E4: =('4Produção - OCULTA'!D4+'4Produção - OCULTA'!D5+'4Produção - OCULTA'!D6)*'6Consumo Especifico - OCULTA'!E4 -> 1871551.6 | F4: =('4Produção - OCULTA'!E4+'4Produção - OCULTA'!E5+'4Produção - OCULTA'!E6)*'6Consumo Especifico - OCULTA'!F4 -> 1811656 | G4: =('4Produção - OCULTA'!F4+'4Produção - OCULTA'!F5+'4Produção - OCULTA'!F6)*'6Consumo Especifico - OCULTA'!G4 -> 1871292.8 | H4: =('4Produção - OCULTA'!G4+'4Produção - OCULTA'!G5+'4Produção - OCULTA'!G6)*'6Consumo Especifico - OCULTA'!H4 -> 1810758.8 | I4: =('4Produção - OCULTA'!H4+'4Produção - OCULTA'!H5+'4Produção - OCULTA'!H6)*'6Consumo Especifico - OCULTA'!I4 -> 1871840.4 | J4: =('4Produção - OCULTA'!I4+'4Produção - OCULTA'!I5+'4Produção - OCULTA'!I6)*'6Consumo Especifico - OCULTA'!J4 -> 1871620.4 | ... N4: =('4Produção - OCULTA'!M4+'4Produção - OCULTA'!M5+'4Produção - OCULTA'!M6)*'6Consumo Especifico - OCULTA'!N4 -> 1872072.5 | O4: =SUM(C4:N4) -> 22034942
A5: 11130180 | B5: Beneficiamento 1 | C5: 1040115.7 | D5: 1040115.7 | E5: 1040115.7 | F5: 1040115.7 | G5: 1040115.7 | H5: 1040115.7 | I5: 1040115.7 | J5: 1040115.7 | K5: 1040115.7 | L5: 1040115.7 | M5: 1040115.7 | N5: 1040115.7 | O5: =SUM(C5:N5) -> 12481388
A6: 11131180 | B6: Beneficiamento 2 | C6: ='6Consumo Especifico - OCULTA'!C6*'4Produção - OCULTA'!B5 -> 25428140 | D6: ='6Consumo Especifico - OCULTA'!D6*'4Produção - OCULTA'!C5 -> 25428140 | E6: ='6Consumo Especifico - OCULTA'!E6*'4Produção - OCULTA'!D5 -> 25428140 | F6: ='6Consumo Especifico - OCULTA'!F6*'4Produção - OCULTA'!E5 -> 25428140 | G6: ='6Consumo Especifico - OCULTA'!G6*'4Produção - OCULTA'!F5 -> 25428140 | H6: ='6Consumo Especifico - OCULTA'!H6*'4Produção - OCULTA'!G5 -> 25428140 | I6: ='6Consumo Especifico - OCULTA'!I6*'4Produção - OCULTA'!H5 -> 25428140 | J6: ='6Consumo Especifico - OCULTA'!J6*'4Produção - OCULTA'!I5 -> 25428140 | ... N6: ='6Consumo Especifico - OCULTA'!N6*'4Produção - OCULTA'!M5 -> 25428140 | O6: =SUM(C6:N6) -> 305137683
A7: 11132180 | B7: Beneficiamento 3 | C7: ='6Consumo Especifico - OCULTA'!C7*'4Produção - OCULTA'!B6 -> 27896233 | D7: ='6Consumo Especifico - OCULTA'!D7*'4Produção - OCULTA'!C6 -> 27896233 | E7: ='6Consumo Especifico - OCULTA'!E7*'4Produção - OCULTA'!D6 -> 27896233 | F7: ='6Consumo Especifico - OCULTA'!F7*'4Produção - OCULTA'!E6 -> 27896233 | G7: ='6Consumo Especifico - OCULTA'!G7*'4Produção - OCULTA'!F6 -> 27896233 | H7: ='6Consumo Especifico - OCULTA'!H7*'4Produção - OCULTA'!G6 -> 27896233 | I7: ='6Consumo Especifico - OCULTA'!I7*'4Produção - OCULTA'!H6 -> 27896233 | J7: ='6Consumo Especifico - OCULTA'!J7*'4Produção - OCULTA'!I6 -> 27896233 | ... N7: ='6Consumo Especifico - OCULTA'!N7*'4Produção - OCULTA'!M6 -> 27896233 | O7: =SUM(C7:N7) -> 334754799
A8: 11162040 | B8: Mineroduto 1 | C8: 230000 | D8: 210000 | E8: 230000 | F8: 225000 | G8: 210000 | H8: 230000 | I8: 225000 | J8: 230000 | K8: 230000 | L8: 230000 | M8: 225000 | N8: 230000 | O8: =SUM(C8:N8) -> 2705000
A9: 11162090 | B9: Mineroduto 2 | C9: ='6Consumo Especifico - OCULTA'!C9*'4Produção - OCULTA'!B8 -> 0 | D9: ='6Consumo Especifico - OCULTA'!D9*'4Produção - OCULTA'!C8 -> 0 | E9: ='6Consumo Especifico - OCULTA'!E9*'4Produção - OCULTA'!D8 -> 0 | F9: ='6Consumo Especifico - OCULTA'!F9*'4Produção - OCULTA'!E8 -> 0 | G9: ='6Consumo Especifico - OCULTA'!G9*'4Produção - OCULTA'!F8 -> 0 | H9: ='6Consumo Especifico - OCULTA'!H9*'4Produção - OCULTA'!G8 -> 0 | I9: ='6Consumo Especifico - OCULTA'!I9*'4Produção - OCULTA'!H8 -> 0 | J9: ='6Consumo Especifico - OCULTA'!J9*'4Produção - OCULTA'!I8 -> 0 | ... O9: ='6Consumo Especifico - OCULTA'!O9*'4Produção - OCULTA'!N8 -> 0
A10: 11162120 | B10: Mineroduto 3 | C10: ='6Consumo Especifico - OCULTA'!C10*'4Produção - OCULTA'!B9 -> 8956575.8 | D10: ='6Consumo Especifico - OCULTA'!D10*'4Produção - OCULTA'!C9 -> 8847221 | E10: ='6Consumo Especifico - OCULTA'!E10*'4Produção - OCULTA'!D9 -> 9501719.9 | F10: ='6Consumo Especifico - OCULTA'!F10*'4Produção - OCULTA'!E9 -> 9751316.8 | G10: ='6Consumo Especifico - OCULTA'!G10*'4Produção - OCULTA'!F9 -> 9972118.6 | H10: ='6Consumo Especifico - OCULTA'!H10*'4Produção - OCULTA'!G9 -> 10232758 | I10: ='6Consumo Especifico - OCULTA'!I10*'4Produção - OCULTA'!H9 -> 10435862 | J10: ='6Consumo Especifico - OCULTA'!J10*'4Produção - OCULTA'!I9 -> 10003630 | ... N10: ='6Consumo Especifico - OCULTA'!N10*'4Produção - OCULTA'!M9 -> 9424216.2 | O10: =SUM(C10:N10) -> 1.1629979e+08
A11: 12110080 | B11: Preparação 1 | C11: ='6Consumo Especifico - OCULTA'!C11*'4Produção - OCULTA'!B10 -> 0 | D11: ='6Consumo Especifico - OCULTA'!D11*'4Produção - OCULTA'!C10 -> 0 | E11: ='6Consumo Especifico - OCULTA'!E11*'4Produção - OCULTA'!D10 -> 0 | F11: ='6Consumo Especifico - OCULTA'!F11*'4Produção - OCULTA'!E10 -> 0 | G11: ='6Consumo Especifico - OCULTA'!G11*'4Produção - OCULTA'!F10 -> 0 | H11: ='6Consumo Especifico - OCULTA'!H11*'4Produção - OCULTA'!G10 -> 0 | I11: ='6Consumo Especifico - OCULTA'!I11*'4Produção - OCULTA'!H10 -> 0 | J11: ='6Consumo Especifico - OCULTA'!J11*'4Produção - OCULTA'!I10 -> 0 | ... N11: ='6Consumo Especifico - OCULTA'!N11*'4Produção - OCULTA'!M10 -> 0 | O11: =SUM(C11:N11) -> 0
A12: 12111080 | B12: Preparação 2 | C12: ='6Consumo Especifico - OCULTA'!C12*'4Produção - OCULTA'!B11 -> 13576559 | D12: ='6Consumo Especifico - OCULTA'!D12*'4Produção - OCULTA'!C11 -> 13248122 | E12: ='6Consumo Especifico - OCULTA'!E12*'4Produção - OCULTA'!D11 -> 13538725 | F12: ='6Consumo Especifico - OCULTA'!F12*'4Produção - OCULTA'!E11 -> 14781243 | G12: ='6Consumo Especifico - OCULTA'!G12*'4Produção - OCULTA'!F11 -> 15216844 | H12: ='6Consumo Especifico - OCULTA'!H12*'4Produção - OCULTA'!G11 -> 15312331 | I12: ='6Consumo Especifico - OCULTA'!I12*'4Produção - OCULTA'!H11 -> 15770686 | J12: ='6Consumo Especifico - OCULTA'!J12*'4Produção - OCULTA'!I11 -> 15004087 | ... N12: ='6Consumo Especifico - OCULTA'!N12*'4Produção - OCULTA'!M11 -> 14135045 | O12: =SUM(C12:N12) -> 1.7457338e+08
A13: 12133040 | B13: Usina 1 | C13: ='6Consumo Especifico - OCULTA'!C13*'4Produção - OCULTA'!B12 -> 0 | D13: ='6Consumo Especifico - OCULTA'!D13*'4Produção - OCULTA'!C12 -> 0 | E13: ='6Consumo Especifico - OCULTA'!E13*'4Produção - OCULTA'!D12 -> 0 | F13: ='6Consumo Especifico - OCULTA'!F13*'4Produção - OCULTA'!E12 -> 0 | G13: ='6Consumo Especifico - OCULTA'!G13*'4Produção - OCULTA'!F12 -> 0 | H13: ='6Consumo Especifico - OCULTA'!H13*'4Produção - OCULTA'!G12 -> 0 | I13: ='6Consumo Especifico - OCULTA'!I13*'4Produção - OCULTA'!H12 -> 0 | J13: ='6Consumo Especifico - OCULTA'!J13*'4Produção - OCULTA'!I12 -> 0 | ... N13: ='6Consumo Especifico - OCULTA'!N13*'4Produção - OCULTA'!M12 -> 0 | O13: =SUM(C13:N13) -> 0
A14: 12135040 | B14: Usina 2 | C14: ='6Consumo Especifico - OCULTA'!C14*'4Produção - OCULTA'!B13 -> 0 | D14: ='6Consumo Especifico - OCULTA'!D14*'4Produção - OCULTA'!C13 -> 0 | E14: ='6Consumo Especifico - OCULTA'!E14*'4Produção - OCULTA'!D13 -> 0 | F14: ='6Consumo Especifico - OCULTA'!F14*'4Produção - OCULTA'!E13 -> 0 | G14: ='6Consumo Especifico - OCULTA'!G14*'4Produção - OCULTA'!F13 -> 0 | H14: ='6Consumo Especifico - OCULTA'!H14*'4Produção - OCULTA'!G13 -> 0 | I14: ='6Consumo Especifico - OCULTA'!I14*'4Produção - OCULTA'!H13 -> 0 | J14: ='6Consumo Especifico - OCULTA'!J14*'4Produção - OCULTA'!I13 -> 0 | ... N14: ='6Consumo Especifico - OCULTA'!N14*'4Produção - OCULTA'!M13 -> 0 | O14: =SUM(C14:N14) -> 0
A15: 12136040 | B15: Usina 3 | C15: ='6Consumo Especifico - OCULTA'!C15*'4Produção - OCULTA'!B14 -> 14208007 | D15: ='6Consumo Especifico - OCULTA'!D15*'4Produção - OCULTA'!C14 -> 13696732 | E15: ='6Consumo Especifico - OCULTA'!E15*'4Produção - OCULTA'!D14 -> 11532297 | F15: ='6Consumo Especifico - OCULTA'!F15*'4Produção - OCULTA'!E14 -> 15634192 | G15: ='6Consumo Especifico - OCULTA'!G15*'4Produção - OCULTA'!F14 -> 15789968 | H15: ='6Consumo Especifico - OCULTA'!H15*'4Produção - OCULTA'!G14 -> 15947410 | I15: ='6Consumo Especifico - OCULTA'!I15*'4Produção - OCULTA'!H14 -> 16781463 | J15: ='6Consumo Especifico - OCULTA'!J15*'4Produção - OCULTA'!I14 -> 15792199 | ... N15: ='6Consumo Especifico - OCULTA'!N15*'4Produção - OCULTA'!M14 -> 14629501 | O15: =SUM(C15:N15) -> 1.7988224e+08
A16: 12138040 | B16: Usina 4 | C16: ='6Consumo Especifico - OCULTA'!C16*'4Produção - OCULTA'!B15 -> 19071584 | D16: ='6Consumo Especifico - OCULTA'!D16*'4Produção - OCULTA'!C15 -> 17736321 | E16: ='6Consumo Especifico - OCULTA'!E16*'4Produção - OCULTA'!D15 -> 21838381 | F16: ='6Consumo Especifico - OCULTA'!F16*'4Produção - OCULTA'!E15 -> 20961140 | G16: ='6Consumo Especifico - OCULTA'!G16*'4Produção - OCULTA'!F15 -> 20514207 | H16: ='6Consumo Especifico - OCULTA'!H16*'4Produção - OCULTA'!G15 -> 22132792 | I16: ='6Consumo Especifico - OCULTA'!I16*'4Produção - OCULTA'!H15 -> 22522503 | J16: ='6Consumo Especifico - OCULTA'!J16*'4Produção - OCULTA'!I15 -> 20471536 | ... N16: ='6Consumo Especifico - OCULTA'!N16*'4Produção - OCULTA'!M15 -> 20229319 | O16: =SUM(C16:N16) -> 2.469375e+08
A17: 12420080 | B17: Estocagem | C17: ='6Consumo Especifico - OCULTA'!C17*'4Produção - OCULTA'!B16 -> 927226.16 | D17: ='6Consumo Especifico - OCULTA'!D17*'4Produção - OCULTA'!C16 -> 876333.13 | E17: ='6Consumo Especifico - OCULTA'!E17*'4Produção - OCULTA'!D16 -> 924329.76 | F17: ='6Consumo Especifico - OCULTA'!F17*'4Produção - OCULTA'!E16 -> 1019629.6 | G17: ='6Consumo Especifico - OCULTA'!G17*'4Produção - OCULTA'!F16 -> 1012078.1 | H17: ='6Consumo Especifico - OCULTA'!H17*'4Produção - OCULTA'!G16 -> 1060358.6 | I17: ='6Consumo Especifico - OCULTA'!I17*'4Produção - OCULTA'!H16 -> 1095078.5 | J17: ='6Consumo Especifico - OCULTA'!J17*'4Produção - OCULTA'!I16 -> 1010990.4 | ... N17: ='6Consumo Especifico - OCULTA'!N17*'4Produção - OCULTA'!M16 -> 970720.24 | O17: =SUM(C17:N17) -> 11887243
B19: Consumo
A20: Área | B20: Unidade | C20: Jan | D20: Fev | E20: Mar | F20: Abr | G20: Mai | H20: Jun | I20: Jul | J20: Ago | K20: Set | L20: Out | M20: Nov | N20: Dez | O20: Planejado
A21: Filtragem Germano | B21: MWh | C21: =C3/1000 -> 3471.8614 | D21: =D3/1000 -> 3430.1499 | E21: =E3/1000 -> 3302.027 | F21: =F3/1000 -> 3371.8271 | G21: =G3/1000 -> 3326.5819 | H21: =H3/1000 -> 3337.4504 | I21: =I3/1000 -> 3354.3075 | J21: =J3/1000 -> 3377.1925 | ... O21: =O3/1000 -> 40705.808
A22: Mineração | B22: MWh | C22: =SUM(C4)/1000 -> 1870.8283 | D22: =SUM(D4)/1000 -> 1690.4599 | E22: =SUM(E4)/1000 -> 1871.5516 | F22: =SUM(F4)/1000 -> 1811.656 | G22: =SUM(G4)/1000 -> 1871.2928 | H22: =SUM(H4)/1000 -> 1810.7588 | I22: =SUM(I4)/1000 -> 1871.8404 | J22: =SUM(J4)/1000 -> 1871.6204 | ... O22: =SUM(O4)/1000 -> 22034.942
A23: Concentração | B23: MWh | C23: =SUM(C5:C7)/1000 -> 54364.489 | D23: =SUM(D5:D7)/1000 -> 54364.489 | E23: =SUM(E5:E7)/1000 -> 54364.489 | F23: =SUM(F5:F7)/1000 -> 54364.489 | G23: =SUM(G5:G7)/1000 -> 54364.489 | H23: =SUM(H5:H7)/1000 -> 54364.489 | I23: =SUM(I5:I7)/1000 -> 54364.489 | J23: =SUM(J5:J7)/1000 -> 54364.489 | ... O23: =SUM(O5:O7)/1000 -> 652373.87
A24: Mineroduto | B24: MWh | C24: =SUM(C8:C10)/1000 -> 9186.5758 | D24: =SUM(D8:D10)/1000 -> 9057.221 | E24: =SUM(E8:E10)/1000 -> 9731.7199 | F24: =SUM(F8:F10)/1000 -> 9976.3168 | G24: =SUM(G8:G10)/1000 -> 10182.119 | H24: =SUM(H8:H10)/1000 -> 10462.758 | I24: =SUM(I8:I10)/1000 -> 10660.862 | J24: =SUM(J8:J10)/1000 -> 10233.63 | ... O24: =SUM(O8:O10)/1000 -> 119004.79
A25: Preparação | B25: MWh | C25: =SUM(C11:C12)/1000 -> 13576.559 | D25: =SUM(D11:D12)/1000 -> 13248.122 | E25: =SUM(E11:E12)/1000 -> 13538.725 | F25: =SUM(F11:F12)/1000 -> 14781.243 | G25: =SUM(G11:G12)/1000 -> 15216.844 | H25: =SUM(H11:H12)/1000 -> 15312.331 | I25: =SUM(I11:I12)/1000 -> 15770.686 | J25: =SUM(J11:J12)/1000 -> 15004.087 | ... O25: =SUM(O11:O12)/1000 -> 174573.38
A26: Pelotização | B26: MWh | C26: =SUM(C13:C16)/1000 -> 33279.591 | D26: =SUM(D13:D16)/1000 -> 31433.054 | E26: =SUM(E13:E16)/1000 -> 33370.678 | F26: =SUM(F13:F16)/1000 -> 36595.333 | G26: =SUM(G13:G16)/1000 -> 36304.174 | H26: =SUM(H13:H16)/1000 -> 38080.202 | I26: =SUM(I13:I16)/1000 -> 39303.966 | J26: =SUM(J13:J16)/1000 -> 36263.735 | ... O26: =SUM(O13:O16)/1000 -> 426819.74
A27: Estocagem | B27: MWh | C27: =C17/1000 -> 927.22616 | D27: =D17/1000 -> 876.33313 | E27: =E17/1000 -> 924.32976 | F27: =F17/1000 -> 1019.6296 | G27: =G17/1000 -> 1012.0781 | H27: =H17/1000 -> 1060.3586 | I27: =I17/1000 -> 1095.0785 | J27: =J17/1000 -> 1010.9904 | ... N27: =N17/1000 -> 970.72024 | O27: =SUM(C27:N27) -> 11887.243
A28: Total | C28: =SUM(C21:C27) -> 116677.13 | D28: =SUM(D21:D27) -> 114099.83 | E28: =SUM(E21:E27) -> 117103.52 | F28: =SUM(F21:F27) -> 121920.49 | G28: =SUM(G21:G27) -> 122277.58 | H28: =SUM(H21:H27) -> 124428.35 | I28: =SUM(I21:I27) -> 126421.23 | J28: =SUM(J21:J27) -> 122125.74 | ... O28: =SUM(O21:O27) -> 1447399.8
A30: Totais por estado | B30: Unidade | C30: Jan | D30: Fev | E30: Mar | F30: Abr | G30: Mai | H30: Jun | I30: Jul | J30: Ago | K30: Set | L30: Out | M30: Nov | N30: Dez | O30: Planejado
A31: Minas Gerais | B31: MWh | C31: =SUM(C21:C24) -> 68893.755 | D31: =SUM(D21:D24) -> 68542.32 | E31: =SUM(E21:E24) -> 69269.788 | F31: =SUM(F21:F24) -> 69524.289 | G31: =SUM(G21:G24) -> 69744.483 | H31: =SUM(H21:H24) -> 69975.456 | I31: =SUM(I21:I24) -> 70251.499 | J31: =SUM(J21:J24) -> 69846.932 | ... O31: =SUM(O21:O24) -> 834119.41
A32: Espirito do Santo | B32: MWh | C32: =SUM(C25:C27) -> 47783.376 | D32: =SUM(D25:D27) -> 45557.509 | E32: =SUM(E25:E27) -> 47833.733 | F32: =SUM(F25:F27) -> 52396.206 | G32: =SUM(G25:G27) -> 52533.096 | H32: =SUM(H25:H27) -> 54452.892 | I32: =SUM(I25:I27) -> 56169.73 | J32: =SUM(J25:J27) -> 52278.812 | ... O32: =SUM(O25:O27) -> 613280.36
A33: Minas Gerais | B33: % | C33: =C31/C28 -> 0.59046494 | D33: =D31/D28 -> 0.60072237 | E33: =E31/E28 -> 0.59152609 | F33: =F31/F28 -> 0.57024284 | G33: =G31/G28 -> 0.57037834 | H33: =H31/H28 -> 0.56237551 | I33: =I31/I28 -> 0.55569385 | J33: =J31/J28 -> 0.57192636 | ... N33: =N31/N28 -> 0.58147804 | O33: =O31/$C$28 -> 7.1489537
A34: Espirito do Santo | B34: % | C34: =C32/C28 -> 0.40953506 | D34: =D32/D28 -> 0.39927763 | E34: =E32/E28 -> 0.40847391 | F34: =F32/F28 -> 0.42975716 | G34: =G32/G28 -> 0.42962166 | H34: =H32/H28 -> 0.43762449 | I34: =I32/I28 -> 0.44430615 | J34: =J32/J28 -> 0.42807364 | ... N34: =N32/N28 -> 0.41852196 | O34: =O32/$C$28 -> 5.2562174
A36: Divisão de Custo
A37: Centro de Custo | B37: Área | C37: Jan | D37: Fev | E37: Mar | F37: Abr | G37: Mai | H37: Jun | I37: Jul | J37: Ago | K37: Set | L37: Out | M37: Nov | N37: Dez | O37: Planejado
A38: 11140030 | B38: Filtragem Germano | C38: =(C3)/($C$31*1000) -> 0.050394429 | D38: =(D3)/(D31*1000) -> 0.050044263 | E38: =(E3)/(E31*1000) -> 0.04766908 | F38: =(F3)/(F31*1000) -> 0.048498548 | G38: =(G3)/(G31*1000) -> 0.047696703 | H38: =(H3)/(H31*1000) -> 0.047694586 | I38: =(I3)/(I31*1000) -> 0.047747131 | J38: =(J3)/(J31*1000) -> 0.048351337 | K38: =(K3)/(K31*1000) -> 0.047992079 | ... N38: =(N3)/(N31*1000) -> 0.050822812 | O38: =AVERAGE(C38:N38) -> 0.048806908
A39: =A11 -> 12110080 | B39: Mineração | C39: =(C4)/($C$31*1000) -> 0.027155267 | D39: =(D4)/($C$31*1000) -> 0.0245372 | E39: =(E4)/($C$31*1000) -> 0.027165766 | F39: =(F4)/($C$31*1000) -> 0.026296374 | G39: =(G4)/($C$31*1000) -> 0.02716201 | H39: =(H4)/($C$31*1000) -> 0.026283352 | I39: =(I4)/($C$31*1000) -> 0.027169958 | J39: =(J4)/($C$31*1000) -> 0.027166764 | ... N39: =(N4)/($C$31*1000) -> 0.027173327 | O39: =AVERAGE(C39:N39) -> 0.02665329
A40: =A12 -> 12111080 | B40: Beneficiamento 1 | C40: =(C5)/($C$31*1000) -> 0.015097387 | D40: =(D5)/($C$31*1000) -> 0.015097387 | E40: =(E5)/($C$31*1000) -> 0.015097387 | F40: =(F5)/($C$31*1000) -> 0.015097387 | G40: =(G5)/($C$31*1000) -> 0.015097387 | H40: =(H5)/($C$31*1000) -> 0.015097387 | I40: =(I5)/($C$31*1000) -> 0.015097387 | J40: =(J5)/($C$31*1000) -> 0.015097387 | ... N40: =(N5)/($C$31*1000) -> 0.015097387 | O40: =AVERAGE(C40:N40) -> 0.015097387
A41: =A13 -> 12133040 | B41: Beneficiamento 2 | C41: =(C6)/($C$31*1000) -> 0.36909209 | D41: =(D6)/($C$31*1000) -> 0.36909209 | E41: =(E6)/($C$31*1000) -> 0.36909209 | F41: =(F6)/($C$31*1000) -> 0.36909209 | G41: =(G6)/($C$31*1000) -> 0.36909209 | H41: =(H6)/($C$31*1000) -> 0.36909209 | I41: =(I6)/($C$31*1000) -> 0.36909209 | J41: =(J6)/($C$31*1000) -> 0.36909209 | ... N41: =(N6)/($C$31*1000) -> 0.36909209 | O41: =AVERAGE(C41:N41) -> 0.36909209
A42: =A14 -> 12135040 | B42: Beneficiamento 3 | C42: =(C7)/($C$31*1000) -> 0.40491672 | D42: =(D7)/($C$31*1000) -> 0.40491672 | E42: =(E7)/($C$31*1000) -> 0.40491672 | F42: =(F7)/($C$31*1000) -> 0.40491672 | G42: =(G7)/($C$31*1000) -> 0.40491672 | H42: =(H7)/($C$31*1000) -> 0.40491672 | I42: =(I7)/($C$31*1000) -> 0.40491672 | J42: =(J7)/($C$31*1000) -> 0.40491672 | ... N42: =(N7)/($C$31*1000) -> 0.40491672 | O42: =AVERAGE(C42:N42) -> 0.40491672
A43: =A16 -> 12138040 | B43: Mineroduto 1 | C43: =(C8)/($C$31*1000) -> 0.0033384739 | D43: =(D8)/($C$31*1000) -> 0.0030481718 | E43: =(E8)/($C$31*1000) -> 0.0033384739 | F43: =(F8)/($C$31*1000) -> 0.0032658983 | G43: =(G8)/($C$31*1000) -> 0.0030481718 | H43: =(H8)/($C$31*1000) -> 0.0033384739 | I43: =(I8)/($C$31*1000) -> 0.0032658983 | J43: =(J8)/($C$31*1000) -> 0.0033384739 | ... N43: =(N8)/($C$31*1000) -> 0.0033384739 | O43: =AVERAGE(C43:N43) -> 0.0032719463
A44: =A17 -> 12420080 | B44: Mineroduto 2 | C44: =(C9)/($C$31*1000) -> 0 | D44: =(D9)/($C$31*1000) -> 0 | E44: =(E9)/($C$31*1000) -> 0 | F44: =(F9)/($C$31*1000) -> 0 | G44: =(G9)/($C$31*1000) -> 0 | H44: =(H9)/($C$31*1000) -> 0 | I44: =(I9)/($C$31*1000) -> 0 | J44: =(J9)/($C$31*1000) -> 0 | ... N44: =(N9)/($C$31*1000) -> 0 | O44: =AVERAGE(C44:N44) -> 0
A45: =A18 -> 0 | B45: Mineroduto 3 | C45: =(C10)/($C$31*1000) -> 0.13000563 | D45: =(D10)/($C$31*1000) -> 0.12841833 | E45: =(E10)/($C$31*1000) -> 0.13791845 | F45: =(F10)/($C$31*1000) -> 0.14154137 | G45: =(G10)/($C$31*1000) -> 0.14474634 | H45: =(H10)/($C$31*1000) -> 0.14852954 | I45: =(I10)/($C$31*1000) -> 0.15147762 | J45: =(J10)/($C$31*1000) -> 0.14520373 | ... N45: =(N10)/($C$31*1000) -> 0.13679348 | O45: =AVERAGE(C45:N45) -> 0.14067529
A46: =A19 -> 0 | B46: Preparação 1 | C46: =(C11)/($C$32*1000) -> 0 | D46: =(D11)/($C$32*1000) -> 0 | E46: =(E11)/($C$32*1000) -> 0 | F46: =(F11)/($C$32*1000) -> 0 | G46: =(G11)/($C$32*1000) -> 0 | H46: =(H11)/($C$32*1000) -> 0 | I46: =(I11)/($C$32*1000) -> 0 | J46: =(J11)/($C$32*1000) -> 0 | ... N46: =(N11)/($C$32*1000) -> 0 | O46: =AVERAGE(C46:N46) -> 0
A47: =A20 -> Área | B47: Preparação 2 | C47: =(C12)/($C$32*1000) -> 0.28412724 | D47: =(D12)/($C$32*1000) -> 0.27725379 | E47: =(E12)/($C$32*1000) -> 0.28333547 | F47: =(F12)/($C$32*1000) -> 0.30933861 | G47: =(G12)/($C$32*1000) -> 0.31845478 | H47: =(H12)/($C$32*1000) -> 0.32045311 | I47: =(I12)/($C$32*1000) -> 0.33004545 | J47: =(J12)/($C$32*1000) -> 0.31400223 | ... N47: =(N12)/($C$32*1000) -> 0.29581511 | O47: =AVERAGE(C47:N47) -> 0.30445278
A48: =A21 -> Filtragem Germano | B48: Usina 1 | C48: =(C13)/($C$32*1000) -> 0 | D48: =(D13)/($C$32*1000) -> 0 | E48: =(E13)/($C$32*1000) -> 0 | F48: =(F13)/($C$32*1000) -> 0 | G48: =(G13)/($C$32*1000) -> 0 | H48: =(H13)/($C$32*1000) -> 0 | I48: =(I13)/($C$32*1000) -> 0 | J48: =(J13)/($C$32*1000) -> 0 | ... N48: =(N13)/($C$32*1000) -> 0 | O48: =AVERAGE(C48:N48) -> 0
A49: =A22 -> Mineração | B49: Usina 2 | C49: =(C14)/($C$32*1000) -> 0 | D49: =(D14)/($C$32*1000) -> 0 | E49: =(E14)/($C$32*1000) -> 0 | F49: =(F14)/($C$32*1000) -> 0 | G49: =(G14)/($C$32*1000) -> 0 | H49: =(H14)/($C$32*1000) -> 0 | I49: =(I14)/($C$32*1000) -> 0 | J49: =(J14)/($C$32*1000) -> 0 | ... N49: =(N14)/($C$32*1000) -> 0 | O49: =AVERAGE(C49:N49) -> 0
A50: =A23 -> Concentração | B50: Usina 3 | C50: =(C15)/($C$32*1000) -> 0.29734206 | D50: =(D15)/($C$32*1000) -> 0.28664221 | E50: =(E15)/($C$32*1000) -> 0.24134538 | F50: =(F15)/($C$32*1000) -> 0.32718895 | G50: =(G15)/($C$32*1000) -> 0.33044898 | H50: =(H15)/($C$32*1000) -> 0.3337439 | I50: =(I15)/($C$32*1000) -> 0.35119877 | J50: =(J15)/($C$32*1000) -> 0.33049567 | ... N50: =(N15)/($C$32*1000) -> 0.30616298 | O50: =AVERAGE(C50:N50) -> 0.31371133
A51: =A24 -> Mineroduto | B51: Usina 4 | C51: =(C16)/($C$32*1000) -> 0.39912592 | D51: =(D16)/($C$32*1000) -> 0.37118184 | E51: =(E16)/($C$32*1000) -> 0.45702884 | F51: =(F16)/($C$32*1000) -> 0.43867015 | G51: =(G16)/($C$32*1000) -> 0.42931681 | H51: =(H16)/($C$32*1000) -> 0.46319021 | I51: =(I16)/($C$32*1000) -> 0.471346 | J51: =(J16)/($C$32*1000) -> 0.4284238 | ... N51: =(N16)/($C$32*1000) -> 0.42335474 | O51: =AVERAGE(C51:N51) -> 0.43065449
A52: =A25 -> Preparação | B52: Estocagem | C52: =(C17)/($C$32*1000) -> 0.019404786 | D52: =(D17)/($C$32*1000) -> 0.018339707 | E52: =(E17)/($C$32*1000) -> 0.01934417 | F52: =(F17)/($C$32*1000) -> 0.021338585 | G52: =(G17)/($C$32*1000) -> 0.021180548 | H52: =(H17)/($C$32*1000) -> 0.022190951 | I52: =(I17)/($C$32*1000) -> 0.022917562 | J52: =(J17)/($C$32*1000) -> 0.021157786 | ... N52: =(N17)/($C$32*1000) -> 0.02031502 | O52: =AVERAGE(C52:N52) -> 0.020731134

Sheet 8Planejamento Geração - INPUT
A1: Geração (MWh) - Planejado | B1: Jan | C1: Fev | D1: Mar | E1: Abr | F1: Mai | G1: Jun | H1: Jul | I1: Ago | J1: Set | K1: Out | L1: Nov | M1: Dez
A2: Guilman Amorim | B2: 23979.167 | C2: 21368.452 | D2: 24144.728 | E2: 24559.148 | F2: 24972.533 | G2: 18891.653 | H2: 16420.194 | I2: 15320.572 | J2: 15407.459 | K2: 16528.92 | L2: 17382.712 | M2: 21189.34
A3: Muniz Freire | B3: 13943 | C3: 12192 | D3: 13483 | E3: 9537 | F3: 9350 | G3: 6545 | H3: 5891 | I3: 5830 | J3: 4930 | K3: 5800 | L3: 10753 | M3: 13750
A5: Os dados dessa planilha são todos imputados por cada área. Assim, alguém de área de produção deverá cadastrar todos os dados presentees nessa planilha.

Sheet 9Geração Própria - CALC
A1: Ano Base | B1: 2026
A2: Qtde de Horas Ponta/Dia | B2: 3
A3: Qtde de Horas no Dia | B3: 24
A5: Calendário | B5: Jan | C5: Fev | D5: Mar | E5: Abr | F5: Mai | G5: Jun | H5: Jul | I5: Ago | J5: Set | K5: Out | L5: Nov | M5: Dez
A6: Número de dias | B6: 31 | C6: 28 | D6: 31 | E6: 30 | F6: 31 | G6: 30 | H6: 31 | I6: 31 | J6: 30 | K6: 31 | L6: 30 | M6: 31
A7: Número de dias não uteis | B7: 10 | C7: 9 | D7: 10 | E7: 8 | F7: 11 | G7: 8 | H7: 8 | I7: 10 | J7: 8 | K7: 9 | L7: 10 | M7: 9
A8: Número de dias úteis no mês | B8: =B6-B7 -> 21 | C8: =C6-C7 -> 19 | D8: =D6-D7 -> 21 | E8: =E6-E7 -> 22 | F8: =F6-F7 -> 20 | G8: =G6-G7 -> 22 | H8: =H6-H7 -> 23 | I8: =I6-I7 -> 21 | ... M8: =M6-M7 -> 22
A9: Total de Horas/Ponta | B9: =B8*$B$2 -> 63 | C9: =C8*$B$2 -> 57 | D9: =D8*$B$2 -> 63 | E9: =E8*$B$2 -> 66 | F9: =F8*$B$2 -> 60 | G9: =G8*$B$2 -> 66 | H9: =H8*$B$2 -> 69 | I9: =I8*$B$2 -> 63 | ... M9: =M8*$B$2 -> 66
A10: Total de Horas/Fora Ponta | B10: =B11-B9 -> 681 | C10: =C11-C9 -> 615 | D10: =D11-D9 -> 681 | E10: =E11-E9 -> 654 | F10: =F11-F9 -> 684 | G10: =G11-G9 -> 654 | H10: =H11-H9 -> 675 | I10: =I11-I9 -> 681 | ... M10: =M11-M9 -> 678
A11: Total de Horas no mês | B11: =$B$3*B6 -> 744 | C11: =$B$3*C6 -> 672 | D11: =$B$3*D6 -> 744 | E11: =$B$3*E6 -> 720 | F11: =$B$3*F6 -> 744 | G11: =$B$3*G6 -> 720 | H11: =$B$3*H6 -> 744 | I11: =$B$3*I6 -> 744 | ... M11: =$B$3*M6 -> 744
A14: Unidade | B14: Geração | C14: Jan | D14: Fev | E14: Mar | F14: Abr | G14: Mai | H14: Jun | I14: Jul | J14: Ago | K14: Set | L14: Out | M14: Nov | N14: Dez | O14: Acumulado Planejado
A15: UHE Guilman Amorin | B15: MWh | C15: ='8Planejamento Geração - INPUT'!B2 -> 23979.167 | D15: ='8Planejamento Geração - INPUT'!C2 -> 21368.452 | E15: ='8Planejamento Geração - INPUT'!D2 -> 24144.728 | F15: ='8Planejamento Geração - INPUT'!E2 -> 24559.148 | G15: ='8Planejamento Geração - INPUT'!F2 -> 24972.533 | H15: ='8Planejamento Geração - INPUT'!G2 -> 18891.653 | I15: ='8Planejamento Geração - INPUT'!H2 -> 16420.194 | J15: ='8Planejamento Geração - INPUT'!I2 -> 15320.572 | ... N15: ='8Planejamento Geração - INPUT'!M2 -> 21189.34 | O15: =SUM(C15:N15) -> 240164.88
A16: UHE Guilman Amorin | B16: MWmédios | C16: =C15/B11 -> 32.230063 | D16: =D15/C11 -> 31.798292 | E16: =E15/D11 -> 32.452591 | F16: =F15/E11 -> 34.109928 | G16: =G15/F11 -> 33.565233 | H16: =H15/G11 -> 26.238406 | I16: =I15/H11 -> 22.070153 | J16: =J15/I11 -> 20.592167 | ... N16: =N15/M11 -> 28.480296 | O16: =AVERAGE(C16:N16) -> 27.441277
A17: PCH Muniz Freire | B17: MWh | C17: ='8Planejamento Geração - INPUT'!B3 -> 13943 | D17: ='8Planejamento Geração - INPUT'!C3 -> 12192 | E17: ='8Planejamento Geração - INPUT'!D3 -> 13483 | F17: ='8Planejamento Geração - INPUT'!E3 -> 9537 | G17: ='8Planejamento Geração - INPUT'!F3 -> 9350 | H17: ='8Planejamento Geração - INPUT'!G3 -> 6545 | I17: ='8Planejamento Geração - INPUT'!H3 -> 5891 | J17: ='8Planejamento Geração - INPUT'!I3 -> 5830 | ... N17: ='8Planejamento Geração - INPUT'!M3 -> 13750 | O17: =SUM(C17:N17) -> 112004
A18: PCH Muniz Freire | B18: MWmédios | C18: =C17/B11 -> 18.740591 | D18: =D17/C11 -> 18.142857 | E18: =E17/D11 -> 18.122312 | F18: =F17/E11 -> 13.245833 | G18: =G17/F11 -> 12.567204 | H18: =H17/G11 -> 9.0902778 | I18: =I17/H11 -> 7.9180108 | J18: =J17/I11 -> 7.8360215 | ... N18: =N17/M11 -> 18.481183 | O18: =AVERAGE(C18:N18) -> 12.810161
A19: Total | B19: MWh | C19: =C15+C17 -> 37922.167 | D19: =D15+D17 -> 33560.452 | E19: =E15+E17 -> 37627.728 | F19: =F15+F17 -> 34096.148 | G19: =G15+G17 -> 34322.533 | H19: =H15+H17 -> 25436.653 | I19: =I15+I17 -> 22311.194 | J19: =J15+J17 -> 21150.572 | ... N19: =N15+N17 -> 34939.34 | O19: =SUM(C19:N19) -> 352168.88
A20: Total | B20: MWmédios | C20: =C19/B11 -> 50.970655 | D20: =D19/C11 -> 49.941149 | E20: =E19/D11 -> 50.574903 | F20: =F19/E11 -> 47.355761 | G20: =G19/F11 -> 46.132437 | H20: =H19/G11 -> 35.328684 | I20: =I19/H11 -> 29.988164 | J20: =J19/I11 -> 28.428188 | ... N20: =N19/M11 -> 46.961479 | O20: =AVERAGE(C20:N20) -> 40.251438

Sheet 10Demanda - INPUT
A1: Unidade | B1: Horário | C1: Jan | D1: Fev | E1: Mar | F1: Abr | G1: Mai | H1: Jun | I1: Jul | J1: Ago | K1: Set | L1: Out | M1: Nov | N1: Dez
A2: Germano | B2: Ponta | C2: 120000 | D2: 120000 | E2: 120000 | F2: 120000 | G2: 120000 | H2: 120000 | I2: 120000 | J2: 120000 | K2: 120000 | L2: 120000 | M2: 120000 | N2: 120000
A3: Germano | B3: Fora Ponta | C3: 120000 | D3: 120000 | E3: 120000 | F3: 120000 | G3: 120000 | H3: 120000 | I3: 120000 | J3: 120000 | K3: 120000 | L3: 120000 | M3: 120000 | N3: 120000
A4: Matipo | B4: Ponta | C4: 11000 | D4: 11000 | E4: 11000 | F4: 11000 | G4: 11000 | H4: 11000 | I4: 11000 | J4: 11000 | K4: 11000 | L4: 11000 | M4: 11000 | N4: 11000
A5: Matipo | B5: Fora Ponta | C5: 11000 | D5: 11000 | E5: 11000 | F5: 11000 | G5: 11000 | H5: 11000 | I5: 11000 | J5: 11000 | K5: 11000 | L5: 11000 | M5: 11000 | N5: 11000
A6: Ubu | B6: Ponta | C6: 88000 | D6: 88000 | E6: 88000 | F6: 88000 | G6: 88000 | H6: 88000 | I6: 88000 | J6: 88000 | K6: 88000 | L6: 88000 | M6: 88000 | N6: 88000
A7: Ubu | B7: Fora Ponta | C7: 88000 | D7: 88000 | E7: 88000 | F7: 88000 | G7: 88000 | H7: 88000 | I7: 88000 | J7: 88000 | K7: 88000 | L7: 88000 | M7: 88000 | N7: 88000

Sheet 12Encargos ESS EER - CALC
A1: Samarco | C1: Jan | D1: Fev | E1: Mar | F1: Abr | G1: Mai | H1: Jun | I1: Jul | J1: Ago | K1: Set | L1: Out | M1: Nov | N1: Dez | O1: Acumulado Planejado
A2: ERR | B2: R$ / MWh | C2: 11.329954 | D2: 14.292512 | E2: 16.609237 | F2: 16.926332 | G2: 17.072441 | H2: 11.862747 | I2: 10.542097 | J2: 8.8279994 | K2: 7.9380953 | L2: 8.7729648 | M2: 9.8928874 | N2: 12.062907
A3: ERCAP | B3: R$ / MWh | C3: 3.31 | D3: 3.42 | E3: 3.24 | F3: 3.5611997 | G3: 3.5850922 | H3: 3.7472061 | I3: 7.0888037 | J3: 7.0674703 | K3: 6.991121 | L3: 6.755736 | M3: 7.0361196 | N3: 6.9628329
A4: Total ERR/ERCAP | B4: R$ / MWh | C4: =SUM(C2:C3) -> 14.639954 | D4: =SUM(D2:D3) -> 17.712512 | E4: =SUM(E2:E3) -> 19.849237 | F4: =SUM(F2:F3) -> 20.487532 | G4: =SUM(G2:G3) -> 20.657533 | H4: =SUM(H2:H3) -> 15.609953 | I4: =SUM(I2:I3) -> 17.6309 | J4: =SUM(J2:J3) -> 15.89547 | ... N4: =SUM(N2:N3) -> 19.02574 | O4: =O6/O5 -> 17.31442
A5: Consumo Samarco | B5: MWh | C5: ='7Consumo Área - CALC'!C28-'9Geração Própria - CALC'!C19 -> 78754.964 | D5: ='7Consumo Área - CALC'!D28-'9Geração Própria - CALC'!D19 -> 80539.376 | E5: ='7Consumo Área - CALC'!E28-'9Geração Própria - CALC'!E19 -> 79475.793 | F5: ='7Consumo Área - CALC'!F28-'9Geração Própria - CALC'!F19 -> 87824.346 | G5: ='7Consumo Área - CALC'!G28-'9Geração Própria - CALC'!G19 -> 87955.046 | H5: ='7Consumo Área - CALC'!H28-'9Geração Própria - CALC'!H19 -> 98991.696 | I5: ='7Consumo Área - CALC'!I28-'9Geração Própria - CALC'!I19 -> 104110.04 | J5: ='7Consumo Área - CALC'!J28-'9Geração Própria - CALC'!J19 -> 100975.17 | ... N5: ='7Consumo Área - CALC'!N28-'9Geração Própria - CALC'!N19 -> 84444.082 | O5: =SUM(C5:N5) -> 1095230.9
A6: Valor Total EER | B6: R$ | C6: =C5*C4 -> 1152969.1 | D6: =D5*D4 -> 1426554.7 | E6: =E5*E4 -> 1577533.8 | F6: =F5*F4 -> 1799304.1 | G6: =G5*G4 -> 1816934.3 | H6: =H5*H4 -> 1545255.8 | I6: =I5*I4 -> 1835553.7 | J6: =J5*J4 -> 1605047.8 | ... N6: =N5*N4 -> 1606611.1 | O6: =SUM(C6:N6) -> 18963288
A7: ESS | B7: R$ / MWh | C7: 3.0351273 | D7: 0.20743695 | E7: 1.5353796 | F7: 0.68569874 | G7: 0.35952279 | H7: 0.90967792 | I7: 4.2593959 | J7: 7.4116561 | K7: 7.520548 | L7: 3.6415843 | M7: 5.2125415 | N7: 2.1172701 | O7: =O8/O5 -> 3.2249208
A8: Valor Total ESS | B8: R$ | C8: =C7*C5 -> 239031.34 | D8: =D7*D5 -> 16706.842 | E8: =E7*E5 -> 122025.51 | F8: =F7*F5 -> 60221.044 | G8: =G7*G5 -> 31621.843 | H8: =H7*H5 -> 90050.56 | I8: =I7*I5 -> 443445.86 | J8: =J7*J5 -> 748393.25 | ... N8: =N7*N5 -> 178790.93 | O8: =SUM(C8:N8) -> 3532032.9
A10: Total por Estado | C10: Classe Custo | D10: Jan | E10: Fev | F10: Mar | G10: Abr | H10: Mai | I10: Jun | J10: Jul | K10: Ago | L10: Set | M10: Out | N10: Nov | O10: Dez
A11: Minas Gerais | B11: ERR/ERCAP | C11: 50610007 | D11: =C6*'7Consumo Área - CALC'!C33 -> 680787.81 | E11: =D6*'7Consumo Área - CALC'!D33 -> 856963.33 | F11: =E6*'7Consumo Área - CALC'!E33 -> 933152.43 | G11: =F6*'7Consumo Área - CALC'!F33 -> 1026040.3 | H11: =G6*'7Consumo Área - CALC'!G33 -> 1036340 | I11: =H6*'7Consumo Área - CALC'!H33 -> 869014 | J11: =I6*'7Consumo Área - CALC'!I33 -> 1020005.9 | K11: =J6*'7Consumo Área - CALC'!J33 -> 917969.14 | ... O11: =N6*'7Consumo Área - CALC'!N33 -> 934209.09
B12: ESS | C12: 50610008 | D12: =C8*'7Consumo Área - CALC'!C33 -> 141139.63 | E12: =D8*'7Consumo Área - CALC'!D33 -> 10036.174 | F12: =E8*'7Consumo Área - CALC'!E33 -> 72181.271 | G12: =F8*'7Consumo Área - CALC'!F33 -> 34340.619 | H12: =G8*'7Consumo Área - CALC'!G33 -> 18036.414 | I12: =H8*'7Consumo Área - CALC'!H33 -> 50642.23 | J12: =I8*'7Consumo Área - CALC'!I33 -> 246420.13 | K12: =J8*'7Consumo Área - CALC'!J33 -> 428025.83 | ... O12: =N8*'7Consumo Área - CALC'!N33 -> 103963
B13: TOTAL | D13: =D12+D11 -> 821927.44 | E13: =E12+E11 -> 866999.5 | F13: =F12+F11 -> 1005333.7 | G13: =G12+G11 -> 1060380.9 | H13: =H12+H11 -> 1054376.4 | I13: =I12+I11 -> 919656.23 | J13: =J12+J11 -> 1266426 | K13: =K12+K11 -> 1345995 | ... O13: =O12+O11 -> 1038172.1
A14: Espirito do Santo | B14: ERCAP | C14: 50610007 | D14: =C6*'7Consumo Área - CALC'!C34 -> 472181.26 | E14: =D6*'7Consumo Área - CALC'!D34 -> 569591.38 | F14: =E6*'7Consumo Área - CALC'!E34 -> 644381.42 | G14: =F6*'7Consumo Área - CALC'!F34 -> 773263.81 | H14: =G6*'7Consumo Área - CALC'!G34 -> 780594.32 | I14: =H6*'7Consumo Área - CALC'!H34 -> 676241.76 | J14: =I6*'7Consumo Área - CALC'!I34 -> 815547.79 | K14: =J6*'7Consumo Área - CALC'!J34 -> 687078.65 | ... O14: =N6*'7Consumo Área - CALC'!N34 -> 672402.04
B15: ESS | C15: 50610008 | D15: =C8*'7Consumo Área - CALC'!C34 -> 97891.716 | E15: =D8*'7Consumo Área - CALC'!D34 -> 6670.6684 | F15: =E8*'7Consumo Área - CALC'!E34 -> 49844.236 | G15: =F8*'7Consumo Área - CALC'!F34 -> 25880.425 | H15: =G8*'7Consumo Área - CALC'!G34 -> 13585.429 | I15: =H8*'7Consumo Área - CALC'!H34 -> 39408.33 | J15: =I8*'7Consumo Área - CALC'!I34 -> 197025.72 | K15: =J8*'7Consumo Área - CALC'!J34 -> 320367.42 | ... O15: =N8*'7Consumo Área - CALC'!N34 -> 74827.932
B16: TOTAL | D16: =D14+D15 -> 570072.97 | E16: =E14+E15 -> 576262.05 | F16: =F14+F15 -> 694225.65 | G16: =G14+G15 -> 799144.24 | H16: =H14+H15 -> 794179.74 | I16: =I14+I15 -> 715650.09 | J16: =J14+J15 -> 1012573.5 | K16: =K14+K15 -> 1007446.1 | ... O16: =O14+O15 -> 747229.98

Sheet 13Distribuição de Carga
A1: Distribuição de Carga Por Estado
A2: Minas Gerais
A3: Descrição | B3: Unidade | C3: Jan | D3: Fev | E3: Mar | F3: Abr | G3: Mai | H3: Jun | I3: Jul | J3: Ago | K3: Set | L3: Out | M3: Nov | N3: Dez
A4: Percentual de Perda | B4: % | C4: 0.03 | D4: 0.03 | E4: 0.03 | F4: 0.03 | G4: 0.03 | H4: 0.03 | I4: 0.03 | J4: 0.03 | K4: 0.03 | L4: 0.03 | M4: 0.03 | N4: 0.03
A5: Consumo Energia | B5: MWh | C5: ='7Consumo Área - CALC'!C31 -> 68893.755 | D5: ='7Consumo Área - CALC'!D31 -> 68542.32 | E5: ='7Consumo Área - CALC'!E31 -> 69269.788 | F5: ='7Consumo Área - CALC'!F31 -> 69524.289 | G5: ='7Consumo Área - CALC'!G31 -> 69744.483 | H5: ='7Consumo Área - CALC'!H31 -> 69975.456 | I5: ='7Consumo Área - CALC'!I31 -> 70251.499 | J5: ='7Consumo Área - CALC'!J31 -> 69846.932 | ... N5: ='7Consumo Área - CALC'!N31 -> 69418.838
A6: Geração Guilman no Mês | B6: MWh | C6: ='9Geração Própria - CALC'!C15 -> 23979.167 | D6: ='9Geração Própria - CALC'!D15 -> 21368.452 | E6: ='9Geração Própria - CALC'!E15 -> 24144.728 | F6: ='9Geração Própria - CALC'!F15 -> 24559.148 | G6: ='9Geração Própria - CALC'!G15 -> 24972.533 | H6: ='9Geração Própria - CALC'!H15 -> 18891.653 | I6: ='9Geração Própria - CALC'!I15 -> 16420.194 | J6: ='9Geração Própria - CALC'!J15 -> 15320.572 | ... N6: ='9Geração Própria - CALC'!N15 -> 21189.34
A7: Perdas | B7: MWh | C7: =C5*C4 -> 2066.8126 | D7: =D5*D4 -> 2056.2696 | E7: =E5*E4 -> 2078.0936 | F7: =F5*F4 -> 2085.7287 | G7: =G5*G4 -> 2092.3345 | H7: =H5*H4 -> 2099.2637 | I7: =I5*I4 -> 2107.545 | J7: =J5*J4 -> 2095.408 | ... N7: =N5*N4 -> 2082.5652
A8: Proinfa | B8: MWh | C8: 0 | D8: 0 | E8: 0 | F8: 0 | G8: 0 | H8: 0 | I8: 0 | J8: 0 | K8: 0 | L8: 0 | M8: 0 | N8: 0
A9: Necessidade Total de Energia | B9: MWh | C9: =C5+C7-C8 -> 70960.567 | D9: =D5+D7-D8 -> 70598.589 | E9: =E5+E7-E8 -> 71347.881 | F9: =F5+F7-F8 -> 71610.018 | G9: =G5+G7-G8 -> 71836.817 | H9: =H5+H7-H8 -> 72074.72 | I9: =I5+I7-I8 -> 72359.044 | J9: =J5+J7-J8 -> 71942.34 | ... N9: =N5+N7-N8 -> 71501.404
A10: Necessidade de Compra | B10: MWh | C10: =IF(C9-C6<0,,C9-C6) -> 46981.4 | D10: =IF(D9-D6<0,,D9-D6) -> 49230.137 | E10: =IF(E9-E6<0,,E9-E6) -> 47203.153 | F10: =IF(F9-F6<0,,F9-F6) -> 47050.869 | G10: =IF(G9-G6<0,,G9-G6) -> 46864.284 | H10: =IF(H9-H6<0,,H9-H6) -> 53183.068 | I10: =IF(I9-I6<0,,I9-I6) -> 55938.85 | J10: =IF(J9-J6<0,,J9-J6) -> 56621.768 | ... N10: =IF(N9-N6<0,,N9-N6) -> 50312.063
A11: Qtde Energia Comprada | B11: MWh | C11: 46981.4 | D11: 49230.137 | E11: 47203.153 | F11: 47050.869 | G11: 46864.284 | H11: 53183.068 | I11: 55938.85 | J11: 56621.768 | K11: 56517.618 | L11: 55543.843 | M11: 53531.057 | N11: 50312.063
A13: Espirito do Santo
A14: Descrição | B14: Unidade | C14: Jan | D14: Fev | E14: Mar | F14: Abr | G14: Mai | H14: Jun | I14: Jul | J14: Ago | K14: Set | L14: Out | M14: Nov | N14: Dez
A15: Percentual de Perda | B15: % | C15: 0.03 | D15: 0.03 | E15: 0.03 | F15: 0.03 | G15: 0.03 | H15: 0.03 | I15: 0.03 | J15: 0.03 | K15: 0.03 | L15: 0.03 | M15: 0.03 | N15: 0.03
A16: Consumo Energia | B16: MWh | C16: ='7Consumo Área - CALC'!C32 -> 47783.376 | D16: ='7Consumo Área - CALC'!D32 -> 45557.509 | E16: ='7Consumo Área - CALC'!E32 -> 47833.733 | F16: ='7Consumo Área - CALC'!F32 -> 52396.206 | G16: ='7Consumo Área - CALC'!G32 -> 52533.096 | H16: ='7Consumo Área - CALC'!H32 -> 54452.892 | I16: ='7Consumo Área - CALC'!I32 -> 56169.73 | J16: ='7Consumo Área - CALC'!J32 -> 52278.812 | ... N16: ='7Consumo Área - CALC'!N32 -> 49964.584
A17: Geração Muniz Freire | B17: MWh | C17: ='9Geração Própria - CALC'!C17 -> 13943 | D17: ='9Geração Própria - CALC'!D17 -> 12192 | E17: ='9Geração Própria - CALC'!E17 -> 13483 | F17: ='9Geração Própria - CALC'!F17 -> 9537 | G17: ='9Geração Própria - CALC'!G17 -> 9350 | H17: ='9Geração Própria - CALC'!H17 -> 6545 | I17: ='9Geração Própria - CALC'!I17 -> 5891 | J17: ='9Geração Própria - CALC'!J17 -> 5830 | ... N17: ='9Geração Própria - CALC'!N17 -> 13750
A18: Perdas | B18: MWh | C18: =C16*C15 -> 1433.5013 | D18: =D16*D15 -> 1366.7253 | E18: =E16*E15 -> 1435.012 | F18: =F16*F15 -> 1571.8862 | G18: =G16*G15 -> 1575.9929 | H18: =H16*H15 -> 1633.5868 | I18: =I16*I15 -> 1685.0919 | J18: =J16*J15 -> 1568.3644 | ... N18: =N16*N15 -> 1498.9375
A19: Proinfa | B19: MWh | C19: 0 | D19: 0 | E19: 0 | F19: 0 | G19: 0 | H19: 0 | I19: 0 | J19: 0 | K19: 0 | L19: 0 | M19: 0 | N19: 0
A20: Necessidade Total de Energia | B20: MWh | C20: =C16+C18 -> 49216.877 | D20: =D16+D18 -> 46924.234 | E20: =E16+E18 -> 49268.745 | F20: =F16+F18 -> 53968.092 | G20: =G16+G18 -> 54109.089 | H20: =H16+H18 -> 56086.479 | I20: =I16+I18 -> 57854.822 | J20: =J16+J18 -> 53847.176 | ... N20: =N16+N18 -> 51463.522
A21: Necessidade de Compra | B21: MWh | C21: =C20-C17 -> 35273.877 | D21: =D20-D17 -> 34732.234 | E21: =E20-E17 -> 35785.745 | F21: =F20-F17 -> 44431.092 | G21: =G20-G17 -> 44759.089 | H21: =H20-H17 -> 49541.479 | I21: =I20-I17 -> 51963.822 | J21: =J20-J17 -> 48017.176 | ... N21: =N20-N17 -> 37713.522
A22: Qtde Energia Comprada | B22: MWh | C22: 35273.877 | D22: 34732.234 | E22: 35785.745 | F22: 44431.092 | G22: 44759.089 | H22: 49541.479 | I22: 51963.822 | J22: 48017.176 | K22: 50401.991 | L22: 49616.43 | M22: 37438.318 | N22: 37713.522
A24: Samarco - Total Geral
A25: Descrição | B25: Unidade | C25: Jan | D25: Fev | E25: Mar | F25: Abr | G25: Mai | H25: Jun | I25: Jul | J25: Ago | K25: Set | L25: Out | M25: Nov | N25: Dez
A26: Consumo Energia | B26: MWh | C26: =C16+C5 -> 116677.13 | D26: =D16+D5 -> 114099.83 | E26: =E16+E5 -> 117103.52 | F26: =F16+F5 -> 121920.49 | G26: =G16+G5 -> 122277.58 | H26: =H16+H5 -> 124428.35 | I26: =I16+I5 -> 126421.23 | J26: =J16+J5 -> 122125.74 | ... N26: =N16+N5 -> 119383.42
A27: Geração Total do Mês | B27: MWh | C27: =C17+C6 -> 37922.167 | D27: =D17+D6 -> 33560.452 | E27: =E17+E6 -> 37627.728 | F27: =F17+F6 -> 34096.148 | G27: =G17+G6 -> 34322.533 | H27: =H17+H6 -> 25436.653 | I27: =I17+I6 -> 22311.194 | J27: =J17+J6 -> 21150.572 | ... N27: =N17+N6 -> 34939.34
A28: Perdas | B28: MWh | C28: =C18+C7 -> 3500.3139 | D28: =D18+D7 -> 3422.9949 | E28: =E18+E7 -> 3513.1056 | F28: =F18+F7 -> 3657.6148 | G28: =G18+G7 -> 3668.3274 | H28: =H18+H7 -> 3732.8505 | I28: =I18+I7 -> 3792.6369 | J28: =J18+J7 -> 3663.7723 | ... N28: =N18+N7 -> 3581.5027
A29: Proinfa | B29: MWh | C29: =C8+C19 -> 0 | D29: =D8+D19 -> 0 | E29: =E8+E19 -> 0 | F29: =F8+F19 -> 0 | G29: =G8+G19 -> 0 | H29: =H8+H19 -> 0 | I29: =I8+I19 -> 0 | J29: =J8+J19 -> 0 | ... N29: =N8+N19 -> 0
A30: Necessidade Total de Energia | B30: MWh | C30: =C20+C9 -> 120177.44 | D30: =D20+D9 -> 117522.82 | E30: =E20+E9 -> 120616.63 | F30: =F20+F9 -> 125578.11 | G30: =G20+G9 -> 125945.91 | H30: =H20+H9 -> 128161.2 | I30: =I20+I9 -> 130213.87 | J30: =J20+J9 -> 125789.52 | ... N30: =N20+N9 -> 122964.93
A31: Necessidade de Compra | B31: MWh | C31: =C21+C10 -> 82255.278 | D31: =D21+D10 -> 83962.371 | E31: =E21+E10 -> 82988.898 | F31: =F21+F10 -> 91481.961 | G31: =G21+G10 -> 91623.373 | H31: =H21+H10 -> 102724.55 | I31: =I21+I10 -> 107902.67 | J31: =J21+J10 -> 104638.94 | ... N31: =N21+N10 -> 88025.585
A32: Qtde Energia Comprada | B32: MWh | C32: =C22+C11 -> 82255.278 | D32: =D22+D11 -> 83962.371 | E32: =E22+E11 -> 82988.898 | F32: =F22+F11 -> 91481.961 | G32: =G22+G11 -> 91623.373 | H32: =H22+H11 -> 102724.55 | I32: =I22+I11 -> 107902.67 | J32: =J22+J11 -> 104638.94 | ... N32: =N22+N11 -> 88025.585

Sheet 14Distrib de Classe de Custo
A1: Distribuição de Classe de Custo por Estado
A2: Minas Gerais
A3: Classe de Custo | B3: Área | C3: Jan | D3: Fev | E3: Mar | F3: Abr | G3: Mai | H3: Jun | I3: Jul | J3: Ago | K3: Set | L3: Out | M3: Nov | N3: Dez
A4: Devoluç. Enc .CDE PROINFA | B4: Total | C4: ='9Geração Própria - CALC'!C15*'2Tabela Tarifas Distribuidoras'!E6 -> 1595094.2 | D4: ='9Geração Própria - CALC'!D15*'2Tabela Tarifas Distribuidoras'!F6 -> 1421429.5 | E4: ='9Geração Própria - CALC'!E15*'2Tabela Tarifas Distribuidoras'!G6 -> 1606107.3 | F4: ='9Geração Própria - CALC'!F15*'2Tabela Tarifas Distribuidoras'!H6 -> 1633674.5 | G4: ='9Geração Própria - CALC'!G15*'2Tabela Tarifas Distribuidoras'!I6 -> 1661172.9 | H4: ='9Geração Própria - CALC'!H15*'2Tabela Tarifas Distribuidoras'!J6 -> 1256672.7 | I4: ='9Geração Própria - CALC'!I15*'2Tabela Tarifas Distribuidoras'!K6 -> 996048.97 | J4: ='9Geração Própria - CALC'!J15*'2Tabela Tarifas Distribuidoras'!L6 -> 929345.9 | ... N4: ='9Geração Própria - CALC'!N15*'2Tabela Tarifas Distribuidoras'!P6 -> 1285345.4
A5: Uso da Rede (TUSD FIO / DEM ) 50610003 | B5: Germano | C5: =('10Demanda - INPUT'!C2*'2Tabela Tarifas Distribuidoras'!E3)+('10Demanda - INPUT'!C3*'2Tabela Tarifas Distribuidoras'!E4) -> 1641503.8 | D5: =('10Demanda - INPUT'!D2*'2Tabela Tarifas Distribuidoras'!F3)+('10Demanda - INPUT'!D3*'2Tabela Tarifas Distribuidoras'!F4) -> 1641503.8 | E5: =('10Demanda - INPUT'!E2*'2Tabela Tarifas Distribuidoras'!G3)+('10Demanda - INPUT'!E3*'2Tabela Tarifas Distribuidoras'!G4) -> 1641503.8 | F5: =('10Demanda - INPUT'!F2*'2Tabela Tarifas Distribuidoras'!H3)+('10Demanda - INPUT'!F3*'2Tabela Tarifas Distribuidoras'!H4) -> 1641503.8 | G5: =('10Demanda - INPUT'!G2*'2Tabela Tarifas Distribuidoras'!I3)+('10Demanda - INPUT'!G3*'2Tabela Tarifas Distribuidoras'!I4) -> 1641503.8 | H5: =('10Demanda - INPUT'!H2*'2Tabela Tarifas Distribuidoras'!J3)+('10Demanda - INPUT'!H3*'2Tabela Tarifas Distribuidoras'!J4) -> 1641503.8 | I5: =('10Demanda - INPUT'!I2*'2Tabela Tarifas Distribuidoras'!K3)+('10Demanda - INPUT'!I3*'2Tabela Tarifas Distribuidoras'!K4) -> 1805249.2 | J5: =('10Demanda - INPUT'!J2*'2Tabela Tarifas Distribuidoras'!L3)+('10Demanda - INPUT'!J3*'2Tabela Tarifas Distribuidoras'!L4) -> 1805249.2 | ... N5: =('10Demanda - INPUT'!N2*'2Tabela Tarifas Distribuidoras'!P3)+('10Demanda - INPUT'!N3*'2Tabela Tarifas Distribuidoras'!P4) -> 1805249.2
B6: Matipo | C6: =('10Demanda - INPUT'!C4*'2Tabela Tarifas Distribuidoras'!E8)+('10Demanda - INPUT'!C5*'2Tabela Tarifas Distribuidoras'!E9) -> 263409.19 | D6: =('10Demanda - INPUT'!D4*'2Tabela Tarifas Distribuidoras'!F8)+('10Demanda - INPUT'!D5*'2Tabela Tarifas Distribuidoras'!F9) -> 263409.19 | E6: =('10Demanda - INPUT'!E4*'2Tabela Tarifas Distribuidoras'!G8)+('10Demanda - INPUT'!E5*'2Tabela Tarifas Distribuidoras'!G9) -> 263409.19 | F6: =('10Demanda - INPUT'!F4*'2Tabela Tarifas Distribuidoras'!H8)+('10Demanda - INPUT'!F5*'2Tabela Tarifas Distribuidoras'!H9) -> 263409.19 | G6: =('10Demanda - INPUT'!G4*'2Tabela Tarifas Distribuidoras'!I8)+('10Demanda - INPUT'!G5*'2Tabela Tarifas Distribuidoras'!I9) -> 263409.19 | H6: =('10Demanda - INPUT'!H4*'2Tabela Tarifas Distribuidoras'!J8)+('10Demanda - INPUT'!H5*'2Tabela Tarifas Distribuidoras'!J9) -> 263409.19 | I6: =('10Demanda - INPUT'!I4*'2Tabela Tarifas Distribuidoras'!K8)+('10Demanda - INPUT'!I5*'2Tabela Tarifas Distribuidoras'!K9) -> 454929.09 | J6: =('10Demanda - INPUT'!J4*'2Tabela Tarifas Distribuidoras'!L8)+('10Demanda - INPUT'!J5*'2Tabela Tarifas Distribuidoras'!L9) -> 454929.09 | ... N6: =('10Demanda - INPUT'!N4*'2Tabela Tarifas Distribuidoras'!P8)+('10Demanda - INPUT'!N5*'2Tabela Tarifas Distribuidoras'!P9) -> 454929.09
B7: Total | C7: =C6+C5 -> 1904913 | D7: =D6+D5 -> 1904913 | E7: =E6+E5 -> 1904913 | F7: =F6+F5 -> 1904913 | G7: =G6+G5 -> 1904913 | H7: =H6+H5 -> 1904913 | I7: =I6+I5 -> 2260178.3 | J7: =J6+J5 -> 2260178.3 | ... N7: =N6+N5 -> 2260178.3
A8: Uso da Rede (TUSD ENCARGO ) 50610006 | B8: Germano | C8: =IF((((SUM('7Consumo Área - CALC'!C3:C7)/1000)*'2Tabela Tarifas Distribuidoras'!E5)-C4) < 0, 0,((SUM('7Consumo Área - CALC'!C3:C7)/1000)*'2Tabela Tarifas Distribuidoras'!E5)-C4) -> 2235005.8 | D8: =IF((((SUM('7Consumo Área - CALC'!D3:D7)/1000)*'2Tabela Tarifas Distribuidoras'!F5)-D4) < 0, 0,((SUM('7Consumo Área - CALC'!D3:D7)/1000)*'2Tabela Tarifas Distribuidoras'!F5)-D4) -> 2394424.5 | E8: =IF((((SUM('7Consumo Área - CALC'!E3:E7)/1000)*'2Tabela Tarifas Distribuidoras'!G5)-E4) < 0, 0,((SUM('7Consumo Área - CALC'!E3:E7)/1000)*'2Tabela Tarifas Distribuidoras'!G5)-E4) -> 2213144.5 | F8: =IF((((SUM('7Consumo Área - CALC'!F3:F7)/1000)*'2Tabela Tarifas Distribuidoras'!H5)-F4) < 0, 0,((SUM('7Consumo Área - CALC'!F3:F7)/1000)*'2Tabela Tarifas Distribuidoras'!H5)-F4) -> 2186212.6 | G8: =IF((((SUM('7Consumo Área - CALC'!G3:G7)/1000)*'2Tabela Tarifas Distribuidoras'!I5)-G4) < 0, 0,((SUM('7Consumo Área - CALC'!G3:G7)/1000)*'2Tabela Tarifas Distribuidoras'!I5)-G4) -> 2159637.5 | H8: =IF((((SUM('7Consumo Área - CALC'!H3:H7)/1000)*'2Tabela Tarifas Distribuidoras'!J5)-H4) < 0, 0,((SUM('7Consumo Área - CALC'!H3:H7)/1000)*'2Tabela Tarifas Distribuidoras'!J5)-H4) -> 2224642.6 | I8: =IF((((SUM('7Consumo Área - CALC'!I3:I7)/1000)*'2Tabela Tarifas Distribuidoras'!K5)-I4) < 0, 0,((SUM('7Consumo Área - CALC'!I3:I7)/1000)*'2Tabela Tarifas Distribuidoras'!K5)-I4) -> 2489825.6 | J8: =IF((((SUM('7Consumo Área - CALC'!J3:J7)/1000)*'2Tabela Tarifas Distribuidoras'!L5)-J4) < 0, 0,((SUM('7Consumo Área - CALC'!J3:J7)/1000)*'2Tabela Tarifas Distribuidoras'!L5)-J4) -> 2557854.5 | ... N8: =IF((((SUM('7Consumo Área - CALC'!N3:N7)/1000)*'2Tabela Tarifas Distribuidoras'!P5)-N4) < 0, 0,((SUM('7Consumo Área - CALC'!N3:N7)/1000)*'2Tabela Tarifas Distribuidoras'!P5)-N4) -> 2210706.8
B9: Matipo | C9: =(SUM('7Consumo Área - CALC'!C8:C10)/1000)*'2Tabela Tarifas Distribuidoras'!E12 -> 745741.78 | D9: =(SUM('7Consumo Área - CALC'!D8:D10)/1000)*'2Tabela Tarifas Distribuidoras'!F12 -> 735241.09 | E9: =(SUM('7Consumo Área - CALC'!E8:E10)/1000)*'2Tabela Tarifas Distribuidoras'!G12 -> 789995.12 | F9: =(SUM('7Consumo Área - CALC'!F8:F10)/1000)*'2Tabela Tarifas Distribuidoras'!H12 -> 809850.85 | G9: =(SUM('7Consumo Área - CALC'!G8:G10)/1000)*'2Tabela Tarifas Distribuidoras'!I12 -> 826557.29 | H9: =(SUM('7Consumo Área - CALC'!H8:H10)/1000)*'2Tabela Tarifas Distribuidoras'!J12 -> 849338.85 | I9: =(SUM('7Consumo Área - CALC'!I8:I10)/1000)*'2Tabela Tarifas Distribuidoras'!K12 -> 878300.98 | J9: =(SUM('7Consumo Área - CALC'!J8:J10)/1000)*'2Tabela Tarifas Distribuidoras'!L12 -> 843103.24 | ... N9: =(SUM('7Consumo Área - CALC'!N8:N10)/1000)*'2Tabela Tarifas Distribuidoras'!P12 -> 795367.9
B10: Total | C10: =C8+C9 -> 2980747.6 | D10: =D8+D9 -> 3129665.6 | E10: =E8+E9 -> 3003139.6 | F10: =F8+F9 -> 2996063.5 | G10: =G8+G9 -> 2986194.8 | H10: =H8+H9 -> 3073981.5 | I10: =I8+I9 -> 3368126.6 | J10: =J8+J9 -> 3400957.7 | ... N10: =N8+N9 -> 3006074.7
A11: Consumo de Energia 50610002 | B11: Pmix | C11: ='13Distribuição de Carga'!C11*'2Tabela Tarifas Distribuidoras'!E13 -> 7563933.2 | D11: ='13Distribuição de Carga'!D11*'2Tabela Tarifas Distribuidoras'!F13 -> 7925976.3 | E11: ='13Distribuição de Carga'!E11*'2Tabela Tarifas Distribuidoras'!G13 -> 7599635.1 | F11: ='13Distribuição de Carga'!F11*'2Tabela Tarifas Distribuidoras'!H13 -> 7575117.6 | G11: ='13Distribuição de Carga'!G11*'2Tabela Tarifas Distribuidoras'!I13 -> 7545077.6 | H11: ='13Distribuição de Carga'!H11*'2Tabela Tarifas Distribuidoras'!J13 -> 8562392.1 | I11: ='13Distribuição de Carga'!I11*'2Tabela Tarifas Distribuidoras'!K13 -> 9006068.8 | J11: ='13Distribuição de Carga'!J11*'2Tabela Tarifas Distribuidoras'!L13 -> 9116017.6 | ... N11: ='13Distribuição de Carga'!N11*'2Tabela Tarifas Distribuidoras'!P13 -> 8100164.8
B12: Total | C12: =C11 -> 7563933.2 | D12: =D11 -> 7925976.3 | E12: =E11 -> 7599635.1 | F12: =F11 -> 7575117.6 | G12: =G11 -> 7545077.6 | H12: =H11 -> 8562392.1 | I12: =I11 -> 9006068.8 | J12: =J11 -> 9116017.6 | ... N12: =N11 -> 8100164.8
A13: Espirito do Santo
A14: Classe de Custo | B14: Área | C14: Jan | D14: Fev | E14: Mar | F14: Abr | G14: Mai | H14: Jun | I14: Jul | J14: Ago | K14: Set | L14: Out | M14: Nov | N14: Dez
A15: Devoluç. Enc .CDE PROINFA | B15: Total | C15: ='9Geração Própria - CALC'!C17*'2Tabela Tarifas Distribuidoras'!E20 -> 1081279.6 | D15: 1421429 | E15: 1606107 | F15: 1633675 | G15: 1661173 | H15: 1256673 | I15: 996049 | J15: 929346 | K15: 934616 | L15: 1002644 | M15: 1054435 | N15: 1285345
A16: Uso da Rede (TUSD FIO / DEM ) 50610003 | B16: Ubu | C16: =('10Demanda - INPUT'!C6*'2Tabela Tarifas Distribuidoras'!E17)+('10Demanda - INPUT'!C7*'2Tabela Tarifas Distribuidoras'!E18) -> 2539410.6 | D16: =('10Demanda - INPUT'!D6*'2Tabela Tarifas Distribuidoras'!F17)+('10Demanda - INPUT'!D7*'2Tabela Tarifas Distribuidoras'!F18) -> 2539410.6 | E16: =('10Demanda - INPUT'!E6*'2Tabela Tarifas Distribuidoras'!G17)+('10Demanda - INPUT'!E7*'2Tabela Tarifas Distribuidoras'!G18) -> 2539410.6 | F16: =('10Demanda - INPUT'!F6*'2Tabela Tarifas Distribuidoras'!H17)+('10Demanda - INPUT'!F7*'2Tabela Tarifas Distribuidoras'!H18) -> 2539410.6 | G16: =('10Demanda - INPUT'!G6*'2Tabela Tarifas Distribuidoras'!I17)+('10Demanda - INPUT'!G7*'2Tabela Tarifas Distribuidoras'!I18) -> 2539410.6 | H16: =('10Demanda - INPUT'!H6*'2Tabela Tarifas Distribuidoras'!J17)+('10Demanda - INPUT'!H7*'2Tabela Tarifas Distribuidoras'!J18) -> 2539410.6 | I16: =('10Demanda - INPUT'!I6*'2Tabela Tarifas Distribuidoras'!K17)+('10Demanda - INPUT'!I7*'2Tabela Tarifas Distribuidoras'!K18) -> 2831528.5 | J16: =('10Demanda - INPUT'!J6*'2Tabela Tarifas Distribuidoras'!L17)+('10Demanda - INPUT'!J7*'2Tabela Tarifas Distribuidoras'!L18) -> 2522127 | ... N16: =('10Demanda - INPUT'!N6*'2Tabela Tarifas Distribuidoras'!P17)+('10Demanda - INPUT'!N7*'2Tabela Tarifas Distribuidoras'!P18) -> 2522127
B17: Total | C17: =C16 -> 2539410.6 | D17: =D16 -> 2539410.6 | E17: =E16 -> 2539410.6 | F17: =F16 -> 2539410.6 | G17: =G16 -> 2539410.6 | H17: =H16 -> 2539410.6 | I17: =I16 -> 2831528.5 | J17: =J16 -> 2522127 | ... N17: =N16 -> 2522127
A18: Uso da Rede (TUSD ENCARGO ) 50610006 | B18: Ubu | C18: =SUM('7Consumo Área - CALC'!C11:C17)/1000*'2Tabela Tarifas Distribuidoras'!E21 -> 4149025.8 | D18: =SUM('7Consumo Área - CALC'!D11:D17)/1000*'2Tabela Tarifas Distribuidoras'!F21 -> 3955753.9 | E18: =SUM('7Consumo Área - CALC'!E11:E17)/1000*'2Tabela Tarifas Distribuidoras'!G21 -> 4153398.3 | F18: =SUM('7Consumo Área - CALC'!F11:F17)/1000*'2Tabela Tarifas Distribuidoras'!H21 -> 4549557.3 | G18: =SUM('7Consumo Área - CALC'!G11:G17)/1000*'2Tabela Tarifas Distribuidoras'!I21 -> 4561443.5 | H18: =SUM('7Consumo Área - CALC'!H11:H17)/1000*'2Tabela Tarifas Distribuidoras'!J21 -> 4728139.2 | I18: =SUM('7Consumo Área - CALC'!I11:I17)/1000*'2Tabela Tarifas Distribuidoras'!K21 -> 4877212.1 | J18: =SUM('7Consumo Área - CALC'!J11:J17)/1000*'2Tabela Tarifas Distribuidoras'!L21 -> 4350438.9 | ... N18: =SUM('7Consumo Área - CALC'!N11:N17)/1000*'2Tabela Tarifas Distribuidoras'!P21 -> 4157857.9
B19: Total | C19: =IF(C18-C15<0,0,C18-C15) -> 3067746.1 | D19: =IF(D18-D15<0,0,D18-D15) -> 2534324.9 | E19: =IF(E18-E15<0,0,E18-E15) -> 2547291.3 | F19: =IF(F18-F15<0,0,F18-F15) -> 2915882.3 | G19: =IF(G18-G15<0,0,G18-G15) -> 2900270.5 | H19: =IF(H18-H15<0,0,H18-H15) -> 3471466.2 | I19: =IF(I18-I15<0,0,I18-I15) -> 3881163.1 | J19: =IF(J18-J15<0,0,J18-J15) -> 3421092.9 | ... N19: =IF(N18-N15<0,0,N18-N15) -> 2872512.9
A20: Consumo de Energia 50610002 | B20: Pmix | C20: ='13Distribuição de Carga'!C22*'2Tabela Tarifas Distribuidoras'!E22 -> 5687739.7 | D20: ='13Distribuição de Carga'!D22*'2Tabela Tarifas Distribuidoras'!F22 -> 5600402.4 | E20: ='13Distribuição de Carga'!E22*'2Tabela Tarifas Distribuidoras'!G22 -> 5770275.8 | F20: ='13Distribuição de Carga'!F22*'2Tabela Tarifas Distribuidoras'!H22 -> 7164295.6 | G20: ='13Distribuição de Carga'!G22*'2Tabela Tarifas Distribuidoras'!I22 -> 7217183.6 | H20: ='13Distribuição de Carga'!H22*'2Tabela Tarifas Distribuidoras'!J22 -> 7988320.5 | I20: ='13Distribuição de Carga'!I22*'2Tabela Tarifas Distribuidoras'!K22 -> 8378911.4 | J20: ='13Distribuição de Carga'!J22*'2Tabela Tarifas Distribuidoras'!L22 -> 7742534.1 | ... N20: ='13Distribuição de Carga'!N22*'2Tabela Tarifas Distribuidoras'!P22 -> 6081120.4
B21: Total | C21: =C20 -> 5687739.7 | D21: =D20 -> 5600402.4 | E21: =E20 -> 5770275.8 | F21: =F20 -> 7164295.6 | G21: =G20 -> 7217183.6 | H21: =H20 -> 7988320.5 | I21: =I20 -> 8378911.4 | J21: =J20 -> 7742534.1 | ... N21: =N20 -> 6081120.4

Sheet 15Distrib Centro de Custos
A1: Distribuição de Centro de Custos por Estado
A2: Minas Gerais
A3: Centro de Custo | B3: Classe de Custo | C3: Tipo | D3: Jan | E3: Fev | F3: Mar | G3: Abr | H3: Mai | I3: Jun | J3: Jul | K3: Ago | L3: Set | M3: Out | N3: Nov | O3: Dez
A4: 11140030 FILTRAGEM GERMANO | B4: 50610002 | C4: Consumo | D4: ='14Distrib de Classe de Custo'!C12*'7Consumo Área - CALC'!C38 -> 381180.09 | E4: ='14Distrib de Classe de Custo'!D12*'7Consumo Área - CALC'!D38 -> 396649.64 | F4: ='14Distrib de Classe de Custo'!E12*'7Consumo Área - CALC'!E38 -> 362267.61 | G4: ='14Distrib de Classe de Custo'!F12*'7Consumo Área - CALC'!F38 -> 367382.21 | H4: ='14Distrib de Classe de Custo'!G12*'7Consumo Área - CALC'!G38 -> 359875.33 | I4: ='14Distrib de Classe de Custo'!H12*'7Consumo Área - CALC'!H38 -> 408379.75 | J4: ='14Distrib de Classe de Custo'!I12*'7Consumo Área - CALC'!I38 -> 430013.95 | K4: ='14Distrib de Classe de Custo'!J12*'7Consumo Área - CALC'!J38 -> 440771.64 | ... O4: ='14Distrib de Classe de Custo'!N12*'7Consumo Área - CALC'!N38 -> 411673.15
B5: 50610003 | C5: Uso de Rede | D5: ='14Distrib de Classe de Custo'!C7*'7Consumo Área - CALC'!C38 -> 95997.004 | E5: ='14Distrib de Classe de Custo'!D7*'7Consumo Área - CALC'!D38 -> 95329.969 | F5: ='14Distrib de Classe de Custo'!E7*'7Consumo Área - CALC'!E38 -> 90805.452 | G5: ='14Distrib de Classe de Custo'!F7*'7Consumo Área - CALC'!F38 -> 92385.517 | H5: ='14Distrib de Classe de Custo'!G7*'7Consumo Área - CALC'!G38 -> 90858.072 | I5: ='14Distrib de Classe de Custo'!H7*'7Consumo Área - CALC'!H38 -> 90854.039 | J5: ='14Distrib de Classe de Custo'!I7*'7Consumo Área - CALC'!I38 -> 107917.03 | K5: ='14Distrib de Classe de Custo'!J7*'7Consumo Área - CALC'!J38 -> 109282.64 | ... O5: ='14Distrib de Classe de Custo'!N7*'7Consumo Área - CALC'!N38 -> 114868.62
B6: 50610006 | C6: Encargo | D6: ='14Distrib de Classe de Custo'!C10*'7Consumo Área - CALC'!C38 -> 150213.07 | E6: ='14Distrib de Classe de Custo'!D10*'7Consumo Área - CALC'!D38 -> 156621.81 | F6: ='14Distrib de Classe de Custo'!E10*'7Consumo Área - CALC'!E38 -> 143156.9 | G6: ='14Distrib de Classe de Custo'!F10*'7Consumo Área - CALC'!F38 -> 145304.73 | H6: ='14Distrib de Classe de Custo'!G10*'7Consumo Área - CALC'!G38 -> 142431.65 | I6: ='14Distrib de Classe de Custo'!H10*'7Consumo Área - CALC'!H38 -> 146612.27 | J6: ='14Distrib de Classe de Custo'!I10*'7Consumo Área - CALC'!I38 -> 160818.38 | K6: ='14Distrib de Classe de Custo'!J10*'7Consumo Área - CALC'!J38 -> 164440.85 | ... O6: ='14Distrib de Classe de Custo'!N10*'7Consumo Área - CALC'!N38 -> 152777.17
A7: 11110060 MINERAÇÃO | B7: 50610002 | C7: Consumo | D7: ='14Distrib de Classe de Custo'!C12*'7Consumo Área - CALC'!C39 -> 205400.63 | E7: ='14Distrib de Classe de Custo'!D12*'7Consumo Área - CALC'!D39 -> 194481.27 | F7: ='14Distrib de Classe de Custo'!E12*'7Consumo Área - CALC'!E39 -> 206449.91 | G7: ='14Distrib de Classe de Custo'!F12*'7Consumo Área - CALC'!F39 -> 199198.13 | H7: ='14Distrib de Classe de Custo'!G12*'7Consumo Área - CALC'!G39 -> 204939.47 | I7: ='14Distrib de Classe de Custo'!H12*'7Consumo Área - CALC'!H39 -> 225048.37 | J7: ='14Distrib de Classe de Custo'!I12*'7Consumo Área - CALC'!I39 -> 244694.51 | K7: ='14Distrib de Classe de Custo'!J12*'7Consumo Área - CALC'!J39 -> 247652.7 | ... O7: ='14Distrib de Classe de Custo'!N12*'7Consumo Área - CALC'!N39 -> 220108.43
B8: 50610003 | C8: Uso de Rede | D8: ='14Distrib de Classe de Custo'!C7*'7Consumo Área - CALC'!C39 -> 51728.423 | E8: ='14Distrib de Classe de Custo'!D7*'7Consumo Área - CALC'!D39 -> 46741.233 | F8: ='14Distrib de Classe de Custo'!E7*'7Consumo Área - CALC'!E39 -> 51748.422 | G8: ='14Distrib de Classe de Custo'!F7*'7Consumo Área - CALC'!F39 -> 50092.307 | H8: ='14Distrib de Classe de Custo'!G7*'7Consumo Área - CALC'!G39 -> 51741.266 | I8: ='14Distrib de Classe de Custo'!H7*'7Consumo Área - CALC'!H39 -> 50067.5 | J8: ='14Distrib de Classe de Custo'!I7*'7Consumo Área - CALC'!I39 -> 61408.949 | K8: ='14Distrib de Classe de Custo'!J7*'7Consumo Área - CALC'!J39 -> 61401.731 | ... O8: ='14Distrib de Classe de Custo'!N7*'7Consumo Área - CALC'!N39 -> 61416.564
B9: 50610006 | C9: Encargo | D9: ='14Distrib de Classe de Custo'!C10*'7Consumo Área - CALC'!C39 -> 80942.997 | E9: ='14Distrib de Classe de Custo'!D10*'7Consumo Área - CALC'!D39 -> 76793.233 | F9: ='14Distrib de Classe de Custo'!E10*'7Consumo Área - CALC'!E39 -> 81582.59 | G9: ='14Distrib de Classe de Custo'!F10*'7Consumo Área - CALC'!F39 -> 78785.607 | H9: ='14Distrib de Classe de Custo'!G10*'7Consumo Área - CALC'!G39 -> 81111.051 | I9: ='14Distrib de Classe de Custo'!H10*'7Consumo Área - CALC'!H39 -> 80794.538 | J9: ='14Distrib de Classe de Custo'!I10*'7Consumo Área - CALC'!I39 -> 91511.857 | K9: ='14Distrib de Classe de Custo'!J10*'7Consumo Área - CALC'!J39 -> 92393.017 | ... O9: ='14Distrib de Classe de Custo'!N10*'7Consumo Área - CALC'!N39 -> 81685.05
A10: 11130180 BENEFICIAMENTO 1 | B10: 50610002 | C10: Consumo | D10: ='14Distrib de Classe de Custo'!C12*'7Consumo Área - CALC'!C40 -> 114195.63 | E10: ='14Distrib de Classe de Custo'!D12*'7Consumo Área - CALC'!D40 -> 119661.53 | F10: ='14Distrib de Classe de Custo'!E12*'7Consumo Área - CALC'!E40 -> 114734.63 | G10: ='14Distrib de Classe de Custo'!F12*'7Consumo Área - CALC'!F40 -> 114364.48 | H10: ='14Distrib de Classe de Custo'!G12*'7Consumo Área - CALC'!G40 -> 113910.96 | I10: ='14Distrib de Classe de Custo'!H12*'7Consumo Área - CALC'!H40 -> 129269.75 | J10: ='14Distrib de Classe de Custo'!I12*'7Consumo Área - CALC'!I40 -> 135968.11 | K10: ='14Distrib de Classe de Custo'!J12*'7Consumo Área - CALC'!J40 -> 137628.05 | ... O10: ='14Distrib de Classe de Custo'!N12*'7Consumo Área - CALC'!N40 -> 122291.32
B11: 50610003 | C11: Uso de Rede | D11: ='14Distrib de Classe de Custo'!C7*'7Consumo Área - CALC'!C40 -> 28759.209 | E11: ='14Distrib de Classe de Custo'!D7*'7Consumo Área - CALC'!D40 -> 28759.209 | F11: ='14Distrib de Classe de Custo'!E7*'7Consumo Área - CALC'!E40 -> 28759.209 | G11: ='14Distrib de Classe de Custo'!F7*'7Consumo Área - CALC'!F40 -> 28759.209 | H11: ='14Distrib de Classe de Custo'!G7*'7Consumo Área - CALC'!G40 -> 28759.209 | I11: ='14Distrib de Classe de Custo'!H7*'7Consumo Área - CALC'!H40 -> 28759.209 | J11: ='14Distrib de Classe de Custo'!I7*'7Consumo Área - CALC'!I40 -> 34122.787 | K11: ='14Distrib de Classe de Custo'!J7*'7Consumo Área - CALC'!J40 -> 34122.787 | ... O11: ='14Distrib de Classe de Custo'!N7*'7Consumo Área - CALC'!N40 -> 34122.787
B12: 50610006 | C12: Encargo | D12: ='14Distrib de Classe de Custo'!C10*'7Consumo Área - CALC'!C40 -> 45001.5 | E12: ='14Distrib de Classe de Custo'!D10*'7Consumo Área - CALC'!D40 -> 47249.773 | F12: ='14Distrib de Classe de Custo'!E10*'7Consumo Área - CALC'!E40 -> 45339.562 | G12: ='14Distrib de Classe de Custo'!F10*'7Consumo Área - CALC'!F40 -> 45232.73 | H12: ='14Distrib de Classe de Custo'!G10*'7Consumo Área - CALC'!G40 -> 45083.738 | I12: ='14Distrib de Classe de Custo'!H10*'7Consumo Área - CALC'!H40 -> 46409.088 | J12: ='14Distrib de Classe de Custo'!I10*'7Consumo Área - CALC'!I40 -> 50849.91 | K12: ='14Distrib de Classe de Custo'!J10*'7Consumo Área - CALC'!J40 -> 51345.575 | ... O12: ='14Distrib de Classe de Custo'!N10*'7Consumo Área - CALC'!N40 -> 45383.873
A13: 11131180 BENEFICIAMENTO 2 | B13: 50610002 | C13: Consumo | D13: ='14Distrib de Classe de Custo'!C12*'7Consumo Área - CALC'!C41 -> 2791787.9 | E13: ='14Distrib de Classe de Custo'!D12*'7Consumo Área - CALC'!D41 -> 2925415.2 | F13: ='14Distrib de Classe de Custo'!E12*'7Consumo Área - CALC'!E41 -> 2804965.2 | G13: ='14Distrib de Classe de Custo'!F12*'7Consumo Área - CALC'!F41 -> 2795916 | H13: ='14Distrib de Classe de Custo'!G12*'7Consumo Área - CALC'!G41 -> 2784828.5 | I13: ='14Distrib de Classe de Custo'!H12*'7Consumo Área - CALC'!H41 -> 3160311.2 | J13: ='14Distrib de Classe de Custo'!I12*'7Consumo Área - CALC'!I41 -> 3324068.8 | K13: ='14Distrib de Classe de Custo'!J12*'7Consumo Área - CALC'!J41 -> 3364650 | ... O13: ='14Distrib de Classe de Custo'!N12*'7Consumo Área - CALC'!N41 -> 2989706.8
B14: 50610003 | C14: Uso de Rede | D14: ='14Distrib de Classe de Custo'!C7*'7Consumo Área - CALC'!C41 -> 703088.34 | E14: ='14Distrib de Classe de Custo'!D7*'7Consumo Área - CALC'!D41 -> 703088.34 | F14: ='14Distrib de Classe de Custo'!E7*'7Consumo Área - CALC'!E41 -> 703088.34 | G14: ='14Distrib de Classe de Custo'!F7*'7Consumo Área - CALC'!F41 -> 703088.34 | H14: ='14Distrib de Classe de Custo'!G7*'7Consumo Área - CALC'!G41 -> 703088.34 | I14: ='14Distrib de Classe de Custo'!H7*'7Consumo Área - CALC'!H41 -> 703088.34 | J14: ='14Distrib de Classe de Custo'!I7*'7Consumo Área - CALC'!I41 -> 834213.94 | K14: ='14Distrib de Classe de Custo'!J7*'7Consumo Área - CALC'!J41 -> 834213.94 | ... O14: ='14Distrib de Classe de Custo'!N7*'7Consumo Área - CALC'!N41 -> 834213.94
B15: 50610006 | C15: Encargo | D15: ='14Distrib de Classe de Custo'!C10*'7Consumo Área - CALC'!C41 -> 1100170.4 | E15: ='14Distrib de Classe de Custo'!D10*'7Consumo Área - CALC'!D41 -> 1155134.8 | F15: ='14Distrib de Classe de Custo'!E10*'7Consumo Área - CALC'!E41 -> 1108435.1 | G15: ='14Distrib de Classe de Custo'!F10*'7Consumo Área - CALC'!F41 -> 1105823.3 | H15: ='14Distrib de Classe de Custo'!G10*'7Consumo Área - CALC'!G41 -> 1102180.9 | I15: ='14Distrib de Classe de Custo'!H10*'7Consumo Área - CALC'!H41 -> 1134582.3 | J15: ='14Distrib de Classe de Custo'!I10*'7Consumo Área - CALC'!I41 -> 1243148.9 | K15: ='14Distrib de Classe de Custo'!J10*'7Consumo Área - CALC'!J41 -> 1255266.6 | ... O15: ='14Distrib de Classe de Custo'!N10*'7Consumo Área - CALC'!N41 -> 1109518.4
A16: 11132080 BENEFICIAMENTO 3 | B16: 50610002 | C16: Consumo | D16: ='14Distrib de Classe de Custo'!C12*'7Consumo Área - CALC'!C42 -> 3062763 | E16: ='14Distrib de Classe de Custo'!D12*'7Consumo Área - CALC'!D42 -> 3209360.4 | F16: ='14Distrib de Classe de Custo'!E12*'7Consumo Área - CALC'!E42 -> 3077219.3 | G16: ='14Distrib de Classe de Custo'!F12*'7Consumo Área - CALC'!F42 -> 3067291.8 | H16: ='14Distrib de Classe de Custo'!G12*'7Consumo Área - CALC'!G42 -> 3055128.1 | I16: ='14Distrib de Classe de Custo'!H12*'7Consumo Área - CALC'!H42 -> 3467055.7 | J16: ='14Distrib de Classe de Custo'!I12*'7Consumo Área - CALC'!I42 -> 3646707.9 | K16: ='14Distrib de Classe de Custo'!J12*'7Consumo Área - CALC'!J42 -> 3691227.9 | ... O16: ='14Distrib de Classe de Custo'!N12*'7Consumo Área - CALC'!N42 -> 3279892.2
B17: 50610003 | C17: Uso de Rede | D17: ='14Distrib de Classe de Custo'!C7*'7Consumo Área - CALC'!C42 -> 771331.14 | E17: ='14Distrib de Classe de Custo'!D7*'7Consumo Área - CALC'!D42 -> 771331.14 | F17: ='14Distrib de Classe de Custo'!E7*'7Consumo Área - CALC'!E42 -> 771331.14 | G17: ='14Distrib de Classe de Custo'!F7*'7Consumo Área - CALC'!F42 -> 771331.14 | H17: ='14Distrib de Classe de Custo'!G7*'7Consumo Área - CALC'!G42 -> 771331.14 | I17: ='14Distrib de Classe de Custo'!H7*'7Consumo Área - CALC'!H42 -> 771331.14 | J17: ='14Distrib de Classe de Custo'!I7*'7Consumo Área - CALC'!I42 -> 915183.98 | K17: ='14Distrib de Classe de Custo'!J7*'7Consumo Área - CALC'!J42 -> 915183.98 | ... O17: ='14Distrib de Classe de Custo'!N7*'7Consumo Área - CALC'!N42 -> 915183.98
B18: 50610006 | C18: Encargo | D18: ='14Distrib de Classe de Custo'!C10*'7Consumo Área - CALC'!C42 -> 1206954.5 | E18: ='14Distrib de Classe de Custo'!D10*'7Consumo Área - CALC'!D42 -> 1267253.9 | F18: ='14Distrib de Classe de Custo'!E10*'7Consumo Área - CALC'!E42 -> 1216021.5 | G18: ='14Distrib de Classe de Custo'!F10*'7Consumo Área - CALC'!F42 -> 1213156.2 | H18: ='14Distrib de Classe de Custo'!G10*'7Consumo Área - CALC'!G42 -> 1209160.2 | I18: ='14Distrib de Classe de Custo'!H10*'7Consumo Área - CALC'!H42 -> 1244706.5 | J18: ='14Distrib de Classe de Custo'!I10*'7Consumo Área - CALC'!I42 -> 1363810.8 | K18: ='14Distrib de Classe de Custo'!J10*'7Consumo Área - CALC'!J42 -> 1377104.6 | ... O18: ='14Distrib de Classe de Custo'!N10*'7Consumo Área - CALC'!N42 -> 1217209.9
A19: 11162040 MINERODUTO 1 | B19: 50610002 | C19: Consumo | D19: ='14Distrib de Classe de Custo'!C12*'7Consumo Área - CALC'!C43 -> 25251.993 | E19: ='14Distrib de Classe de Custo'!D12*'7Consumo Área - CALC'!D43 -> 24159.738 | F19: ='14Distrib de Classe de Custo'!E12*'7Consumo Área - CALC'!E43 -> 25371.183 | G19: ='14Distrib de Classe de Custo'!F12*'7Consumo Área - CALC'!F43 -> 24739.564 | H19: ='14Distrib de Classe de Custo'!G12*'7Consumo Área - CALC'!G43 -> 22998.693 | I19: ='14Distrib de Classe de Custo'!H12*'7Consumo Área - CALC'!H43 -> 28585.322 | J19: ='14Distrib de Classe de Custo'!I12*'7Consumo Área - CALC'!I43 -> 29412.905 | K19: ='14Distrib de Classe de Custo'!J12*'7Consumo Área - CALC'!J43 -> 30433.586 | ... O19: ='14Distrib de Classe de Custo'!N12*'7Consumo Área - CALC'!N43 -> 27042.189
B20: 50610003 | C20: Uso de Rede | D20: ='14Distrib de Classe de Custo'!C7*'7Consumo Área - CALC'!C43 -> 6359.5024 | E20: ='14Distrib de Classe de Custo'!D7*'7Consumo Área - CALC'!D43 -> 5806.5022 | F20: ='14Distrib de Classe de Custo'!E7*'7Consumo Área - CALC'!E43 -> 6359.5024 | G20: ='14Distrib de Classe de Custo'!F7*'7Consumo Área - CALC'!F43 -> 6221.2523 | H20: ='14Distrib de Classe de Custo'!G7*'7Consumo Área - CALC'!G43 -> 5806.5022 | I20: ='14Distrib de Classe de Custo'!H7*'7Consumo Área - CALC'!H43 -> 6359.5024 | J20: ='14Distrib de Classe de Custo'!I7*'7Consumo Área - CALC'!I43 -> 7381.5126 | K20: ='14Distrib de Classe de Custo'!J7*'7Consumo Área - CALC'!J43 -> 7545.5462 | ... O20: ='14Distrib de Classe de Custo'!N7*'7Consumo Área - CALC'!N43 -> 7545.5462
B21: 50610006 | C21: Encargo | D21: ='14Distrib de Classe de Custo'!C10*'7Consumo Área - CALC'!C43 -> 9951.1478 | E21: ='14Distrib de Classe de Custo'!D10*'7Consumo Área - CALC'!D43 -> 9539.7585 | F21: ='14Distrib de Classe de Custo'!E10*'7Consumo Área - CALC'!E43 -> 10025.903 | G21: ='14Distrib de Classe de Custo'!F10*'7Consumo Área - CALC'!F43 -> 9784.8388 | H21: ='14Distrib de Classe de Custo'!G10*'7Consumo Área - CALC'!G43 -> 9102.4346 | I21: ='14Distrib de Classe de Custo'!H10*'7Consumo Área - CALC'!H43 -> 10262.407 | J21: ='14Distrib de Classe de Custo'!I10*'7Consumo Área - CALC'!I43 -> 10999.959 | K21: ='14Distrib de Classe de Custo'!J10*'7Consumo Área - CALC'!J43 -> 11354.008 | ... O21: ='14Distrib de Classe de Custo'!N10*'7Consumo Área - CALC'!N43 -> 10035.702
A22: 11162090 MINERODUTO 2 | B22: 50610002 | C22: Consumo | D22: ='14Distrib de Classe de Custo'!C12*'7Consumo Área - CALC'!C44 -> 0 | E22: ='14Distrib de Classe de Custo'!D12*'7Consumo Área - CALC'!D44 -> 0 | F22: ='14Distrib de Classe de Custo'!E12*'7Consumo Área - CALC'!E44 -> 0 | G22: ='14Distrib de Classe de Custo'!F12*'7Consumo Área - CALC'!F44 -> 0 | H22: ='14Distrib de Classe de Custo'!G12*'7Consumo Área - CALC'!G44 -> 0 | I22: ='14Distrib de Classe de Custo'!H12*'7Consumo Área - CALC'!H44 -> 0 | J22: ='14Distrib de Classe de Custo'!I12*'7Consumo Área - CALC'!I44 -> 0 | K22: ='14Distrib de Classe de Custo'!J12*'7Consumo Área - CALC'!J44 -> 0 | ... O22: ='14Distrib de Classe de Custo'!N12*'7Consumo Área - CALC'!N44 -> 0
B23: 50610003 | C23: Uso de Rede | D23: ='14Distrib de Classe de Custo'!C7*'7Consumo Área - CALC'!C44 -> 0 | E23: ='14Distrib de Classe de Custo'!D7*'7Consumo Área - CALC'!D44 -> 0 | F23: ='14Distrib de Classe de Custo'!E7*'7Consumo Área - CALC'!E44 -> 0 | G23: ='14Distrib de Classe de Custo'!F7*'7Consumo Área - CALC'!F44 -> 0 | H23: ='14Distrib de Classe de Custo'!G7*'7Consumo Área - CALC'!G44 -> 0 | I23: ='14Distrib de Classe de Custo'!H7*'7Consumo Área - CALC'!H44 -> 0 | J23: ='14Distrib de Classe de Custo'!I7*'7Consumo Área - CALC'!I44 -> 0 | K23: ='14Distrib de Classe de Custo'!J7*'7Consumo Área - CALC'!J44 -> 0 | ... O23: ='14Distrib de Classe de Custo'!N7*'7Consumo Área - CALC'!N44 -> 0
B24: 50610006 | C24: Encargo | D24: ='14Distrib de Classe de Custo'!C10*'7Consumo Área - CALC'!C44 -> 0 | E24: ='14Distrib de Classe de Custo'!D10*'7Consumo Área - CALC'!D44 -> 0 | F24: ='14Distrib de Classe de Custo'!E10*'7Consumo Área - CALC'!E44 -> 0 | G24: ='14Distrib de Classe de Custo'!F10*'7Consumo Área - CALC'!F44 -> 0 | H24: ='14Distrib de Classe de Custo'!G10*'7Consumo Área - CALC'!G44 -> 0 | I24: ='14Distrib de Classe de Custo'!H10*'7Consumo Área - CALC'!H44 -> 0 | J24: ='14Distrib de Classe de Custo'!I10*'7Consumo Área - CALC'!I44 -> 0 | K24: ='14Distrib de Classe de Custo'!J10*'7Consumo Área - CALC'!J44 -> 0 | ... O24: ='14Distrib de Classe de Custo'!N10*'7Consumo Área - CALC'!N44 -> 0
A25: 11162120 MINERODUTO 3 | B25: 50610002 | C25: Consumo | D25: ='14Distrib de Classe de Custo'!C12*'7Consumo Área - CALC'!C45 -> 983353.88 | E25: ='14Distrib de Classe de Custo'!D12*'7Consumo Área - CALC'!D45 -> 1017840.6 | F25: ='14Distrib de Classe de Custo'!E12*'7Consumo Área - CALC'!E45 -> 1048129.9 | G25: ='14Distrib de Classe de Custo'!F12*'7Consumo Área - CALC'!F45 -> 1072192.6 | H25: ='14Distrib de Classe de Custo'!G12*'7Consumo Área - CALC'!G45 -> 1092122.3 | I25: ='14Distrib de Classe de Custo'!H12*'7Consumo Área - CALC'!H45 -> 1271768.2 | J25: ='14Distrib de Classe de Custo'!I12*'7Consumo Área - CALC'!I45 -> 1364217.9 | K25: ='14Distrib de Classe de Custo'!J12*'7Consumo Área - CALC'!J45 -> 1323679.7 | ... O25: ='14Distrib de Classe de Custo'!N12*'7Consumo Área - CALC'!N45 -> 1108049.7
B26: 50610003 | C26: Uso de Rede | D26: ='14Distrib de Classe de Custo'!C7*'7Consumo Área - CALC'!C45 -> 247649.42 | E26: ='14Distrib de Classe de Custo'!D7*'7Consumo Área - CALC'!D45 -> 244625.75 | F26: ='14Distrib de Classe de Custo'!E7*'7Consumo Área - CALC'!E45 -> 262722.65 | G26: ='14Distrib de Classe de Custo'!F7*'7Consumo Área - CALC'!F45 -> 269624.01 | H26: ='14Distrib de Classe de Custo'!G7*'7Consumo Área - CALC'!G45 -> 275729.18 | I26: ='14Distrib de Classe de Custo'!H7*'7Consumo Área - CALC'!H45 -> 282935.86 | J26: ='14Distrib de Classe de Custo'!I7*'7Consumo Área - CALC'!I45 -> 342366.43 | K26: ='14Distrib de Classe de Custo'!J7*'7Consumo Área - CALC'!J45 -> 328186.32 | ... O26: ='14Distrib de Classe de Custo'!N7*'7Consumo Área - CALC'!N45 -> 309177.65
B27: 50610006 | C27: Encargo | D27: ='14Distrib de Classe de Custo'!C10*'7Consumo Área - CALC'!C45 -> 387513.96 | E27: ='14Distrib de Classe de Custo'!D10*'7Consumo Área - CALC'!D45 -> 401906.43 | F27: ='14Distrib de Classe de Custo'!E10*'7Consumo Área - CALC'!E45 -> 414188.37 | G27: ='14Distrib de Classe de Custo'!F10*'7Consumo Área - CALC'!F45 -> 424066.94 | H27: ='14Distrib de Classe de Custo'!G10*'7Consumo Área - CALC'!G45 -> 432240.75 | I27: ='14Distrib de Classe de Custo'!H10*'7Consumo Área - CALC'!H45 -> 456577.07 | J27: ='14Distrib de Classe de Custo'!I10*'7Consumo Área - CALC'!I45 -> 510195.8 | K27: ='14Distrib de Classe de Custo'!J10*'7Consumo Área - CALC'!J45 -> 493831.74 | ... O27: ='14Distrib de Classe de Custo'!N10*'7Consumo Área - CALC'!N45 -> 411211.4
A28: Espirito Santo
A29: 12110080 PREPARAÇÃO 1 | B29: 50610002 | C29: Consumo | D29: ='14Distrib de Classe de Custo'!C21*'7Consumo Área - CALC'!C46 -> 0 | E29: ='14Distrib de Classe de Custo'!D21*'7Consumo Área - CALC'!D46 -> 0 | F29: ='14Distrib de Classe de Custo'!E21*'7Consumo Área - CALC'!E46 -> 0 | G29: ='14Distrib de Classe de Custo'!F21*'7Consumo Área - CALC'!F46 -> 0 | H29: ='14Distrib de Classe de Custo'!G21*'7Consumo Área - CALC'!G46 -> 0 | I29: ='14Distrib de Classe de Custo'!H21*'7Consumo Área - CALC'!H46 -> 0 | J29: ='14Distrib de Classe de Custo'!I21*'7Consumo Área - CALC'!I46 -> 0 | K29: ='14Distrib de Classe de Custo'!J21*'7Consumo Área - CALC'!J46 -> 0 | ... O29: ='14Distrib de Classe de Custo'!N21*'7Consumo Área - CALC'!N46 -> 0
B30: 50610003 | C30: Uso de Rede | D30: ='14Distrib de Classe de Custo'!C17*'7Consumo Área - CALC'!C46 -> 0 | E30: ='14Distrib de Classe de Custo'!D17*'7Consumo Área - CALC'!D46 -> 0 | F30: ='14Distrib de Classe de Custo'!E17*'7Consumo Área - CALC'!E46 -> 0 | G30: ='14Distrib de Classe de Custo'!F17*'7Consumo Área - CALC'!F46 -> 0 | H30: ='14Distrib de Classe de Custo'!G17*'7Consumo Área - CALC'!G46 -> 0 | I30: ='14Distrib de Classe de Custo'!H17*'7Consumo Área - CALC'!H46 -> 0 | J30: ='14Distrib de Classe de Custo'!I17*'7Consumo Área - CALC'!I46 -> 0 | K30: ='14Distrib de Classe de Custo'!J17*'7Consumo Área - CALC'!J46 -> 0 | ... O30: ='14Distrib de Classe de Custo'!N17*'7Consumo Área - CALC'!N46 -> 0
B31: 50610006 | C31: Encargo | D31: ='14Distrib de Classe de Custo'!C19*'7Consumo Área - CALC'!C46 -> 0 | E31: ='14Distrib de Classe de Custo'!D19*'7Consumo Área - CALC'!D46 -> 0 | F31: ='14Distrib de Classe de Custo'!E19*'7Consumo Área - CALC'!E46 -> 0 | G31: ='14Distrib de Classe de Custo'!F19*'7Consumo Área - CALC'!F46 -> 0 | H31: ='14Distrib de Classe de Custo'!G19*'7Consumo Área - CALC'!G46 -> 0 | I31: ='14Distrib de Classe de Custo'!H19*'7Consumo Área - CALC'!H46 -> 0 | J31: ='14Distrib de Classe de Custo'!I19*'7Consumo Área - CALC'!I46 -> 0 | K31: ='14Distrib de Classe de Custo'!J19*'7Consumo Área - CALC'!J46 -> 0 | ... O31: ='14Distrib de Classe de Custo'!N19*'7Consumo Área - CALC'!N46 -> 0
A32: 12111080 PREPARAÇÃO 2 | B32: 50610002 | C32: Consumo | D32: ='14Distrib de Classe de Custo'!C21*'7Consumo Área - CALC'!C47 -> 1616041.8 | E32: ='14Distrib de Classe de Custo'!D21*'7Consumo Área - CALC'!D47 -> 1552732.8 | F32: ='14Distrib de Classe de Custo'!E21*'7Consumo Área - CALC'!E47 -> 1634923.8 | G32: ='14Distrib de Classe de Custo'!F21*'7Consumo Área - CALC'!F47 -> 2216193.2 | H32: ='14Distrib de Classe de Custo'!G21*'7Consumo Área - CALC'!G47 -> 2298346.6 | I32: ='14Distrib de Classe de Custo'!H21*'7Consumo Área - CALC'!H47 -> 2559882.1 | J32: ='14Distrib de Classe de Custo'!I21*'7Consumo Área - CALC'!I47 -> 2765421.6 | K32: ='14Distrib de Classe de Custo'!J21*'7Consumo Área - CALC'!J47 -> 2431173 | ... O32: ='14Distrib de Classe de Custo'!N21*'7Consumo Área - CALC'!N47 -> 1798887.3
B33: 50610003 | C33: Uso de Rede | D33: ='14Distrib de Classe de Custo'!C17*'7Consumo Área - CALC'!C47 -> 721515.71 | E33: ='14Distrib de Classe de Custo'!D17*'7Consumo Área - CALC'!D47 -> 704061.19 | F33: ='14Distrib de Classe de Custo'!E17*'7Consumo Área - CALC'!E47 -> 719505.07 | G33: ='14Distrib de Classe de Custo'!F17*'7Consumo Área - CALC'!F47 -> 785537.73 | H33: ='14Distrib de Classe de Custo'!G17*'7Consumo Área - CALC'!G47 -> 808687.42 | I33: ='14Distrib de Classe de Custo'!H17*'7Consumo Área - CALC'!H47 -> 813762.01 | J33: ='14Distrib de Classe de Custo'!I17*'7Consumo Área - CALC'!I47 -> 934533.1 | K33: ='14Distrib de Classe de Custo'!J17*'7Consumo Área - CALC'!J47 -> 791953.52 | ... O33: ='14Distrib de Classe de Custo'!N17*'7Consumo Área - CALC'!N47 -> 746083.28
B34: 50610006 | C34: Encargo | D34: ='14Distrib de Classe de Custo'!C19*'7Consumo Área - CALC'!C47 -> 871630.24 | E34: ='14Distrib de Classe de Custo'!D19*'7Consumo Área - CALC'!D47 -> 702651.19 | F34: ='14Distrib de Classe de Custo'!E19*'7Consumo Área - CALC'!E47 -> 721737.95 | G34: ='14Distrib de Classe de Custo'!F19*'7Consumo Área - CALC'!F47 -> 901994.98 | H34: ='14Distrib de Classe de Custo'!G19*'7Consumo Área - CALC'!G47 -> 923605 | I34: ='14Distrib de Classe de Custo'!H19*'7Consumo Área - CALC'!H47 -> 1112442.1 | J34: ='14Distrib de Classe de Custo'!I19*'7Consumo Área - CALC'!I47 -> 1280960.2 | K34: ='14Distrib de Classe de Custo'!J19*'7Consumo Área - CALC'!J47 -> 1074230.8 | ... O34: ='14Distrib de Classe de Custo'!N19*'7Consumo Área - CALC'!N47 -> 849732.73
A35: 12133040 USINA 1 | B35: 50610002 | C35: Consumo | D35: ='14Distrib de Classe de Custo'!C21*'7Consumo Área - CALC'!C48 -> 0 | E35: ='14Distrib de Classe de Custo'!D21*'7Consumo Área - CALC'!D48 -> 0 | F35: ='14Distrib de Classe de Custo'!E21*'7Consumo Área - CALC'!E48 -> 0 | G35: ='14Distrib de Classe de Custo'!F21*'7Consumo Área - CALC'!F48 -> 0 | H35: ='14Distrib de Classe de Custo'!G21*'7Consumo Área - CALC'!G48 -> 0 | I35: ='14Distrib de Classe de Custo'!H21*'7Consumo Área - CALC'!H48 -> 0 | J35: ='14Distrib de Classe de Custo'!I21*'7Consumo Área - CALC'!I48 -> 0 | K35: ='14Distrib de Classe de Custo'!J21*'7Consumo Área - CALC'!J48 -> 0 | ... O35: ='14Distrib de Classe de Custo'!N21*'7Consumo Área - CALC'!N48 -> 0
B36: 50610003 | C36: Uso de Rede | D36: ='14Distrib de Classe de Custo'!C17*'7Consumo Área - CALC'!C48 -> 0 | E36: ='14Distrib de Classe de Custo'!D17*'7Consumo Área - CALC'!D48 -> 0 | F36: ='14Distrib de Classe de Custo'!E17*'7Consumo Área - CALC'!E48 -> 0 | G36: ='14Distrib de Classe de Custo'!F17*'7Consumo Área - CALC'!F48 -> 0 | H36: ='14Distrib de Classe de Custo'!G17*'7Consumo Área - CALC'!G48 -> 0 | I36: ='14Distrib de Classe de Custo'!H17*'7Consumo Área - CALC'!H48 -> 0 | J36: ='14Distrib de Classe de Custo'!I17*'7Consumo Área - CALC'!I48 -> 0 | K36: ='14Distrib de Classe de Custo'!J17*'7Consumo Área - CALC'!J48 -> 0 | ... O36: ='14Distrib de Classe de Custo'!N17*'7Consumo Área - CALC'!N48 -> 0
B37: 50610006 | C37: Encargo | D37: ='14Distrib de Classe de Custo'!C19*'7Consumo Área - CALC'!C48 -> 0 | E37: ='14Distrib de Classe de Custo'!D19*'7Consumo Área - CALC'!D48 -> 0 | F37: ='14Distrib de Classe de Custo'!E19*'7Consumo Área - CALC'!E48 -> 0 | G37: ='14Distrib de Classe de Custo'!F19*'7Consumo Área - CALC'!F48 -> 0 | H37: ='14Distrib de Classe de Custo'!G19*'7Consumo Área - CALC'!G48 -> 0 | I37: ='14Distrib de Classe de Custo'!H19*'7Consumo Área - CALC'!H48 -> 0 | J37: ='14Distrib de Classe de Custo'!I19*'7Consumo Área - CALC'!I48 -> 0 | K37: ='14Distrib de Classe de Custo'!J19*'7Consumo Área - CALC'!J48 -> 0 | ... O37: ='14Distrib de Classe de Custo'!N19*'7Consumo Área - CALC'!N48 -> 0
A38: 12135040 USINA 2 | B38: 50610002 | C38: Consumo | D38: ='14Distrib de Classe de Custo'!C21*'7Consumo Área - CALC'!C49 -> 0 | E38: ='14Distrib de Classe de Custo'!D21*'7Consumo Área - CALC'!D49 -> 0 | F38: ='14Distrib de Classe de Custo'!E21*'7Consumo Área - CALC'!E49 -> 0 | G38: ='14Distrib de Classe de Custo'!F21*'7Consumo Área - CALC'!F49 -> 0 | H38: ='14Distrib de Classe de Custo'!G21*'7Consumo Área - CALC'!G49 -> 0 | I38: ='14Distrib de Classe de Custo'!H21*'7Consumo Área - CALC'!H49 -> 0 | J38: ='14Distrib de Classe de Custo'!I21*'7Consumo Área - CALC'!I49 -> 0 | K38: ='14Distrib de Classe de Custo'!J21*'7Consumo Área - CALC'!J49 -> 0 | ... O38: ='14Distrib de Classe de Custo'!N21*'7Consumo Área - CALC'!N49 -> 0
B39: 50610003 | C39: Uso de Rede | D39: ='14Distrib de Classe de Custo'!C17*'7Consumo Área - CALC'!C49 -> 0 | E39: ='14Distrib de Classe de Custo'!D17*'7Consumo Área - CALC'!D49 -> 0 | F39: ='14Distrib de Classe de Custo'!E17*'7Consumo Área - CALC'!E49 -> 0 | G39: ='14Distrib de Classe de Custo'!F17*'7Consumo Área - CALC'!F49 -> 0 | H39: ='14Distrib de Classe de Custo'!G17*'7Consumo Área - CALC'!G49 -> 0 | I39: ='14Distrib de Classe de Custo'!H17*'7Consumo Área - CALC'!H49 -> 0 | J39: ='14Distrib de Classe de Custo'!I17*'7Consumo Área - CALC'!I49 -> 0 | K39: ='14Distrib de Classe de Custo'!J17*'7Consumo Área - CALC'!J49 -> 0 | ... O39: ='14Distrib de Classe de Custo'!N17*'7Consumo Área - CALC'!N49 -> 0
B40: 50610006 | C40: Encargo | D40: ='14Distrib de Classe de Custo'!C19*'7Consumo Área - CALC'!C49 -> 0 | E40: ='14Distrib de Classe de Custo'!D19*'7Consumo Área - CALC'!D49 -> 0 | F40: ='14Distrib de Classe de Custo'!E19*'7Consumo Área - CALC'!E49 -> 0 | G40: ='14Distrib de Classe de Custo'!F19*'7Consumo Área - CALC'!F49 -> 0 | H40: ='14Distrib de Classe de Custo'!G19*'7Consumo Área - CALC'!G49 -> 0 | I40: ='14Distrib de Classe de Custo'!H19*'7Consumo Área - CALC'!H49 -> 0 | J40: ='14Distrib de Classe de Custo'!I19*'7Consumo Área - CALC'!I49 -> 0 | K40: ='14Distrib de Classe de Custo'!J19*'7Consumo Área - CALC'!J49 -> 0 | ... O40: ='14Distrib de Classe de Custo'!N19*'7Consumo Área - CALC'!N49 -> 0
A41: 12136040 USINA 3 | B41: 50610002 | C41: Consumo | D41: ='14Distrib de Classe de Custo'!C21*'7Consumo Área - CALC'!C50 -> 1691204.2 | E41: ='14Distrib de Classe de Custo'!D21*'7Consumo Área - CALC'!D50 -> 1605311.7 | F41: ='14Distrib de Classe de Custo'!E21*'7Consumo Área - CALC'!E50 -> 1392629.4 | G41: ='14Distrib de Classe de Custo'!F21*'7Consumo Área - CALC'!F50 -> 2344078.3 | H41: ='14Distrib de Classe de Custo'!G21*'7Consumo Área - CALC'!G50 -> 2384910.9 | I41: ='14Distrib de Classe de Custo'!H21*'7Consumo Área - CALC'!H50 -> 2666053.2 | J41: ='14Distrib de Classe de Custo'!I21*'7Consumo Área - CALC'!I50 -> 2942663.4 | K41: ='14Distrib de Classe de Custo'!J21*'7Consumo Área - CALC'!J50 -> 2558874 | ... O41: ='14Distrib de Classe de Custo'!N21*'7Consumo Área - CALC'!N50 -> 1861813.9
B42: 50610003 | C42: Uso de Rede | D42: ='14Distrib de Classe de Custo'!C17*'7Consumo Área - CALC'!C50 -> 755073.56 | E42: ='14Distrib de Classe de Custo'!D17*'7Consumo Área - CALC'!D50 -> 727902.25 | F42: ='14Distrib de Classe de Custo'!E17*'7Consumo Área - CALC'!E50 -> 612875 | G42: ='14Distrib de Classe de Custo'!F17*'7Consumo Área - CALC'!F50 -> 830867.06 | H42: ='14Distrib de Classe de Custo'!G17*'7Consumo Área - CALC'!G50 -> 839145.61 | I42: ='14Distrib de Classe de Custo'!H17*'7Consumo Área - CALC'!H50 -> 847512.77 | J42: ='14Distrib de Classe de Custo'!I17*'7Consumo Área - CALC'!I50 -> 994429.34 | K42: ='14Distrib de Classe de Custo'!J17*'7Consumo Área - CALC'!J50 -> 833552.06 | ... O42: ='14Distrib de Classe de Custo'!N17*'7Consumo Área - CALC'!N50 -> 772181.92
B43: 50610006 | C43: Encargo | D43: ='14Distrib de Classe de Custo'!C19*'7Consumo Área - CALC'!C50 -> 912169.94 | E43: ='14Distrib de Classe de Custo'!D19*'7Consumo Área - CALC'!D50 -> 726444.5 | F43: ='14Distrib de Classe de Custo'!E19*'7Consumo Área - CALC'!E50 -> 614776.97 | G43: ='14Distrib de Classe de Custo'!F19*'7Consumo Área - CALC'!F50 -> 954044.46 | H43: ='14Distrib de Classe de Custo'!G19*'7Consumo Área - CALC'!G50 -> 958391.42 | I43: ='14Distrib de Classe de Custo'!H19*'7Consumo Área - CALC'!H50 -> 1158580.6 | J43: ='14Distrib de Classe de Custo'!I19*'7Consumo Área - CALC'!I50 -> 1363059.7 | K43: ='14Distrib de Classe de Custo'!J19*'7Consumo Área - CALC'!J50 -> 1130656.4 | ... O43: ='14Distrib de Classe de Custo'!N19*'7Consumo Área - CALC'!N50 -> 879457.12
A44: 12138040 USINA 4 | B44: 50610002 | C44: Consumo | D44: ='14Distrib de Classe de Custo'!C21*'7Consumo Área - CALC'!C51 -> 2270124.3 | E44: ='14Distrib de Classe de Custo'!D21*'7Consumo Área - CALC'!D51 -> 2078767.7 | F44: ='14Distrib de Classe de Custo'!E21*'7Consumo Área - CALC'!E51 -> 2637182.5 | G44: ='14Distrib de Classe de Custo'!F21*'7Consumo Área - CALC'!F51 -> 3142762.6 | H44: ='14Distrib de Classe de Custo'!G21*'7Consumo Área - CALC'!G51 -> 3098458.3 | I44: ='14Distrib de Classe de Custo'!H21*'7Consumo Área - CALC'!H51 -> 3700111.8 | J44: ='14Distrib de Classe de Custo'!I21*'7Consumo Área - CALC'!I51 -> 3949366.4 | K44: ='14Distrib de Classe de Custo'!J21*'7Consumo Área - CALC'!J51 -> 3317085.9 | ... O44: ='14Distrib de Classe de Custo'!N21*'7Consumo Área - CALC'!N51 -> 2574471.2
B45: 50610003 | C45: Uso de Rede | D45: ='14Distrib de Classe de Custo'!C17*'7Consumo Área - CALC'!C51 -> 1013544.6 | E45: ='14Distrib de Classe de Custo'!D17*'7Consumo Área - CALC'!D51 -> 942583.08 | F45: ='14Distrib de Classe de Custo'!E17*'7Consumo Área - CALC'!E51 -> 1160583.9 | G45: ='14Distrib de Classe de Custo'!F17*'7Consumo Área - CALC'!F51 -> 1113963.6 | H45: ='14Distrib de Classe de Custo'!G17*'7Consumo Área - CALC'!G51 -> 1090211.6 | I45: ='14Distrib de Classe de Custo'!H17*'7Consumo Área - CALC'!H51 -> 1176230.1 | J45: ='14Distrib de Classe de Custo'!I17*'7Consumo Área - CALC'!I51 -> 1334629.6 | K45: ='14Distrib de Classe de Custo'!J17*'7Consumo Área - CALC'!J51 -> 1080539.3 | ... O45: ='14Distrib de Classe de Custo'!N17*'7Consumo Área - CALC'!N51 -> 1067754.4
B46: 50610006 | C46: Encargo | D46: ='14Distrib de Classe de Custo'!C19*'7Consumo Área - CALC'!C51 -> 1224417 | E46: ='14Distrib de Classe de Custo'!D19*'7Consumo Área - CALC'!D51 -> 940695.4 | F46: ='14Distrib de Classe de Custo'!E19*'7Consumo Área - CALC'!E51 -> 1164185.6 | G46: ='14Distrib de Classe de Custo'!F19*'7Consumo Área - CALC'!F51 -> 1279110.5 | H46: ='14Distrib de Classe de Custo'!G19*'7Consumo Área - CALC'!G51 -> 1245134.9 | I46: ='14Distrib de Classe de Custo'!H19*'7Consumo Área - CALC'!H51 -> 1607949.1 | J46: ='14Distrib de Classe de Custo'!I19*'7Consumo Área - CALC'!I51 -> 1829370.7 | K46: ='14Distrib de Classe de Custo'!J19*'7Consumo Área - CALC'!J51 -> 1465677.6 | ... O46: ='14Distrib de Classe de Custo'!N19*'7Consumo Área - CALC'!N51 -> 1216092
A47: 12420080 ESTOC/EMBARQUE | B47: 50610002 | C47: Consumo | D47: ='14Distrib de Classe de Custo'!C21*'7Consumo Área - CALC'!C52 -> 110369.37 | E47: ='14Distrib de Classe de Custo'!D21*'7Consumo Área - CALC'!D52 -> 102709.74 | F47: ='14Distrib de Classe de Custo'!E21*'7Consumo Área - CALC'!E52 -> 111621.2 | G47: ='14Distrib de Classe de Custo'!F21*'7Consumo Área - CALC'!F52 -> 152875.93 | H47: ='14Distrib de Classe de Custo'!G21*'7Consumo Área - CALC'!G52 -> 152863.91 | I47: ='14Distrib de Classe de Custo'!H21*'7Consumo Área - CALC'!H52 -> 177268.43 | J47: ='14Distrib de Classe de Custo'!I21*'7Consumo Área - CALC'!I52 -> 192024.22 | K47: ='14Distrib de Classe de Custo'!J21*'7Consumo Área - CALC'!J52 -> 163814.88 | ... O47: ='14Distrib de Classe de Custo'!N21*'7Consumo Área - CALC'!N52 -> 123538.08
B48: 50610003 | C48: Uso de Rede | D48: ='14Distrib de Classe de Custo'!C17*'7Consumo Área - CALC'!C52 -> 49276.717 | E48: ='14Distrib de Classe de Custo'!D17*'7Consumo Área - CALC'!D52 -> 46572.046 | F48: ='14Distrib de Classe de Custo'!E17*'7Consumo Área - CALC'!E52 -> 49122.79 | G48: ='14Distrib de Classe de Custo'!F17*'7Consumo Área - CALC'!F52 -> 54187.427 | H48: ='14Distrib de Classe de Custo'!G17*'7Consumo Área - CALC'!G52 -> 53786.108 | I48: ='14Distrib de Classe de Custo'!H17*'7Consumo Área - CALC'!H52 -> 56351.936 | J48: ='14Distrib de Classe de Custo'!I17*'7Consumo Área - CALC'!I52 -> 64891.731 | K48: ='14Distrib de Classe de Custo'!J17*'7Consumo Área - CALC'!J52 -> 53362.623 | ... O48: ='14Distrib de Classe de Custo'!N17*'7Consumo Área - CALC'!N52 -> 51237.061
B49: 50610006 | C49: Encargo | D49: ='14Distrib de Classe de Custo'!C19*'7Consumo Área - CALC'!C52 -> 59528.956 | E49: ='14Distrib de Classe de Custo'!D19*'7Consumo Área - CALC'!D52 -> 46478.778 | F49: ='14Distrib de Classe de Custo'!E19*'7Consumo Área - CALC'!E52 -> 49275.236 | G49: ='14Distrib de Classe de Custo'!F19*'7Consumo Área - CALC'!F52 -> 62220.801 | H49: ='14Distrib de Classe de Custo'!G19*'7Consumo Área - CALC'!G52 -> 61429.32 | I49: ='14Distrib de Classe de Custo'!H19*'7Consumo Área - CALC'!H52 -> 77035.136 | J49: ='14Distrib de Classe de Custo'!I19*'7Consumo Área - CALC'!I52 -> 88946.795 | K49: ='14Distrib de Classe de Custo'!J19*'7Consumo Área - CALC'!J52 -> 72382.751 | ... O49: ='14Distrib de Classe de Custo'!N19*'7Consumo Área - CALC'!N52 -> 58355.158
A51: Total por Estado/Classe de Custo
A52: Estado | B52: Classe de Custo | C52: Tipo | D52: Jan | E52: Fev | F52: Mar | G52: Abr | H52: Mai | I52: Jun | J52: Jul | K52: Ago | L52: Set | M52: Out | N52: Nov | O52: Dez
A53: MG | B53: 50610002 | C53: Consumo | D53: =SUM(D4+D7+D10+D13+D16+D19+D22+D25) -> 7563933.2 | E53: =SUM(E4+E7+E10+E13+E16+E19+E22+E25) -> 7887568.4 | F53: =SUM(F4+F7+F10+F13+F16+F19+F22+F25) -> 7639137.8 | G53: =SUM(G4+G7+G10+G13+G16+G19+G22+G25) -> 7641084.7 | H53: =SUM(H4+H7+H10+H13+H16+H19+H22+H25) -> 7633803.4 | I53: =SUM(I4+I7+I10+I13+I16+I19+I22+I25) -> 8690418.3 | J53: =SUM(J4+J7+J10+J13+J16+J19+J22+J25) -> 9175084 | K53: =SUM(K4+K7+K10+K13+K16+K19+K22+K25) -> 9236043.7 | ... O53: =SUM(O4+O7+O10+O13+O16+O19+O22+O25) -> 8158763.8
B54: 50610003 | C54: Uso de Rede | D54: =SUM(D5+D8+D11+D14+D17+D20+D23+D26) -> 1904913 | E54: =SUM(E5+E8+E11+E14+E17+E20+E23+E26) -> 1895682.1 | F54: =SUM(F5+F8+F11+F14+F17+F20+F23+F26) -> 1914814.7 | G54: =SUM(G5+G8+G11+G14+G17+G20+G23+G26) -> 1921501.8 | H54: =SUM(H5+H8+H11+H14+H17+H20+H23+H26) -> 1927313.7 | I54: =SUM(I5+I8+I11+I14+I17+I20+I23+I26) -> 1933395.6 | J54: =SUM(J5+J8+J11+J14+J17+J20+J23+J26) -> 2302594.6 | K54: =SUM(K5+K8+K11+K14+K17+K20+K23+K26) -> 2289936.9 | ... O54: =SUM(O5+O8+O11+O14+O17+O20+O23+O26) -> 2276529.1
B55: 50610006 | C55: Encargo | D55: =SUM(D6+D9+D12+D15+D18+D21+D24+D27) -> 2980747.6 | E55: =SUM(E6+E9+E12+E15+E18+E21+E24+E27) -> 3114499.8 | F55: =SUM(F6+F9+F12+F15+F18+F21+F24+F27) -> 3018749.9 | G55: =SUM(G6+G9+G12+G15+G18+G21+G24+G27) -> 3022154.4 | H55: =SUM(H6+H9+H12+H15+H18+H21+H24+H27) -> 3021310.7 | I55: =SUM(I6+I9+I12+I15+I18+I21+I24+I27) -> 3119944.1 | J55: =SUM(J6+J9+J12+J15+J18+J21+J24+J27) -> 3431335.5 | K55: =SUM(K6+K9+K12+K15+K18+K21+K24+K27) -> 3445736.4 | ... O55: =SUM(O6+O9+O12+O15+O18+O21+O24+O27) -> 3027821.5
A56: TOTAL | D56: =SUM(D53:D55) -> 12449594 | E56: =SUM(E53:E55) -> 12897750 | F56: =SUM(F53:F55) -> 12572702 | G56: =SUM(G53:G55) -> 12584741 | H56: =SUM(H53:H55) -> 12582428 | I56: =SUM(I53:I55) -> 13743758 | J56: =SUM(J53:J55) -> 14909014 | K56: =SUM(K53:K55) -> 14971717 | ... O56: =SUM(O53:O55) -> 13463114
A57: ES | B57: 50610002 | C57: Consumo | D57: =D29+D32+D35+D38+D41+D44+D47 -> 5687739.7 | E57: =E29+E32+E35+E38+E41+E44+E47 -> 5339521.9 | F57: =F29+F32+F35+F38+F41+F44+F47 -> 5776356.9 | G57: =G29+G32+G35+G38+G41+G44+G47 -> 7855910.1 | H57: =H29+H32+H35+H38+H41+H44+H47 -> 7934579.7 | I57: =I29+I32+I35+I38+I41+I44+I47 -> 9103315.6 | J57: =J29+J32+J35+J38+J41+J44+J47 -> 9849475.6 | K57: =K29+K32+K35+K38+K41+K44+K47 -> 8470947.8 | ... O57: =O29+O32+O35+O38+O41+O44+O47 -> 6358710.5
B58: 50610003 | C58: Uso de Rede | D58: =D30+D33+D36+D39+D42+D45+D48 -> 2539410.6 | E58: =E30+E33+E36+E39+E42+E45+E48 -> 2421118.6 | F58: =F30+F33+F36+F39+F42+F45+F48 -> 2542086.7 | G58: =G30+G33+G36+G39+G42+G45+G48 -> 2784555.8 | H58: =H30+H33+H36+H39+H42+H45+H48 -> 2791830.8 | I58: =I30+I33+I36+I39+I42+I45+I48 -> 2893856.8 | J58: =J30+J33+J36+J39+J42+J45+J48 -> 3328483.8 | K58: =K30+K33+K36+K39+K42+K45+K48 -> 2759407.5 | ... O58: =O30+O33+O36+O39+O42+O45+O48 -> 2637256.7
B59: 50610006 | C59: Encargo | D59: =D31+D34+D37+D40+D43+D46+D49 -> 3067746.1 | E59: =E31+E34+E37+E40+E43+E46+E49 -> 2416269.9 | F59: =F31+F34+F37+F40+F43+F46+F49 -> 2549975.7 | G59: =G31+G34+G37+G40+G43+G46+G49 -> 3197370.7 | H59: =H31+H34+H37+H40+H43+H46+H49 -> 3188560.6 | I59: =I31+I34+I37+I40+I43+I46+I49 -> 3956007.1 | J59: =J31+J34+J37+J40+J43+J46+J49 -> 4562337.4 | K59: =K31+K34+K37+K40+K43+K46+K49 -> 3742947.6 | ... O59: =O31+O34+O37+O40+O43+O46+O49 -> 3003637
A60: TOTAL | D60: =SUM(D57:D59) -> 11294896 | E60: =SUM(E57:E59) -> 10176910 | F60: =SUM(F57:F59) -> 10868419 | G60: =SUM(G57:G59) -> 13837837 | H60: =SUM(H57:H59) -> 13914971 | I60: =SUM(I57:I59) -> 15953179 | J60: =SUM(J57:J59) -> 17740297 | K60: =SUM(K57:K59) -> 14973303 | ... O60: =SUM(O57:O59) -> 11999604
A62: Total por Classe de Custo
A63: Estado | B63: Classe de Custo | C63: Tipo | D63: Jan | E63: Fev | F63: Mar | G63: Abr | H63: Mai | I63: Jun | J63: Jul | K63: Ago | L63: Set | M63: Out | N63: Nov | O63: Dez
A64: Samarco | B64: 50610002 | C64: Consumo | D64: =D53+D57 -> 13251673 | E64: =E53+E57 -> 13227090 | F64: =F53+F57 -> 13415495 | G64: =G53+G57 -> 15496995 | H64: =H53+H57 -> 15568383 | I64: =I53+I57 -> 17793734 | J64: =J53+J57 -> 19024560 | K64: =K53+K57 -> 17706992 | ... O64: =O53+O57 -> 14517474
B65: 50610003 | C65: Uso de Rede | D65: =D54+D58 -> 4444323.6 | E65: =E54+E58 -> 4316800.7 | F65: =F54+F58 -> 4456901.5 | G65: =G54+G58 -> 4706057.6 | H65: =H54+H58 -> 4719144.5 | I65: =I54+I58 -> 4827252.4 | J65: =J54+J58 -> 5631078.5 | K65: =K54+K58 -> 5049344.4 | ... O65: =O54+O58 -> 4913785.8
B66: 50610006 | C66: Encargo | D66: =D55+D59 -> 6048493.7 | E66: =E55+E59 -> 5530769.6 | F66: =F55+F59 -> 5568725.6 | G66: =G55+G59 -> 6219525.1 | H66: =H55+H59 -> 6209871.3 | I66: =I55+I59 -> 7075951.2 | J66: =J55+J59 -> 7993672.9 | K66: =K55+K59 -> 7188684.1 | ... O66: =O55+O59 -> 6031458.5
A67: TOTAL | D67: =SUM(D64:D66) -> 23744490 | E67: =SUM(E64:E66) -> 23074661 | F67: =SUM(F64:F66) -> 23441122 | G67: =SUM(G64:G66) -> 26422578 | H67: =SUM(H64:H66) -> 26497399 | I67: =SUM(I64:I66) -> 29696938 | J67: =SUM(J64:J66) -> 32649311 | K67: =SUM(K64:K66) -> 29945020 | ... O67: =SUM(O64:O66) -> 25462718

Sheet 16Resumo GERAL
A1: RESUMO GERAL
A2: Classe Custo | B2: Tipo | C2: Jan | D2: Fev | E2: Mar | F2: Abr | G2: Mai | H2: Jun | I2: Jul | J2: Ago | K2: Set | L2: Out | M2: Nov | N2: Dez | O2: Total Anual Planejado
A3: 50610002 | B3: Consumo | C3: ='15Distrib Centro de Custos'!D64 -> 13251673 | D3: ='15Distrib Centro de Custos'!E64 -> 13227090 | E3: ='15Distrib Centro de Custos'!F64 -> 13415495 | F3: ='15Distrib Centro de Custos'!G64 -> 15496995 | G3: ='15Distrib Centro de Custos'!H64 -> 15568383 | H3: ='15Distrib Centro de Custos'!I64 -> 17793734 | I3: ='15Distrib Centro de Custos'!J64 -> 19024560 | J3: ='15Distrib Centro de Custos'!K64 -> 17706992 | ... N3: ='15Distrib Centro de Custos'!O64 -> 14517474 | O3: =SUM(C3:N3) -> 1.9096419e+08
A4: 50610003 | B4: Uso de Rede | C4: ='15Distrib Centro de Custos'!D65 -> 4444323.6 | D4: ='15Distrib Centro de Custos'!E65 -> 4316800.7 | E4: ='15Distrib Centro de Custos'!F65 -> 4456901.5 | F4: ='15Distrib Centro de Custos'!G65 -> 4706057.6 | G4: ='15Distrib Centro de Custos'!H65 -> 4719144.5 | H4: ='15Distrib Centro de Custos'!I65 -> 4827252.4 | I4: ='15Distrib Centro de Custos'!J65 -> 5631078.5 | J4: ='15Distrib Centro de Custos'!K65 -> 5049344.4 | ... N4: ='15Distrib Centro de Custos'!O65 -> 4913785.8 | O4: =SUM(C4:N4) -> 58051648
A5: 50610006 | B5: Encargo | C5: ='15Distrib Centro de Custos'!D66 -> 6048493.7 | D5: ='15Distrib Centro de Custos'!E66 -> 5530769.6 | E5: ='15Distrib Centro de Custos'!F66 -> 5568725.6 | F5: ='15Distrib Centro de Custos'!G66 -> 6219525.1 | G5: ='15Distrib Centro de Custos'!H66 -> 6209871.3 | H5: ='15Distrib Centro de Custos'!I66 -> 7075951.2 | I5: ='15Distrib Centro de Custos'!J66 -> 7993672.9 | J5: ='15Distrib Centro de Custos'!K66 -> 7188684.1 | ... N5: ='15Distrib Centro de Custos'!O66 -> 6031458.5 | O5: =SUM(C5:N5) -> 78553231
A6: 50610007 | B6: EER | C6: ='12Encargos ESS EER - CALC'!C6 -> 1152969.1 | D6: ='12Encargos ESS EER - CALC'!D6 -> 1426554.7 | E6: ='12Encargos ESS EER - CALC'!E6 -> 1577533.8 | F6: ='12Encargos ESS EER - CALC'!F6 -> 1799304.1 | G6: ='12Encargos ESS EER - CALC'!G6 -> 1816934.3 | H6: ='12Encargos ESS EER - CALC'!H6 -> 1545255.8 | I6: ='12Encargos ESS EER - CALC'!I6 -> 1835553.7 | J6: ='12Encargos ESS EER - CALC'!J6 -> 1605047.8 | ... N6: ='12Encargos ESS EER - CALC'!N6 -> 1606611.1 | O6: =SUM(C6:N6) -> 18963288
A7: 50610008 | B7: LiqFin_ESS | C7: ='12Encargos ESS EER - CALC'!C8 -> 239031.34 | D7: ='12Encargos ESS EER - CALC'!D8 -> 16706.842 | E7: ='12Encargos ESS EER - CALC'!E8 -> 122025.51 | F7: ='12Encargos ESS EER - CALC'!F8 -> 60221.044 | G7: ='12Encargos ESS EER - CALC'!G8 -> 31621.843 | H7: ='12Encargos ESS EER - CALC'!H8 -> 90050.56 | I7: ='12Encargos ESS EER - CALC'!I8 -> 443445.86 | J7: ='12Encargos ESS EER - CALC'!J8 -> 748393.25 | ... N7: ='12Encargos ESS EER - CALC'!N8 -> 178790.93 | O7: =SUM(C7:N7) -> 3532032.9
A8: 50620002 | B8: Royalties ANEEL | C8: 241214.44 | D8: 368746.25 | E8: 391217.36 | F8: 336157.11 | G8: 347984.39 | H8: 264024.71 | I8: 238093.51 | J8: 174321.07 | K8: 151424.99 | L8: 141787.8 | M8: 138058.49 | N8: 179222.39 | O8: =SUM(C8:N8) -> 2972252.5
A9: 50620003 | B9: Serv de Transm de EE | C9: 665774.26 | D9: 665774.26 | E9: 665774.26 | F9: 665774.26 | G9: 665774.26 | H9: 665774.26 | I9: 719482.69 | J9: 719482.69 | K9: 719482.69 | L9: 719482.69 | M9: 719482.69 | N9: 719482.69 | O9: =SUM(C9:N9) -> 8311541.7
A10: 50620004 | B10: Serv de Oper de Hidrelétricas | C10: 1178695.9 | D10: 1226507.2 | E10: 1371448 | F10: 1491723.9 | G10: 1540771.1 | H10: 1674148.6 | I10: 1521470.8 | J10: 1806129.9 | K10: 1755559 | L10: 1710922.7 | M10: 1330109.7 | N10: 1234823.8 | O10: =SUM(C10:N10) -> 17842311
A11: 50620099 | B11: Outras despesas Hidreletricas | C11: 203645.69 | D11: 203645.69 | E11: 203645.69 | F11: 203645.69 | G11: 203645.69 | H11: 203645.69 | I11: 203645.69 | J11: 203645.69 | K11: 203645.69 | L11: 203645.69 | M11: 203645.69 | N11: 203645.69 | O11: =SUM(C11:N11) -> 2443748.3
A12: 50630001 | B12: O&M Rede Basica | C12: 334059.96 | D12: 334059.96 | E12: 334059.96 | F12: 454060 | G12: 414060 | H12: 414060 | I12: 334059.96 | J12: 334059.96 | K12: 334059.96 | L12: 334059.96 | M12: 334059.96 | N12: 334059.96 | O12: =SUM(C12:N12) -> 4288719.6
A13: 50630099 | B13: Outras despesas RB | C13: 25000 | D13: 25000 | E13: 25000 | F13: 25000 | G13: 25000 | H13: 25000 | I13: 25000 | J13: 25000 | K13: 25000 | L13: 25000 | M13: 25000 | N13: 25000 | O13: =SUM(C13:N13) -> 300000
A14: 50610005 | B14: Energ. Administr. | C14: 108333 | D14: =C14 -> 108333 | E14: =D14 -> 108333 | F14: =E14 -> 108333 | G14: =F14 -> 108333 | H14: =G14 -> 108333 | I14: =H14 -> 108333 | J14: =I14 -> 108333 | K14: =J14 -> 108333 | ... N14: =M14 -> 108333 | O14: =SUM(C14:N14) -> 1299996
A15: 50610099 | B15: Outros Custos EE | C15: 772738.24 | D15: 235785.28 | E15: 235785.28 | F15: 235785.28 | G15: 331560.28 | H15: 331560.28 | I15: 331560.28 | J15: 331560.28 | K15: 331560.28 | L15: =331560.28+380000 -> 711560.28 | M15: 331560.28 | N15: 331560.28 | O15: =SUM(C15:N15) -> 4512576.3
A16: Total Geral | C16: =SUM(C3:C15) -> 28665952 | D16: =SUM(D3:D15) -> 27685774 | E16: =SUM(E3:E15) -> 28475945 | F16: =SUM(F3:F15) -> 31802582 | G16: =SUM(G3:G15) -> 31983084 | H16: =SUM(H3:H15) -> 35018790 | I16: =SUM(I3:I15) -> 38409956 | J16: =SUM(J3:J15) -> 36000994 | ... N16: =SUM(N3:N15) -> 30384248 | O16: =SUM(C16:N16) -> 3.9203553e+08
A18: Produção
A19: Produto | B19: Unidade | C19: Jan | D19: Fev | E19: Mar | F19: Abr | G19: Mai | H19: Jun | I19: Jul | J19: Ago | K19: Set | L19: Out | M19: Nov | N19: Dez | O19: Total Anual Planejado
A20: Pelotas | B20: tms | C20: =SUM('4Produção - OCULTA'!B12:B15) -> 1067228.4 | D20: =SUM('4Produção - OCULTA'!C12:C15) -> 1008651 | E20: =SUM('4Produção - OCULTA'!D12:D15) -> 1063894.7 | F20: =SUM('4Produção - OCULTA'!E12:E15) -> 1173583.9 | G20: =SUM('4Produção - OCULTA'!F12:F15) -> 1164892.2 | H20: =SUM('4Produção - OCULTA'!G12:G15) -> 1220462.6 | I20: =SUM('4Produção - OCULTA'!H12:H15) -> 1260424.8 | J20: =SUM('4Produção - OCULTA'!I12:I15) -> 1163640.3 | ... N20: =SUM('4Produção - OCULTA'!M12:M15) -> 1117289.7 | O20: =SUM(C20:N20) -> 13682103
A21: Pellet Feed (embarque) | B21: tms | C21: ='4Produção - OCULTA'!B18 -> 385926.88 | D21: ='4Produção - OCULTA'!C18 -> 385926.88 | E21: ='4Produção - OCULTA'!D18 -> 385926.88 | F21: ='4Produção - OCULTA'!E18 -> 385926.88 | G21: ='4Produção - OCULTA'!F18 -> 385926.88 | H21: ='4Produção - OCULTA'!G18 -> 385926.88 | I21: ='4Produção - OCULTA'!H18 -> 385926.88 | J21: ='4Produção - OCULTA'!I18 -> 385926.88 | ... N21: ='4Produção - OCULTA'!M18 -> 385926.88 | O21: =SUM(C21:N21) -> 4631122.6
A22: PSC + PSM | B22: tms | C22: ='4Produção - OCULTA'!B17 -> 143855.06 | D22: ='4Produção - OCULTA'!C17 -> 174652.86 | E22: ='4Produção - OCULTA'!D17 -> 143825.05 | F22: ='4Produção - OCULTA'!E17 -> 144812.26 | G22: ='4Produção - OCULTA'!F17 -> 193959.03 | H22: ='4Produção - OCULTA'!G17 -> 145234.16 | I22: ='4Produção - OCULTA'!H17 -> 145593.82 | J22: ='4Produção - OCULTA'!I17 -> 176047.76 | ... N22: ='4Produção - OCULTA'!M17 -> 144305.61 | O22: =SUM(C22:N22) -> 1895238.9
A23: TOTAL | C23: =SUM(C20:C22) -> 1597010.4 | D23: =SUM(D20:D22) -> 1569230.8 | E23: =SUM(E20:E22) -> 1593646.6 | F23: =SUM(F20:F22) -> 1704323.1 | G23: =SUM(G20:G22) -> 1744778.1 | H23: =SUM(H20:H22) -> 1751623.6 | I23: =SUM(I20:I22) -> 1791945.6 | J23: =SUM(J20:J22) -> 1725614.9 | ... N23: =SUM(N20:N22) -> 1647522.2 | O23: =SUM(C23:N23) -> 20208464
A24: Custo Especifico de Energia Elétrica | C24: =C16/C23 -> 17.949759 | D24: =D16/D23 -> 17.642895 | E24: =E16/E23 -> 17.868418 | F24: =F16/F23 -> 18.659949 | G24: =G16/G23 -> 18.330746 | H24: =H16/H23 -> 19.992189 | I24: =I16/I23 -> 21.434779 | J24: =J16/J23 -> 20.862704 | ... O24: =O16/O23 -> 19.399571
C26: Jan | D26: Fev | E26: Mar | F26: Abr | G26: Mai | H26: Jun | I26: Jul | J26: Ago | K26: Set | L26: Out | M26: Nov | N26: Dez | O26: Total Anual Planejado
A27: Custo Fixo | B27: R$ | C27: =C4+C8+C9+C10+C11+C12+C13+C14+C15 -> 7973785.1 | D27: =D4+D8+D9+D10+D11+D12+D13+D14+D15 -> 7484652.3 | E27: =E4+E8+E9+E10+E11+E12+E13+E14+E15 -> 7792165 | F27: =F4+F8+F9+F10+F11+F12+F13+F14+F15 -> 8226536.9 | G27: =G4+G8+G9+G10+G11+G12+G13+G14+G15 -> 8356273.3 | H27: =H4+H8+H9+H10+H11+H12+H13+H14+H15 -> 8513799 | I27: =I4+I8+I9+I10+I11+I12+I13+I14+I15 -> 9112724.4 | J27: =J4+J8+J9+J10+J11+J12+J13+J14+J15 -> 8751877 | ... N27: =N4+N8+N9+N10+N11+N12+N13+N14+N15 -> 8049913.6 | O27: =SUM(C27:N27) -> 1.0002279e+08
B28: R$/tms | C28: =C27/C23 -> 4.9929451 | D28: =D27/D23 -> 4.7696313 | E28: =E27/E23 -> 4.8895187 | F28: =F27/F23 -> 4.8268648 | G28: =G27/G23 -> 4.7893042 | H28: =H27/H23 -> 4.8605185 | I28: =I27/I23 -> 5.0853802 | J28: =J27/J23 -> 5.0717439 | ... O28: =O27/O23 -> 4.9495494
A29: Custo Variável | B29: R$ | C29: =C3+C5+C6+C7 -> 20692167 | D29: =D3+D5+D6+D7 -> 20201121 | E29: =E3+E5+E6+E7 -> 20683780 | F29: =F3+F5+F6+F7 -> 23576045 | G29: =G3+G5+G6+G7 -> 23626810 | H29: =H3+H5+H6+H7 -> 26504991 | I29: =I3+I5+I6+I7 -> 29297232 | J29: =J3+J5+J6+J7 -> 27249117 | ... N29: =N3+N5+N6+N7 -> 22334335 | O29: =SUM(C29:N29) -> 2.9201274e+08
B30: R$/tms | C30: =C29/C23 -> 12.956814 | D30: =D29/D23 -> 12.873264 | E30: =E29/E23 -> 12.9789 | F30: =F29/F23 -> 13.833085 | G30: =G29/G23 -> 13.541441 | H30: =H29/H23 -> 15.131671 | I30: =I29/I23 -> 16.349399 | J30: =J29/J23 -> 15.79096 | ... O30: =O29/O23 -> 14.450021

Sheet Areas Envolvidas
B1: Consultoria | C1: Infra | D1: UHE Guilman | E1: Suprimentos | F1: Manutenção | G1: Produção | H1: Planjemento Integrado
A2: Tarifas | B2: X
A3: Plano de Produção | H3: X
A4: Consumo Especifico | G4: X
A5: Demanda | F5: X
A6: O&M de Muniz Freire | C6: X
A7: O&M de Guilman | D7: X
A8: Auto Produção | C8: X | D8: X
A9: Despesas com RB | C9: X
A10: Outros Custos com EE | E10: X
